Workbook
Name bin_lbl: Pivots!$A$66:$A$72
Name bin_lo: Pivots!$B$66:$B$72
Name c_nb: Analysis!$B$81
Name c_pt: Analysis!$B$82
Name d_age: Data_Clean!$U$2:$U$251
Name d_band: Data_Clean!$V$2:$V$251
Name d_baths: Data_Clean!$F$2:$F$251
Name d_beds: Data_Clean!$E$2:$E$251
Name d_comm: Data_Clean!$O$2:$O$251
Name d_commusd: Data_Clean!$T$2:$T$251
Name d_cond: Data_Clean!$K$2:$K$251
Name d_date: Data_Clean!$B$2:$B$251
Name d_diff: Data_Clean!$S$2:$S$251
Name d_dom: Data_Clean!$N$2:$N$251
Name d_flag: Data_Clean!$W$2:$W$251
Name d_garage: Data_Clean!$J$2:$J$251
Name d_id: Data_Clean!$A$2:$A$251
Name d_list: Data_Clean!$L$2:$L$251
Name d_lot: Data_Clean!$H$2:$H$251
Name d_month: Data_Clean!$P$2:$P$251
Name d_nbhd: Data_Clean!$C$2:$C$251
Name d_notes: Data_Clean!$X$2:$X$251
Name d_price: Data_Clean!$M$2:$M$251
Name d_psf: Data_Clean!$Q$2:$Q$251
Name d_sqft: Data_Clean!$G$2:$G$251
Name d_stl: Data_Clean!$R$2:$R$251
Name d_type: Data_Clean!$D$2:$D$251
Name d_year: Data_Clean!$I$2:$I$251
Name f_dom_hi: Analysis!$F$23
Name f_price_hi: Analysis!$F$22
Name f_psf_hi: Analysis!$F$24
Name f_psf_lo: Analysis!$E$24

Sheet Pivots
A1: PIVOT TABLES — live, formula-driven summaries of Data_Clean
A2: Every cell is a SUMIFS / COUNTIFS / AVERAGEIFS / MEDIAN(IF()) formula on the cleaned data, so all tables (and the dashboard charts built on them) refresh when Data_Clean changes. Blue = editable inputs.
A4: 1 ▸ BY NEIGHBORHOOD
A5: Neighborhood | B5: Sales | C5: % of Sales | D5: Volume ($) | E5: Avg Price | F5: Median Price | G5: Avg $/sqft | H5: Avg DOM | I5: Avg Sale-to-List | J5: Avg Commission %
A6: Cedar Park | B6: =COUNTIFS(d_nbhd,$A6) -> 39 | C6: =B6/B$12 -> 0.156 | D6: =SUMIFS(d_price,d_nbhd,$A6) -> 11140000 | E6: =IFERROR(AVERAGEIFS(d_price,d_nbhd,$A6),"") -> 285641.03 | F6: {=IFERROR(MEDIAN(IF(d_nbhd=$A6,d_price)),"")} -> 306000 | G6: =IFERROR(AVERAGEIFS(d_psf,d_nbhd,$A6),"") -> 172.14713 | H6: =IFERROR(AVERAGEIFS(d_dom,d_nbhd,$A6),"") -> 67.578947 | I6: =IFERROR(AVERAGEIFS(d_stl,d_nbhd,$A6),"") -> 0.97450341 | J6: =IFERROR(AVERAGEIFS(d_comm,d_nbhd,$A6),"") -> 2.9064865
A7: Downtown | B7: =COUNTIFS(d_nbhd,$A7) -> 36 | C7: =B7/B$12 -> 0.144 | D7: =SUMIFS(d_price,d_nbhd,$A7) -> 15479000 | E7: =IFERROR(AVERAGEIFS(d_price,d_nbhd,$A7),"") -> 429972.22 | F7: {=IFERROR(MEDIAN(IF(d_nbhd=$A7,d_price)),"")} -> 407000 | G7: =IFERROR(AVERAGEIFS(d_psf,d_nbhd,$A7),"") -> 296.95506 | H7: =IFERROR(AVERAGEIFS(d_dom,d_nbhd,$A7),"") -> 52.777778 | I7: =IFERROR(AVERAGEIFS(d_stl,d_nbhd,$A7),"") -> 0.97717766 | J7: =IFERROR(AVERAGEIFS(d_comm,d_nbhd,$A7),"") -> 2.8785714
A8: Maple Heights | B8: =COUNTIFS(d_nbhd,$A8) -> 51 | C8: =B8/B$12 -> 0.204 | D8: =SUMIFS(d_price,d_nbhd,$A8) -> 17166000 | E8: =IFERROR(AVERAGEIFS(d_price,d_nbhd,$A8),"") -> 336588.24 | F8: {=IFERROR(MEDIAN(IF(d_nbhd=$A8,d_price)),"")} -> 339000 | G8: =IFERROR(AVERAGEIFS(d_psf,d_nbhd,$A8),"") -> 193.36796 | H8: =IFERROR(AVERAGEIFS(d_dom,d_nbhd,$A8),"") -> 54.170213 | I8: =IFERROR(AVERAGEIFS(d_stl,d_nbhd,$A8),"") -> 0.97104751 | J8: =IFERROR(AVERAGEIFS(d_comm,d_nbhd,$A8),"") -> 2.9588636
A9: Oak Hill | B9: =COUNTIFS(d_nbhd,$A9) -> 58 | C9: =B9/B$12 -> 0.232 | D9: =SUMIFS(d_price,d_nbhd,$A9) -> 28572000 | E9: =IFERROR(AVERAGEIFS(d_price,d_nbhd,$A9),"") -> 492620.69 | F9: {=IFERROR(MEDIAN(IF(d_nbhd=$A9,d_price)),"")} -> 450500 | G9: =IFERROR(AVERAGEIFS(d_psf,d_nbhd,$A9),"") -> 252.82582 | H9: =IFERROR(AVERAGEIFS(d_dom,d_nbhd,$A9),"") -> 58.142857 | I9: =IFERROR(AVERAGEIFS(d_stl,d_nbhd,$A9),"") -> 0.97342954 | J9: =IFERROR(AVERAGEIFS(d_comm,d_nbhd,$A9),"") -> 2.9075439
A10: Riverside | B10: =COUNTIFS(d_nbhd,$A10) -> 62 | C10: =B10/B$12 -> 0.248 | D10: =SUMIFS(d_price,d_nbhd,$A10) -> 23755000 | E10: =IFERROR(AVERAGEIFS(d_price,d_nbhd,$A10),"") -> 383145.16 | F10: {=IFERROR(MEDIAN(IF(d_nbhd=$A10,d_price)),"")} -> 381500 | G10: =IFERROR(AVERAGEIFS(d_psf,d_nbhd,$A10),"") -> 221.25059 | H10: =IFERROR(AVERAGEIFS(d_dom,d_nbhd,$A10),"") -> 54.770492 | I10: =IFERROR(AVERAGEIFS(d_stl,d_nbhd,$A10),"") -> 0.97690998 | J10: =IFERROR(AVERAGEIFS(d_comm,d_nbhd,$A10),"") -> 2.9426316
A11: Unknown | B11: =COUNTIFS(d_nbhd,$A11) -> 4 | C11: =B11/B$12 -> 0.016 | D11: =SUMIFS(d_price,d_nbhd,$A11) -> 1488000 | E11: =IFERROR(AVERAGEIFS(d_price,d_nbhd,$A11),"") -> 372000 | F11: {=IFERROR(MEDIAN(IF(d_nbhd=$A11,d_price)),"")} -> 333000 | G11: =IFERROR(AVERAGEIFS(d_psf,d_nbhd,$A11),"") -> 207.19019 | H11: =IFERROR(AVERAGEIFS(d_dom,d_nbhd,$A11),"") -> 68.25 | I11: =IFERROR(AVERAGEIFS(d_stl,d_nbhd,$A11),"") -> 0.99839829 | J11: =IFERROR(AVERAGEIFS(d_comm,d_nbhd,$A11),"") -> 3
A12: Grand Total | B12: =SUM(B6:B11) -> 250 | C12: =SUM(C6:C11) -> 1 | D12: =SUM(D6:D11) -> 97600000 | E12: =AVERAGE(d_price) -> 390400 | F12: =MEDIAN(d_price) -> 366000 | G12: =AVERAGE(d_psf) -> 225.90432 | H12: =AVERAGE(d_dom) -> 57.371901 | I12: =AVERAGE(d_stl) -> 0.97491351 | J12: =AVERAGE(d_comm) -> 2.9224893
A14: 2 ▸ BY PROPERTY TYPE
A15: Property Type | B15: Sales | C15: % of Sales | D15: Volume ($) | E15: Avg Price | F15: Median Price | G15: Avg $/sqft | H15: Avg DOM | I15: Avg Sale-to-List | J15: Avg Commission %
A16: Condo | B16: =COUNTIFS(d_type,$A16) -> 57 | C16: =B16/B$19 -> 0.228 | D16: =SUMIFS(d_price,d_type,$A16) -> 15297000 | E16: =IFERROR(AVERAGEIFS(d_price,d_type,$A16),"") -> 268368.42 | F16: {=IFERROR(MEDIAN(IF(d_type=$A16,d_price)),"")} -> 263000 | G16: =IFERROR(AVERAGEIFS(d_psf,d_type,$A16),"") -> 235.81426 | H16: =IFERROR(AVERAGEIFS(d_dom,d_type,$A16),"") -> 59.636364 | I16: =IFERROR(AVERAGEIFS(d_stl,d_type,$A16),"") -> 0.97307063 | J16: =IFERROR(AVERAGEIFS(d_comm,d_type,$A16),"") -> 2.9592157
A17: Single Family | B17: =COUNTIFS(d_type,$A17) -> 146 | C17: =B17/B$19 -> 0.584 | D17: =SUMIFS(d_price,d_type,$A17) -> 66076000 | E17: =IFERROR(AVERAGEIFS(d_price,d_type,$A17),"") -> 452575.34 | F17: {=IFERROR(MEDIAN(IF(d_type=$A17,d_price)),"")} -> 428500 | G17: =IFERROR(AVERAGEIFS(d_psf,d_type,$A17),"") -> 225.45494 | H17: =IFERROR(AVERAGEIFS(d_dom,d_type,$A17),"") -> 57.471831 | I17: =IFERROR(AVERAGEIFS(d_stl,d_type,$A17),"") -> 0.97535231 | J17: =IFERROR(AVERAGEIFS(d_comm,d_type,$A17),"") -> 2.9161314
A18: Townhouse | B18: =COUNTIFS(d_type,$A18) -> 47 | C18: =B18/B$19 -> 0.188 | D18: =SUMIFS(d_price,d_type,$A18) -> 16227000 | E18: =IFERROR(AVERAGEIFS(d_price,d_type,$A18),"") -> 345255.32 | F18: {=IFERROR(MEDIAN(IF(d_type=$A18,d_price)),"")} -> 339000 | G18: =IFERROR(AVERAGEIFS(d_psf,d_type,$A18),"") -> 215.28185 | H18: =IFERROR(AVERAGEIFS(d_dom,d_type,$A18),"") -> 54.288889 | I18: =IFERROR(AVERAGEIFS(d_stl,d_type,$A18),"") -> 0.97578539 | J18: =IFERROR(AVERAGEIFS(d_comm,d_type,$A18),"") -> 2.9002222
A19: Grand Total | B19: =SUM(B16:B18) -> 250 | C19: =SUM(C16:C18) -> 1 | D19: =SUM(D16:D18) -> 97600000 | E19: =AVERAGE(d_price) -> 390400 | F19: =MEDIAN(d_price) -> 366000 | G19: =AVERAGE(d_psf) -> 225.90432 | H19: =AVERAGE(d_dom) -> 57.371901 | I19: =AVERAGE(d_stl) -> 0.97491351 | J19: =AVERAGE(d_comm) -> 2.9224893
A21: 3 ▸ BY CONDITION
A22: Condition | B22: Sales | C22: % of Sales | D22: Volume ($) | E22: Avg Price | F22: Median Price | G22: Avg $/sqft | H22: Avg DOM | I22: Avg Sale-to-List | J22: Avg Commission %
A23: Excellent | B23: =COUNTIFS(d_cond,$A23) -> 62 | C23: =B23/B$28 -> 0.248 | D23: =SUMIFS(d_price,d_cond,$A23) -> 28455000 | E23: =IFERROR(AVERAGEIFS(d_price,d_cond,$A23),"") -> 458951.61 | F23: {=IFERROR(MEDIAN(IF(d_cond=$A23,d_price)),"")} -> 405000 | G23: =IFERROR(AVERAGEIFS(d_psf,d_cond,$A23),"") -> 252.55274 | H23: =IFERROR(AVERAGEIFS(d_dom,d_cond,$A23),"") -> 48.901639 | I23: =IFERROR(AVERAGEIFS(d_stl,d_cond,$A23),"") -> 0.97978707 | J23: =IFERROR(AVERAGEIFS(d_comm,d_cond,$A23),"") -> 2.8951667
A24: Good | B24: =COUNTIFS(d_cond,$A24) -> 105 | C24: =B24/B$28 -> 0.42 | D24: =SUMIFS(d_price,d_cond,$A24) -> 39126000 | E24: =IFERROR(AVERAGEIFS(d_price,d_cond,$A24),"") -> 372628.57 | F24: {=IFERROR(MEDIAN(IF(d_cond=$A24,d_price)),"")} -> 364000 | G24: =IFERROR(AVERAGEIFS(d_psf,d_cond,$A24),"") -> 222.75656 | H24: =IFERROR(AVERAGEIFS(d_dom,d_cond,$A24),"") -> 52.128713 | I24: =IFERROR(AVERAGEIFS(d_stl,d_cond,$A24),"") -> 0.97112013 | J24: =IFERROR(AVERAGEIFS(d_comm,d_cond,$A24),"") -> 2.9216667
A25: Fair | B25: =COUNTIFS(d_cond,$A25) -> 60 | C25: =B25/B$28 -> 0.24 | D25: =SUMIFS(d_price,d_cond,$A25) -> 21605000 | E25: =IFERROR(AVERAGEIFS(d_price,d_cond,$A25),"") -> 360083.33 | F25: {=IFERROR(MEDIAN(IF(d_cond=$A25,d_price)),"")} -> 346000 | G25: =IFERROR(AVERAGEIFS(d_psf,d_cond,$A25),"") -> 212.47926 | H25: =IFERROR(AVERAGEIFS(d_dom,d_cond,$A25),"") -> 72.396552 | I25: =IFERROR(AVERAGEIFS(d_stl,d_cond,$A25),"") -> 0.97609542 | J25: =IFERROR(AVERAGEIFS(d_comm,d_cond,$A25),"") -> 2.9598214
A26: Poor | B26: =COUNTIFS(d_cond,$A26) -> 11 | C26: =B26/B$28 -> 0.044 | D26: =SUMIFS(d_price,d_cond,$A26) -> 3496000 | E26: =IFERROR(AVERAGEIFS(d_price,d_cond,$A26),"") -> 317818.18 | F26: {=IFERROR(MEDIAN(IF(d_cond=$A26,d_price)),"")} -> 315000 | G26: =IFERROR(AVERAGEIFS(d_psf,d_cond,$A26),"") -> 181.72841 | H26: =IFERROR(AVERAGEIFS(d_dom,d_cond,$A26),"") -> 75.3 | I26: =IFERROR(AVERAGEIFS(d_stl,d_cond,$A26),"") -> 0.98119221 | J26: =IFERROR(AVERAGEIFS(d_comm,d_cond,$A26),"") -> 2.967
A27: Unknown | B27: =COUNTIFS(d_cond,$A27) -> 12 | C27: =B27/B$28 -> 0.048 | D27: =SUMIFS(d_price,d_cond,$A27) -> 4918000 | E27: =IFERROR(AVERAGEIFS(d_price,d_cond,$A27),"") -> 409833.33 | F27: {=IFERROR(MEDIAN(IF(d_cond=$A27,d_price)),"")} -> 427500 | G27: =IFERROR(AVERAGEIFS(d_psf,d_cond,$A27),"") -> 223.38364 | H27: =IFERROR(AVERAGEIFS(d_dom,d_cond,$A27),"") -> 57 | I27: =IFERROR(AVERAGEIFS(d_stl,d_cond,$A27),"") -> 0.97126045 | J27: =IFERROR(AVERAGEIFS(d_comm,d_cond,$A27),"") -> 2.8481818
A28: Grand Total | B28: =SUM(B23:B27) -> 250 | C28: =SUM(C23:C27) -> 1 | D28: =SUM(D23:D27) -> 97600000 | E28: =AVERAGE(d_price) -> 390400 | F28: =MEDIAN(d_price) -> 366000 | G28: =AVERAGE(d_psf) -> 225.90432 | H28: =AVERAGE(d_dom) -> 57.371901 | I28: =AVERAGE(d_stl) -> 0.97491351 | J28: =AVERAGE(d_comm) -> 2.9224893
A30: 4 ▸ BY BEDROOMS (6 bedrooms = 1 sale only, treat with caution)
A31: Bedrooms | B31: Sales | C31: % of Sales | D31: Volume ($) | E31: Avg Price | F31: Median Price | G31: Avg $/sqft | H31: Avg DOM | I31: Avg Sale-to-List | J31: Avg Commission %
A32: 1 | B32: =COUNTIFS(d_beds,$A32) -> 27 | C32: =B32/B$38 -> 0.108 | D32: =SUMIFS(d_price,d_beds,$A32) -> 5999000 | E32: =IFERROR(AVERAGEIFS(d_price,d_beds,$A32),"") -> 222185.19 | F32: {=IFERROR(MEDIAN(IF(d_beds=$A32,d_price)),"")} -> 199000 | G32: =IFERROR(AVERAGEIFS(d_psf,d_beds,$A32),"") -> 252.12408 | H32: =IFERROR(AVERAGEIFS(d_dom,d_beds,$A32),"") -> 63.555556 | I32: =IFERROR(AVERAGEIFS(d_stl,d_beds,$A32),"") -> 0.98229399 | J32: =IFERROR(AVERAGEIFS(d_comm,d_beds,$A32),"") -> 2.9990909
A33: 2 | B33: =COUNTIFS(d_beds,$A33) -> 51 | C33: =B33/B$38 -> 0.204 | D33: =SUMIFS(d_price,d_beds,$A33) -> 15424000 | E33: =IFERROR(AVERAGEIFS(d_price,d_beds,$A33),"") -> 302431.37 | F33: {=IFERROR(MEDIAN(IF(d_beds=$A33,d_price)),"")} -> 301000 | G33: =IFERROR(AVERAGEIFS(d_psf,d_beds,$A33),"") -> 233.88435 | H33: =IFERROR(AVERAGEIFS(d_dom,d_beds,$A33),"") -> 57.795918 | I33: =IFERROR(AVERAGEIFS(d_stl,d_beds,$A33),"") -> 0.96993566 | J33: =IFERROR(AVERAGEIFS(d_comm,d_beds,$A33),"") -> 2.922449
A34: 3 | B34: =COUNTIFS(d_beds,$A34) -> 94 | C34: =B34/B$38 -> 0.376 | D34: =SUMIFS(d_price,d_beds,$A34) -> 35757000 | E34: =IFERROR(AVERAGEIFS(d_price,d_beds,$A34),"") -> 380393.62 | F34: {=IFERROR(MEDIAN(IF(d_beds=$A34,d_price)),"")} -> 372000 | G34: =IFERROR(AVERAGEIFS(d_psf,d_beds,$A34),"") -> 220.32431 | H34: =IFERROR(AVERAGEIFS(d_dom,d_beds,$A34),"") -> 59.133333 | I34: =IFERROR(AVERAGEIFS(d_stl,d_beds,$A34),"") -> 0.97516756 | J34: =IFERROR(AVERAGEIFS(d_comm,d_beds,$A34),"") -> 2.9226667
A35: 4 | B35: =COUNTIFS(d_beds,$A35) -> 55 | C35: =B35/B$38 -> 0.22 | D35: =SUMIFS(d_price,d_beds,$A35) -> 24672000 | E35: =IFERROR(AVERAGEIFS(d_price,d_beds,$A35),"") -> 448581.82 | F35: {=IFERROR(MEDIAN(IF(d_beds=$A35,d_price)),"")} -> 444000 | G35: =IFERROR(AVERAGEIFS(d_psf,d_beds,$A35),"") -> 212.24755 | H35: =IFERROR(AVERAGEIFS(d_dom,d_beds,$A35),"") -> 53.111111 | I35: =IFERROR(AVERAGEIFS(d_stl,d_beds,$A35),"") -> 0.97546149 | J35: =IFERROR(AVERAGEIFS(d_comm,d_beds,$A35),"") -> 2.9319608
A36: 5 | B36: =COUNTIFS(d_beds,$A36) -> 22 | C36: =B36/B$38 -> 0.088 | D36: =SUMIFS(d_price,d_beds,$A36) -> 12438000 | E36: =IFERROR(AVERAGEIFS(d_price,d_beds,$A36),"") -> 565363.64 | F36: {=IFERROR(MEDIAN(IF(d_beds=$A36,d_price)),"")} -> 541000 | G36: =IFERROR(AVERAGEIFS(d_psf,d_beds,$A36),"") -> 219.97003 | H36: =IFERROR(AVERAGEIFS(d_dom,d_beds,$A36),"") -> 51.666667 | I36: =IFERROR(AVERAGEIFS(d_stl,d_beds,$A36),"") -> 0.97564398 | J36: =IFERROR(AVERAGEIFS(d_comm,d_beds,$A36),"") -> 2.835
A37: 6 | B37: =COUNTIFS(d_beds,$A37) -> 1 | C37: =B37/B$38 -> 0.004 | D37: =SUMIFS(d_price,d_beds,$A37) -> 3310000 | E37: =IFERROR(AVERAGEIFS(d_price,d_beds,$A37),"") -> 3310000 | F37: {=IFERROR(MEDIAN(IF(d_beds=$A37,d_price)),"")} -> 3310000 | G37: =IFERROR(AVERAGEIFS(d_psf,d_beds,$A37),"") -> 517.1875 | H37: =IFERROR(AVERAGEIFS(d_dom,d_beds,$A37),"") -> 61 | I37: =IFERROR(AVERAGEIFS(d_stl,d_beds,$A37),"") -> 0.95942029 | J37: =IFERROR(AVERAGEIFS(d_comm,d_beds,$A37),"") -> 2.49
A38: Grand Total | B38: =SUM(B32:B37) -> 250 | C38: =SUM(C32:C37) -> 1 | D38: =SUM(D32:D37) -> 97600000 | E38: =AVERAGE(d_price) -> 390400 | F38: =MEDIAN(d_price) -> 366000 | G38: =AVERAGE(d_psf) -> 225.90432 | H38: =AVERAGE(d_dom) -> 57.371901 | I38: =AVERAGE(d_stl) -> 0.97491351 | J38: =AVERAGE(d_comm) -> 2.9224893
A40: 5 ▸ MONTHLY TREND (Aug-26 is a partial month — data ends 23-Aug-2026)
A41: Month | B41: Sales | C41: Volume ($) | D41: Avg Price | E41: Median Price | F41: Avg DOM | G41: Avg Sale-to-List | H41: 3-mo Rolling Avg Price | I41: Chart Label
A42: =MIN(d_month) -> 45658 | B42: =COUNTIFS(d_month,$A42) -> 17 | C42: =SUMIFS(d_price,d_month,$A42) -> 6456000 | D42: =IFERROR(AVERAGEIFS(d_price,d_month,$A42),"") -> 379764.71 | E42: {=IFERROR(MEDIAN(IF(d_month=$A42,d_price)),"")} -> 389000 | F42: =IFERROR(AVERAGEIFS(d_dom,d_month,$A42),"") -> 55.823529 | G42: =IFERROR(AVERAGEIFS(d_stl,d_month,$A42),"") -> 0.97988672 | H42: =SUM(C42:C42)/SUM(B42:B42) -> 379764.71 | I42: =TEXT(A42,"mmm-yy") -> Jan-25
A43: =EDATE(A42,1) -> 45689 | B43: =COUNTIFS(d_month,$A43) -> 12 | C43: =SUMIFS(d_price,d_month,$A43) -> 4361000 | D43: =IFERROR(AVERAGEIFS(d_price,d_month,$A43),"") -> 363416.67 | E43: {=IFERROR(MEDIAN(IF(d_month=$A43,d_price)),"")} -> 359500 | F43: =IFERROR(AVERAGEIFS(d_dom,d_month,$A43),"") -> 51.545455 | G43: =IFERROR(AVERAGEIFS(d_stl,d_month,$A43),"") -> 0.96617896 | H43: =SUM(C42:C43)/SUM(B42:B43) -> 373000 | I43: =TEXT(A43,"mmm-yy") -> Feb-25
A44: =EDATE(A43,1) -> 45717 | B44: =COUNTIFS(d_month,$A44) -> 19 | C44: =SUMIFS(d_price,d_month,$A44) -> 9849000 | D44: =IFERROR(AVERAGEIFS(d_price,d_month,$A44),"") -> 518368.42 | E44: {=IFERROR(MEDIAN(IF(d_month=$A44,d_price)),"")} -> 370000 | F44: =IFERROR(AVERAGEIFS(d_dom,d_month,$A44),"") -> 54.388889 | G44: =IFERROR(AVERAGEIFS(d_stl,d_month,$A44),"") -> 0.96938202 | H44: =SUM(C42:C44)/SUM(B42:B44) -> 430541.67 | I44: =TEXT(A44,"mmm-yy") -> Mar-25
A45: =EDATE(A44,1) -> 45748 | B45: =COUNTIFS(d_month,$A45) -> 13 | C45: =SUMIFS(d_price,d_month,$A45) -> 5756000 | D45: =IFERROR(AVERAGEIFS(d_price,d_month,$A45),"") -> 442769.23 | E45: {=IFERROR(MEDIAN(IF(d_month=$A45,d_price)),"")} -> 382000 | F45: =IFERROR(AVERAGEIFS(d_dom,d_month,$A45),"") -> 53.153846 | G45: =IFERROR(AVERAGEIFS(d_stl,d_month,$A45),"") -> 0.98632747 | H45: =SUM(C43:C45)/SUM(B43:B45) -> 453772.73 | I45: =TEXT(A45,"mmm-yy") -> Apr-25
A46: =EDATE(A45,1) -> 45778 | B46: =COUNTIFS(d_month,$A46) -> 10 | C46: =SUMIFS(d_price,d_month,$A46) -> 4259000 | D46: =IFERROR(AVERAGEIFS(d_price,d_month,$A46),"") -> 425900 | E46: {=IFERROR(MEDIAN(IF(d_month=$A46,d_price)),"")} -> 380000 | F46: =IFERROR(AVERAGEIFS(d_dom,d_month,$A46),"") -> 62.5 | G46: =IFERROR(AVERAGEIFS(d_stl,d_month,$A46),"") -> 0.97588208 | H46: =SUM(C44:C46)/SUM(B44:B46) -> 472952.38 | I46: =TEXT(A46,"mmm-yy") -> May-25
A47: =EDATE(A46,1) -> 45809 | B47: =COUNTIFS(d_month,$A47) -> 11 | C47: =SUMIFS(d_price,d_month,$A47) -> 4532000 | D47: =IFERROR(AVERAGEIFS(d_price,d_month,$A47),"") -> 412000 | E47: {=IFERROR(MEDIAN(IF(d_month=$A47,d_price)),"")} -> 440000 | F47: =IFERROR(AVERAGEIFS(d_dom,d_month,$A47),"") -> 59.272727 | G47: =IFERROR(AVERAGEIFS(d_stl,d_month,$A47),"") -> 0.97155679 | H47: =SUM(C45:C47)/SUM(B45:B47) -> 427852.94 | I47: =TEXT(A47,"mmm-yy") -> Jun-25
A48: =EDATE(A47,1) -> 45839 | B48: =COUNTIFS(d_month,$A48) -> 15 | C48: =SUMIFS(d_price,d_month,$A48) -> 5009000 | D48: =IFERROR(AVERAGEIFS(d_price,d_month,$A48),"") -> 333933.33 | E48: {=IFERROR(MEDIAN(IF(d_month=$A48,d_price)),"")} -> 317000 | F48: =IFERROR(AVERAGEIFS(d_dom,d_month,$A48),"") -> 55.928571 | G48: =IFERROR(AVERAGEIFS(d_stl,d_month,$A48),"") -> 0.95814606 | H48: =SUM(C46:C48)/SUM(B46:B48) -> 383333.33 | I48: =TEXT(A48,"mmm-yy") -> Jul-25
A49: =EDATE(A48,1) -> 45870 | B49: =COUNTIFS(d_month,$A49) -> 13 | C49: =SUMIFS(d_price,d_month,$A49) -> 5202000 | D49: =IFERROR(AVERAGEIFS(d_price,d_month,$A49),"") -> 400153.85 | E49: {=IFERROR(MEDIAN(IF(d_month=$A49,d_price)),"")} -> 373000 | F49: =IFERROR(AVERAGEIFS(d_dom,d_month,$A49),"") -> 57.230769 | G49: =IFERROR(AVERAGEIFS(d_stl,d_month,$A49),"") -> 0.98063578 | H49: =SUM(C47:C49)/SUM(B47:B49) -> 378025.64 | I49: =TEXT(A49,"mmm-yy") -> Aug-25
A50: =EDATE(A49,1) -> 45901 | B50: =COUNTIFS(d_month,$A50) -> 12 | C50: =SUMIFS(d_price,d_month,$A50) -> 4268000 | D50: =IFERROR(AVERAGEIFS(d_price,d_month,$A50),"") -> 355666.67 | E50: {=IFERROR(MEDIAN(IF(d_month=$A50,d_price)),"")} -> 367500 | F50: =IFERROR(AVERAGEIFS(d_dom,d_month,$A50),"") -> 49.583333 | G50: =IFERROR(AVERAGEIFS(d_stl,d_month,$A50),"") -> 0.97953162 | H50: =SUM(C48:C50)/SUM(B48:B50) -> 361975 | I50: =TEXT(A50,"mmm-yy") -> Sep-25
A51: =EDATE(A50,1) -> 45931 | B51: =COUNTIFS(d_month,$A51) -> 13 | C51: =SUMIFS(d_price,d_month,$A51) -> 5222000 | D51: =IFERROR(AVERAGEIFS(d_price,d_month,$A51),"") -> 401692.31 | E51: {=IFERROR(MEDIAN(IF(d_month=$A51,d_price)),"")} -> 422000 | F51: =IFERROR(AVERAGEIFS(d_dom,d_month,$A51),"") -> 45.461538 | G51: =IFERROR(AVERAGEIFS(d_stl,d_month,$A51),"") -> 0.99006871 | H51: =SUM(C49:C51)/SUM(B49:B51) -> 386631.58 | I51: =TEXT(A51,"mmm-yy") -> Oct-25
A52: =EDATE(A51,1) -> 45962 | B52: =COUNTIFS(d_month,$A52) -> 11 | C52: =SUMIFS(d_price,d_month,$A52) -> 4221000 | D52: =IFERROR(AVERAGEIFS(d_price,d_month,$A52),"") -> 383727.27 | E52: {=IFERROR(MEDIAN(IF(d_month=$A52,d_price)),"")} -> 329000 | F52: =IFERROR(AVERAGEIFS(d_dom,d_month,$A52),"") -> 96.5 | G52: =IFERROR(AVERAGEIFS(d_stl,d_month,$A52),"") -> 0.96472888 | H52: =SUM(C50:C52)/SUM(B50:B52) -> 380861.11 | I52: =TEXT(A52,"mmm-yy") -> Nov-25
A53: =EDATE(A52,1) -> 45992 | B53: =COUNTIFS(d_month,$A53) -> 7 | C53: =SUMIFS(d_price,d_month,$A53) -> 2504000 | D53: =IFERROR(AVERAGEIFS(d_price,d_month,$A53),"") -> 357714.29 | E53: {=IFERROR(MEDIAN(IF(d_month=$A53,d_price)),"")} -> 401000 | F53: =IFERROR(AVERAGEIFS(d_dom,d_month,$A53),"") -> 63.714286 | G53: =IFERROR(AVERAGEIFS(d_stl,d_month,$A53),"") -> 0.97114191 | H53: =SUM(C51:C53)/SUM(B51:B53) -> 385387.1 | I53: =TEXT(A53,"mmm-yy") -> Dec-25
A54: =EDATE(A53,1) -> 46023 | B54: =COUNTIFS(d_month,$A54) -> 18 | C54: =SUMIFS(d_price,d_month,$A54) -> 7468000 | D54: =IFERROR(AVERAGEIFS(d_price,d_month,$A54),"") -> 414888.89 | E54: {=IFERROR(MEDIAN(IF(d_month=$A54,d_price)),"")} -> 383000 | F54: =IFERROR(AVERAGEIFS(d_dom,d_month,$A54),"") -> 59.294118 | G54: =IFERROR(AVERAGEIFS(d_stl,d_month,$A54),"") -> 0.98047141 | H54: =SUM(C52:C54)/SUM(B52:B54) -> 394250 | I54: =TEXT(A54,"mmm-yy") -> Jan-26
A55: =EDATE(A54,1) -> 46054 | B55: =COUNTIFS(d_month,$A55) -> 9 | C55: =SUMIFS(d_price,d_month,$A55) -> 3814000 | D55: =IFERROR(AVERAGEIFS(d_price,d_month,$A55),"") -> 423777.78 | E55: {=IFERROR(MEDIAN(IF(d_month=$A55,d_price)),"")} -> 436000 | F55: =IFERROR(AVERAGEIFS(d_dom,d_month,$A55),"") -> 59.25 | G55: =IFERROR(AVERAGEIFS(d_stl,d_month,$A55),"") -> 0.96375944 | H55: =SUM(C53:C55)/SUM(B53:B55) -> 405470.59 | I55: =TEXT(A55,"mmm-yy") -> Feb-26
... A61: =EDATE(A60,1) -> 46235 | B61: =COUNTIFS(d_month,$A61) -> 5 | C61: =SUMIFS(d_price,d_month,$A61) -> 2119000 | D61: =IFERROR(AVERAGEIFS(d_price,d_month,$A61),"") -> 423800 | E61: {=IFERROR(MEDIAN(IF(d_month=$A61,d_price)),"")} -> 355000 | F61: =IFERROR(AVERAGEIFS(d_dom,d_month,$A61),"") -> 60.8 | G61: =IFERROR(AVERAGEIFS(d_stl,d_month,$A61),"") -> 0.98830453 | H61: =SUM(C59:C61)/SUM(B59:B61) -> 350314.29 | I61: =TEXT(A61,"mmm-yy") -> Aug-26
A62: Rolling avg = volume-weighted over the trailing 3 months (first two months use the months available).
A64: 6 ▸ SALE PRICE DISTRIBUTION (edit the blue lower bounds / labels — Data_Clean price_band updates)
A65: Band label | B65: Lower bound ($) | C65: Sales | D65: % of Sales | E65: Avg $/sqft | F65: Avg DOM
A66: Under $200K | B66: 0 | C66: =COUNTIF(d_band,$A66) -> 17 | D66: =C66/SUM($C$66:$C$72) -> 0.068 | E66: =IFERROR(AVERAGEIFS(d_psf,d_band,$A66),"") -> 208.59442 | F66: =IFERROR(AVERAGEIFS(d_dom,d_band,$A66),"") -> 69.705882
A67: $200-300K | B67: 200000 | C67: =COUNTIF(d_band,$A67) -> 47 | D67: =C67/SUM($C$66:$C$72) -> 0.188 | E67: =IFERROR(AVERAGEIFS(d_psf,d_band,$A67),"") -> 200.79541 | F67: =IFERROR(AVERAGEIFS(d_dom,d_band,$A67),"") -> 64.744186
A68: $300-400K | B68: 300000 | C68: =COUNTIF(d_band,$A68) -> 89 | D68: =C68/SUM($C$66:$C$72) -> 0.356 | E68: =IFERROR(AVERAGEIFS(d_psf,d_band,$A68),"") -> 216.53975 | F68: =IFERROR(AVERAGEIFS(d_dom,d_band,$A68),"") -> 54.747126
A69: $400-500K | B69: 400000 | C69: =COUNTIF(d_band,$A69) -> 57 | D69: =C69/SUM($C$66:$C$72) -> 0.228 | E69: =IFERROR(AVERAGEIFS(d_psf,d_band,$A69),"") -> 239.24878 | F69: =IFERROR(AVERAGEIFS(d_dom,d_band,$A69),"") -> 53.836364
A70: $500-600K | B70: 500000 | C70: =COUNTIF(d_band,$A70) -> 25 | D70: =C70/SUM($C$66:$C$72) -> 0.1 | E70: =IFERROR(AVERAGEIFS(d_psf,d_band,$A70),"") -> 248.82454 | F70: =IFERROR(AVERAGEIFS(d_dom,d_band,$A70),"") -> 54.92
A71: $600-800K | B71: 600000 | C71: =COUNTIF(d_band,$A71) -> 13 | D71: =C71/SUM($C$66:$C$72) -> 0.052 | E71: =IFERROR(AVERAGEIFS(d_psf,d_band,$A71),"") -> 271.61688 | F71: =IFERROR(AVERAGEIFS(d_dom,d_band,$A71),"") -> 54.769231
A72: $800K+ | B72: 800000 | C72: =COUNTIF(d_band,$A72) -> 2 | D72: =C72/SUM($C$66:$C$72) -> 0.008 | E72: =IFERROR(AVERAGEIFS(d_psf,d_band,$A72),"") -> 415.86987 | F72: =IFERROR(AVERAGEIFS(d_dom,d_band,$A72),"") -> 53
A75: 7 ▸ BY YEAR BUILT (era) — homes with unknown year_built are excluded
A76: Era | B76: From year | C76: To year | D76: Sales | E76: Avg Price | F76: Avg $/sqft | G76: Avg DOM | H76: Avg Sale-to-List
A77: Pre-1960 | B77: 1900 | C77: 1959 | D77: =COUNTIFS(d_year,">="&$B77,d_year,"<="&$C77) -> 31 | E77: =IFERROR(AVERAGEIFS(d_price,d_year,">="&$B77,d_year,"<="&$C77),"") -> 379870.97 | F77: =IFERROR(AVERAGEIFS(d_psf,d_year,">="&$B77,d_year,"<="&$C77),"") -> 215.43343 | G77: =IFERROR(AVERAGEIFS(d_dom,d_year,">="&$B77,d_year,"<="&$C77),"") -> 57.766667 | H77: =IFERROR(AVERAGEIFS(d_stl,d_year,">="&$B77,d_year,"<="&$C77),"") -> 0.9800088
A78: 1960-1979 | B78: 1960 | C78: 1979 | D78: =COUNTIFS(d_year,">="&$B78,d_year,"<="&$C78) -> 42 | E78: =IFERROR(AVERAGEIFS(d_price,d_year,">="&$B78,d_year,"<="&$C78),"") -> 361380.95 | F78: =IFERROR(AVERAGEIFS(d_psf,d_year,">="&$B78,d_year,"<="&$C78),"") -> 221.71382 | G78: =IFERROR(AVERAGEIFS(d_dom,d_year,">="&$B78,d_year,"<="&$C78),"") -> 66.55 | H78: =IFERROR(AVERAGEIFS(d_stl,d_year,">="&$B78,d_year,"<="&$C78),"") -> 0.9709113
A79: 1980-1999 | B79: 1980 | C79: 1999 | D79: =COUNTIFS(d_year,">="&$B79,d_year,"<="&$C79) -> 66 | E79: =IFERROR(AVERAGEIFS(d_price,d_year,">="&$B79,d_year,"<="&$C79),"") -> 358878.79 | F79: =IFERROR(AVERAGEIFS(d_psf,d_year,">="&$B79,d_year,"<="&$C79),"") -> 223.94037 | G79: =IFERROR(AVERAGEIFS(d_dom,d_year,">="&$B79,d_year,"<="&$C79),"") -> 50.968254 | H79: =IFERROR(AVERAGEIFS(d_stl,d_year,">="&$B79,d_year,"<="&$C79),"") -> 0.97426045
A80: 2000-2014 | B80: 2000 | C80: 2014 | D80: =COUNTIFS(d_year,">="&$B80,d_year,"<="&$C80) -> 53 | E80: =IFERROR(AVERAGEIFS(d_price,d_year,">="&$B80,d_year,"<="&$C80),"") -> 409283.02 | F80: =IFERROR(AVERAGEIFS(d_psf,d_year,">="&$B80,d_year,"<="&$C80),"") -> 234.78851 | G80: =IFERROR(AVERAGEIFS(d_dom,d_year,">="&$B80,d_year,"<="&$C80),"") -> 58.788462 | H80: =IFERROR(AVERAGEIFS(d_stl,d_year,">="&$B80,d_year,"<="&$C80),"") -> 0.97633462
A81: 2015+ | B81: 2015 | C81: 2100 | D81: =COUNTIFS(d_year,">="&$B81,d_year,"<="&$C81) -> 45 | E81: =IFERROR(AVERAGEIFS(d_price,d_year,">="&$B81,d_year,"<="&$C81),"") -> 461466.67 | F81: =IFERROR(AVERAGEIFS(d_psf,d_year,">="&$B81,d_year,"<="&$C81),"") -> 238.20316 | G81: =IFERROR(AVERAGEIFS(d_dom,d_year,">="&$B81,d_year,"<="&$C81),"") -> 57.022727 | H81: =IFERROR(AVERAGEIFS(d_stl,d_year,">="&$B81,d_year,"<="&$C81),"") -> 0.97769369
A84: 8 ▸ HEATMAP — AVG SALE PRICE (neighborhood × property type)
A85: Neighborhood | B85: Condo | C85: Single Family | D85: Townhouse | E85: All types
A86: Cedar Park | B86: =IFERROR(AVERAGEIFS(d_price,d_nbhd,$A86,d_type,B$85),"") -> 168444.44 | C86: =IFERROR(AVERAGEIFS(d_price,d_nbhd,$A86,d_type,C$85),"") -> 333120 | D86: =IFERROR(AVERAGEIFS(d_price,d_nbhd,$A86,d_type,D$85),"") -> 259200 | E86: =IFERROR(AVERAGEIFS(d_price,d_nbhd,$A86),"") -> 285641.03
A87: Downtown | B87: =IFERROR(AVERAGEIFS(d_price,d_nbhd,$A87,d_type,B$85),"") -> 334950 | C87: =IFERROR(AVERAGEIFS(d_price,d_nbhd,$A87,d_type,C$85),"") -> 576692.31 | D87: =IFERROR(AVERAGEIFS(d_price,d_nbhd,$A87,d_type,D$85),"") -> 427666.67 | E87: =IFERROR(AVERAGEIFS(d_price,d_nbhd,$A87),"") -> 429972.22
A88: Maple Heights | B88: =IFERROR(AVERAGEIFS(d_price,d_nbhd,$A88,d_type,B$85),"") -> 206714.29 | C88: =IFERROR(AVERAGEIFS(d_price,d_nbhd,$A88,d_type,C$85),"") -> 376633.33 | D88: =IFERROR(AVERAGEIFS(d_price,d_nbhd,$A88,d_type,D$85),"") -> 315714.29 | E88: =IFERROR(AVERAGEIFS(d_price,d_nbhd,$A88),"") -> 336588.24
A89: Oak Hill | B89: =IFERROR(AVERAGEIFS(d_price,d_nbhd,$A89,d_type,B$85),"") -> 308090.91 | C89: =IFERROR(AVERAGEIFS(d_price,d_nbhd,$A89,d_type,C$85),"") -> 572756.76 | D89: =IFERROR(AVERAGEIFS(d_price,d_nbhd,$A89,d_type,D$85),"") -> 399100 | E89: =IFERROR(AVERAGEIFS(d_price,d_nbhd,$A89),"") -> 492620.69
A90: Riverside | B90: =IFERROR(AVERAGEIFS(d_price,d_nbhd,$A90,d_type,B$85),"") -> 224600 | C90: =IFERROR(AVERAGEIFS(d_price,d_nbhd,$A90,d_type,C$85),"") -> 434128.21 | D90: =IFERROR(AVERAGEIFS(d_price,d_nbhd,$A90,d_type,D$85),"") -> 352153.85 | E90: =IFERROR(AVERAGEIFS(d_price,d_nbhd,$A90),"") -> 383145.16
A91: All areas | B91: =IFERROR(AVERAGEIFS(d_price,d_type,B$85),"") -> 268368.42 | C91: =IFERROR(AVERAGEIFS(d_price,d_type,C$85),"") -> 452575.34 | D91: =IFERROR(AVERAGEIFS(d_price,d_type,D$85),"") -> 345255.32 | E91: =AVERAGE(d_price) -> 390400
A94: 9 ▸ HEATMAP — AVG PRICE PER SQ FT
A95: Neighborhood | B95: Condo | C95: Single Family | D95: Townhouse | E95: All types
A96: Cedar Park | B96: =IFERROR(AVERAGEIFS(d_psf,d_nbhd,$A96,d_type,B$95),"") -> 169.55371 | C96: =IFERROR(AVERAGEIFS(d_psf,d_nbhd,$A96,d_type,C$95),"") -> 177.64611 | D96: =IFERROR(AVERAGEIFS(d_psf,d_nbhd,$A96,d_type,D$95),"") -> 149.32044 | E96: =IFERROR(AVERAGEIFS(d_psf,d_nbhd,$A96),"") -> 172.14713
A97: Downtown | B97: =IFERROR(AVERAGEIFS(d_psf,d_nbhd,$A97,d_type,B$95),"") -> 294.929 | C97: =IFERROR(AVERAGEIFS(d_psf,d_nbhd,$A97,d_type,C$95),"") -> 305.97859 | D97: =IFERROR(AVERAGEIFS(d_psf,d_nbhd,$A97,d_type,D$95),"") -> 271.36019 | E97: =IFERROR(AVERAGEIFS(d_psf,d_nbhd,$A97),"") -> 296.95506
A98: Maple Heights | B98: =IFERROR(AVERAGEIFS(d_psf,d_nbhd,$A98,d_type,B$95),"") -> 178.77915 | C98: =IFERROR(AVERAGEIFS(d_psf,d_nbhd,$A98,d_type,C$95),"") -> 197.9114 | D98: =IFERROR(AVERAGEIFS(d_psf,d_nbhd,$A98,d_type,D$95),"") -> 190.9264 | E98: =IFERROR(AVERAGEIFS(d_psf,d_nbhd,$A98),"") -> 193.36796
A99: Oak Hill | B99: =IFERROR(AVERAGEIFS(d_psf,d_nbhd,$A99,d_type,B$95),"") -> 236.25446 | C99: =IFERROR(AVERAGEIFS(d_psf,d_nbhd,$A99,d_type,C$95),"") -> 258.38389 | D99: =IFERROR(AVERAGEIFS(d_psf,d_nbhd,$A99,d_type,D$95),"") -> 250.48942 | E99: =IFERROR(AVERAGEIFS(d_psf,d_nbhd,$A99),"") -> 252.82582
A100: Riverside | B100: =IFERROR(AVERAGEIFS(d_psf,d_nbhd,$A100,d_type,B$95),"") -> 216.6596 | C100: =IFERROR(AVERAGEIFS(d_psf,d_nbhd,$A100,d_type,C$95),"") -> 221.06576 | D100: =IFERROR(AVERAGEIFS(d_psf,d_nbhd,$A100,d_type,D$95),"") -> 225.3366 | E100: =IFERROR(AVERAGEIFS(d_psf,d_nbhd,$A100),"") -> 221.25059
A101: All areas | B101: =IFERROR(AVERAGEIFS(d_psf,d_type,B$95),"") -> 235.81426 | C101: =IFERROR(AVERAGEIFS(d_psf,d_type,C$95),"") -> 225.45494 | D101: =IFERROR(AVERAGEIFS(d_psf,d_type,D$95),"") -> 215.28185 | E101: =AVERAGE(d_psf) -> 225.90432
A104: 10 ▸ SALES COUNT (neighborhood × property type)
A105: Neighborhood | B105: Condo | C105: Single Family | D105: Townhouse | E105: All types
A106: Cedar Park | B106: =COUNTIFS(d_nbhd,$A106,d_type,B$105) -> 9 | C106: =COUNTIFS(d_nbhd,$A106,d_type,C$105) -> 25 | D106: =COUNTIFS(d_nbhd,$A106,d_type,D$105) -> 5 | E106: =COUNTIFS(d_nbhd,$A106) -> 39
A107: Downtown | B107: =COUNTIFS(d_nbhd,$A107,d_type,B$105) -> 20 | C107: =COUNTIFS(d_nbhd,$A107,d_type,C$105) -> 13 | D107: =COUNTIFS(d_nbhd,$A107,d_type,D$105) -> 3 | E107: =COUNTIFS(d_nbhd,$A107) -> 36
A108: Maple Heights | B108: =COUNTIFS(d_nbhd,$A108,d_type,B$105) -> 7 | C108: =COUNTIFS(d_nbhd,$A108,d_type,C$105) -> 30 | D108: =COUNTIFS(d_nbhd,$A108,d_type,D$105) -> 14 | E108: =COUNTIFS(d_nbhd,$A108) -> 51
A109: Oak Hill | B109: =COUNTIFS(d_nbhd,$A109,d_type,B$105) -> 11 | C109: =COUNTIFS(d_nbhd,$A109,d_type,C$105) -> 37 | D109: =COUNTIFS(d_nbhd,$A109,d_type,D$105) -> 10 | E109: =COUNTIFS(d_nbhd,$A109) -> 58
A110: Riverside | B110: =COUNTIFS(d_nbhd,$A110,d_type,B$105) -> 10 | C110: =COUNTIFS(d_nbhd,$A110,d_type,C$105) -> 39 | D110: =COUNTIFS(d_nbhd,$A110,d_type,D$105) -> 13 | E110: =COUNTIFS(d_nbhd,$A110) -> 62
A111: All areas | B111: =COUNTIFS(d_type,B$105) -> 57 | C111: =COUNTIFS(d_type,C$105) -> 146 | D111: =COUNTIFS(d_type,D$105) -> 47 | E111: =COUNT(d_price) -> 250

Sheet Dashboard
B1: HOME SALES PERFORMANCE DASHBOARD
B2: =" "&COUNT(d_price)&" closed sales | "&TEXT(MIN(d_date),"d mmm yyyy")&" – "&TEXT(MAX(d_date),"d mmm yyyy")&" | Source: home_sales_synthetic.csv (cleaned — see Cleaning_Log)" -> 250 closed sales | 1 Jan 2025 – 23 Aug 2026 | Source: home_sales_synthetic.csv (cleaned — see Cleaning_Log)
B4: NEIGHBORHOOD ▸ | D4: All | F4: PROPERTY TYPE ▸ | H4: All | J4: ◂ dropdowns filter the KPI cards. Click any 🔍 button under a chart to open that graph's detail page.
B6: HOMES SOLD | D6: TOTAL VOLUME | F6: MEDIAN PRICE | H6: AVG $ / SQ FT | J6: AVG DAYS ON MKT | L6: SALE-TO-LIST
B7: =COUNTIFS(d_nbhd,c_nb,d_type,c_pt) -> 250 | D7: =SUMIFS(d_price,d_nbhd,c_nb,d_type,c_pt) -> 97600000 | F7: {=IFERROR(MEDIAN(IF(((Dashboard!$D$4="All")+(d_nbhd=Dashboard!$D$4)>0)*((Dashboard!$H$4="All")+(d_type=Dashboard!$H$4)>0),d_price)),"n/a")} -> 366000 | H7: =IFERROR(AVERAGEIFS(d_psf,d_nbhd,c_nb,d_type,c_pt),"n/a") -> 225.90432 | J7: =IFERROR(AVERAGEIFS(d_dom,d_nbhd,c_nb,d_type,c_pt),"n/a") -> 57.371901 | L7: =IFERROR(AVERAGEIFS(d_stl,d_nbhd,c_nb,d_type,c_pt),"n/a") -> 0.97491351
B8: ="Market: "&TEXT(COUNT(d_price),"#,##0") -> Market: 250 | D8: ="Market: "&TEXT(SUM(d_price),"$#,##0.0,,")&"M" -> Market: $97.6M | F8: ="Market: "&TEXT(MEDIAN(d_price),"$#,##0") -> Market: $3,66,000 | H8: ="Market: "&TEXT(AVERAGE(d_psf),"$#,##0") -> Market: $226 | J8: ="Market: "&TEXT(AVERAGE(d_dom),"0.0")&" days" -> Market: 57.4 days | L8: ="Market: "&TEXT(AVERAGE(d_stl),"0.0%") -> Market: 97.5%
B10: KEY INSIGHTS (auto-generated — text updates with the data)
B11: ="▲ PRICE: "&INDEX(Pivots!$A$6:$A$10,MATCH(MAX(Pivots!$E$6:$E$10),Pivots!$E$6:$E$10,0))&" is the priciest area (avg "&TEXT(MAX(Pivots!$E$6:$E$10),"$#,##0")&"); "&INDEX(Pivots!$A$6:$A$10,MATCH(MIN(Pivots!$E$6:$E$10),Pivots!$E$6:$E$10,0))&" is the most affordable ("&TEXT(MIN(Pivots!$E$6:$E$10),"$#,##0")&") — a "&TEXT(MAX(Pivots!$E$6:$E$10)/MIN(Pivots!$E$6:$E$10)-1,"0%")&" gap." -> ▲ PRICE: Oak Hill is the priciest area (avg $4,92,621); Cedar Park is the most affordable ($2,85,641) — a 72% gap.
B12: ="⏱ SPEED: "&INDEX(Pivots!$A$6:$A$10,MATCH(MIN(Pivots!$H$6:$H$10),Pivots!$H$6:$H$10,0))&" sells fastest ("&TEXT(MIN(Pivots!$H$6:$H$10),"0")&" days avg on market); "&INDEX(Pivots!$A$6:$A$10,MATCH(MAX(Pivots!$H$6:$H$10),Pivots!$H$6:$H$10,0))&" is slowest ("&TEXT(MAX(Pivots!$H$6:$H$10),"0")&" days)." -> ⏱ SPEED: Downtown sells fastest (53 days avg on market); Cedar Park is slowest (68 days).
B13: ="🏠 TYPE: Single Family homes average "&TEXT(Pivots!E17,"$#,##0")&" — "&TEXT(Pivots!E17/Pivots!E16-1,"0%")&" above condos ("&TEXT(Pivots!E16,"$#,##0")&"); townhouses sit between at "&TEXT(Pivots!E18,"$#,##0")&"." -> 🏠 TYPE: Single Family homes average $4,52,575 — 69% above condos ($2,68,368); townhouses sit between at $3,45,255.
B14: ="📐 SIZE: Living area is the strongest price driver (r = "&TEXT(Analysis!B30,"0.00")&"). Excluding outliers, each extra sq ft adds ≈ "&TEXT(Analysis!C42,"$#,##0")&" to the price (R² = "&TEXT(Analysis!C44,"0.00")&")." -> 📐 SIZE: Living area is the strongest price driver (r = 0.80). Excluding outliers, each extra sq ft adds ≈ $184 to the price (R² = 0.59).
B15: ="🤝 NEGOTIATION: Homes close at "&TEXT(Analysis!B58,"0.0%")&" of list on average — "&TEXT(Analysis!B60,"0%")&" sell above asking, "&TEXT(Analysis!B62,"0%")&" below (avg "&TEXT(-Analysis!B64,"$#,##0")&" off when they do)." -> 🤝 NEGOTIATION: Homes close at 97.5% of list on average — 19% sell above asking, 79% below (avg $14,782 off when they do).
B16: ="✨ CONDITION: Excellent homes average "&TEXT(Pivots!E23,"$#,##0")&" vs "&TEXT(Pivots!E26,"$#,##0")&" for Poor ("&TEXT(Pivots!E23/Pivots!E26-1,"0%")&" gap"&IF(AVERAGEIFS(d_sqft,d_cond,"Excellent")>1.05*AVERAGEIFS(d_sqft,d_cond,"Poor"),", partly because they are larger",", not explained by home size")&") and sell "&TEXT(Pivots!H26-Pivots!H23,"0")&" days faster." -> ✨ CONDITION: Excellent homes average $4,58,952 vs $3,17,818 for Poor (44% gap, not explained by home size) and sell 26 days faster.
B18: MARKET TREND — volume vs. price by month
B35: 🔍 Click for details & drill-down: Monthly Trend ▸
B36: NEIGHBORHOOD PERFORMANCE
B53: 🔍 Click for details & drill-down: Neighborhood Pricing ▸ | H53: 🔍 Click for details & drill-down: Speed & Negotiation ▸
B54: MARKET MIX
B71: 🔍 Click for details & drill-down: Property Type ▸ | H71: 🔍 Click for details & drill-down: Price Distribution ▸
B72: PRICE DRIVERS
B89: 🔍 Click for details & drill-down: Size vs. Price ▸ | H89: 🔍 Click for details & drill-down: Condition ▸
B90: SIZE PREMIUM & NEIGHBORHOOD × TYPE HEATMAP
H91: Average Sale Price — Neighborhood × Property Type
H92: Neighborhood | I92: Condo | J92: Single Family | K92: Townhouse | L92: All types | M92: Sales (n)
H93: =Pivots!A86 -> Cedar Park | I93: =Pivots!B86 -> 168444.44 | J93: =Pivots!C86 -> 333120 | K93: =Pivots!D86 -> 259200 | L93: =Pivots!E86 -> 285641.03 | M93: =Pivots!E106 -> 39
H94: =Pivots!A87 -> Downtown | I94: =Pivots!B87 -> 334950 | J94: =Pivots!C87 -> 576692.31 | K94: =Pivots!D87 -> 427666.67 | L94: =Pivots!E87 -> 429972.22 | M94: =Pivots!E107 -> 36
H95: =Pivots!A88 -> Maple Heights | I95: =Pivots!B88 -> 206714.29 | J95: =Pivots!C88 -> 376633.33 | K95: =Pivots!D88 -> 315714.29 | L95: =Pivots!E88 -> 336588.24 | M95: =Pivots!E108 -> 51
H96: =Pivots!A89 -> Oak Hill | I96: =Pivots!B89 -> 308090.91 | J96: =Pivots!C89 -> 572756.76 | K96: =Pivots!D89 -> 399100 | L96: =Pivots!E89 -> 492620.69 | M96: =Pivots!E109 -> 58
H97: =Pivots!A90 -> Riverside | I97: =Pivots!B90 -> 224600 | J97: =Pivots!C90 -> 434128.21 | K97: =Pivots!D90 -> 352153.85 | L97: =Pivots!E90 -> 383145.16 | M97: =Pivots!E110 -> 62
H98: =Pivots!A91 -> All areas | I98: =Pivots!B91 -> 268368.42 | J98: =Pivots!C91 -> 452575.34 | K98: =Pivots!D91 -> 345255.32 | L98: =Pivots!E91 -> 390400 | M98: =Pivots!E111 -> 250
H100: How to read: darker green = higher average price. Blank cells mean no sales in that combination (e.g. condos may not exist in every area). Bedroom chart excludes the single 6-BR sale. For full detail see the Pivots sheet.
H105: 🔍 Full heatmaps & all pivot tables ▸
B108: 🔍 Click for details & drill-down: Bedrooms ▸
B109: ="Notes: Aug-2026 is a partial month. Outliers ("&Analysis!G22&" high-price, "&Analysis!G23&" long-DOM, "&Analysis!G24&" $/sqft flags) are kept and labelled in Data_Clean › outlier_flag. Imputed values are documented in Cleaning_Log." -> Notes: Aug-2026 is a partial month. Outliers (4 high-price, 5 long-DOM, 2 $/sqft flags) are kept and labelled in Data_Clean › outlier_flag. Imputed values are documented in Cleaning_Log.

Sheet D1_Trend
B1: 1 ▸ MONTHLY TREND — DRILL-DOWN
B2: Sales volume and pricing month by month, with the rolling average that smooths short-term noise.
B3: ◂ Back to Dashboard | C3: ◂ Previous graph | E3: Next graph ▸ | G3: Graph 1 of 8 • use the buttons to move between graphs or return to the dashboard
B5: TOTAL SALES | E5: BUSIEST MONTH | H5: PEAK AVG PRICE MONTH | K5: AVG SALES / FULL MONTH
B6: =C50 -> 250 | E6: =INDEX(B30:B49,MATCH(MAX(C30:C49),C30:C49,0)) -> 46204 | H6: =INDEX(B30:B49,MATCH(MAX(E30:E49),E30:E49,0)) -> 45717 | K6: =AVERAGE(C30:C48) -> 12.894737
B7: ="Across "&COUNT(C30:C49)&" months" -> Across 20 months | E7: =MAX(C30:C49)&" homes sold" -> 21 homes sold | H7: =TEXT(MAX(E30:E49),"$#,##0")&" average" -> $5,18,368 average | K7: ="excl. partial "&TEXT(B49,"mmm-yy") -> excl. partial Aug-26
B9: THE GRAPH | I9: KEY TAKEAWAYS (auto-generated)
I10: ="Busiest month: "&TEXT(INDEX(B30:B49,MATCH(MAX(C30:C49),C30:C49,0)),"mmm-yy")&" ("&MAX(C30:C49)&" sales). Quietest full month: "&TEXT(INDEX(B30:B48,MATCH(MIN(C30:C48),C30:C48,0)),"mmm-yy")&" ("&MIN(C30:C48)&" sales)." -> Busiest month: Jul-26 (21 sales). Quietest full month: Dec-25 (7 sales).
I13: ="Average price ranged from "&TEXT(MIN(E30:E49),"$#,##0")&" ("&TEXT(INDEX(B30:B49,MATCH(MIN(E30:E49),E30:E49,0)),"mmm-yy")&") to "&TEXT(MAX(E30:E49),"$#,##0")&" ("&TEXT(INDEX(B30:B49,MATCH(MAX(E30:E49),E30:E49,0)),"mmm-yy")&")." -> Average price ranged from $3,07,444 (Apr-26) to $5,18,368 (Mar-25).
I16: ="Biggest average-vs-median gap: "&TEXT(INDEX(B30:B49,MATCH(MAX(L30:L49),L30:L49,0)),"mmm-yy")&" ("&TEXT(MAX(L30:L49),"$#,##0")&") — a few high-value sales lifted that month; the median is the fairer read." -> Biggest average-vs-median gap: Mar-25 ($1,48,368) — a few high-value sales lifted that month; the median is the fairer read.
I19: ="The 3-month rolling average moved from "&TEXT(I30,"$#,##0")&" to "&TEXT(I49,"$#,##0")&" ("&TEXT(I49/I30-1,"+0.0%;-0.0%")&") over the period." -> The 3-month rolling average moved from $3,79,765 to $3,50,314 (-7.8%) over the period.
I22: ="Volume beat the monthly average ("&TEXT(AVERAGE(C30:C49),"0.0")&") in "&COUNTIF(C30:C49,">"&AVERAGE(C30:C49))&" of "&COUNT(C30:C49)&" months." -> Volume beat the monthly average (12.5) in 9 of 20 months.
B28: DATA BEHIND THE GRAPH
B29: Month | C29: Sales | D29: Volume ($) | E29: Avg Price | F29: Median Price | G29: Avg DOM | H29: Sale-to-List | I29: 3-mo Rolling Avg | J29: Δ Avg Price MoM | K29: Δ Sales MoM | L29: Avg − Median
B30: =Pivots!A42 -> 45658 | C30: =Pivots!B42 -> 17 | D30: =Pivots!C42 -> 6456000 | E30: =Pivots!D42 -> 379764.71 | F30: =Pivots!E42 -> 389000 | G30: =Pivots!F42 -> 55.823529 | H30: =Pivots!G42 -> 0.97988672 | I30: =Pivots!H42 -> 379764.71 | J30: — | K30: — | L30: =IFERROR(E30-F30,"") -> -9235.2941
B31: =Pivots!A43 -> 45689 | C31: =Pivots!B43 -> 12 | D31: =Pivots!C43 -> 4361000 | E31: =Pivots!D43 -> 363416.67 | F31: =Pivots!E43 -> 359500 | G31: =Pivots!F43 -> 51.545455 | H31: =Pivots!G43 -> 0.96617896 | I31: =Pivots!H43 -> 373000 | J31: =IFERROR(E31/E30-1,"") -> -0.043047811 | K31: =IFERROR(C31/C30-1,"") -> -0.29411765 | L31: =IFERROR(E31-F31,"") -> 3916.6667
B32: =Pivots!A44 -> 45717 | C32: =Pivots!B44 -> 19 | D32: =Pivots!C44 -> 9849000 | E32: =Pivots!D44 -> 518368.42 | F32: =Pivots!E44 -> 370000 | G32: =Pivots!F44 -> 54.388889 | H32: =Pivots!G44 -> 0.96938202 | I32: =Pivots!H44 -> 430541.67 | J32: =IFERROR(E32/E31-1,"") -> 0.42637493 | K32: =IFERROR(C32/C31-1,"") -> 0.58333333 | L32: =IFERROR(E32-F32,"") -> 148368.42
B33: =Pivots!A45 -> 45748 | C33: =Pivots!B45 -> 13 | D33: =Pivots!C45 -> 5756000 | E33: =Pivots!D45 -> 442769.23 | F33: =Pivots!E45 -> 382000 | G33: =Pivots!F45 -> 53.153846 | H33: =Pivots!G45 -> 0.98632747 | I33: =Pivots!H45 -> 453772.73 | J33: =IFERROR(E33/E32-1,"") -> -0.14584066 | K33: =IFERROR(C33/C32-1,"") -> -0.31578947 | L33: =IFERROR(E33-F33,"") -> 60769.231
B34: =Pivots!A46 -> 45778 | C34: =Pivots!B46 -> 10 | D34: =Pivots!C46 -> 4259000 | E34: =Pivots!D46 -> 425900 | F34: =Pivots!E46 -> 380000 | G34: =Pivots!F46 -> 62.5 | H34: =Pivots!G46 -> 0.97588208 | I34: =Pivots!H46 -> 472952.38 | J34: =IFERROR(E34/E33-1,"") -> -0.038099375 | K34: =IFERROR(C34/C33-1,"") -> -0.23076923 | L34: =IFERROR(E34-F34,"") -> 45900
B35: =Pivots!A47 -> 45809 | C35: =Pivots!B47 -> 11 | D35: =Pivots!C47 -> 4532000 | E35: =Pivots!D47 -> 412000 | F35: =Pivots!E47 -> 440000 | G35: =Pivots!F47 -> 59.272727 | H35: =Pivots!G47 -> 0.97155679 | I35: =Pivots!H47 -> 427852.94 | J35: =IFERROR(E35/E34-1,"") -> -0.032636769 | K35: =IFERROR(C35/C34-1,"") -> 0.1 | L35: =IFERROR(E35-F35,"") -> -28000
B36: =Pivots!A48 -> 45839 | C36: =Pivots!B48 -> 15 | D36: =Pivots!C48 -> 5009000 | E36: =Pivots!D48 -> 333933.33 | F36: =Pivots!E48 -> 317000 | G36: =Pivots!F48 -> 55.928571 | H36: =Pivots!G48 -> 0.95814606 | I36: =Pivots!H48 -> 383333.33 | J36: =IFERROR(E36/E35-1,"") -> -0.1894822 | K36: =IFERROR(C36/C35-1,"") -> 0.36363636 | L36: =IFERROR(E36-F36,"") -> 16933.333
B37: =Pivots!A49 -> 45870 | C37: =Pivots!B49 -> 13 | D37: =Pivots!C49 -> 5202000 | E37: =Pivots!D49 -> 400153.85 | F37: =Pivots!E49 -> 373000 | G37: =Pivots!F49 -> 57.230769 | H37: =Pivots!G49 -> 0.98063578 | I37: =Pivots!H49 -> 378025.64 | J37: =IFERROR(E37/E36-1,"") -> 0.19830459 | K37: =IFERROR(C37/C36-1,"") -> -0.13333333 | L37: =IFERROR(E37-F37,"") -> 27153.846
B38: =Pivots!A50 -> 45901 | C38: =Pivots!B50 -> 12 | D38: =Pivots!C50 -> 4268000 | E38: =Pivots!D50 -> 355666.67 | F38: =Pivots!E50 -> 367500 | G38: =Pivots!F50 -> 49.583333 | H38: =Pivots!G50 -> 0.97953162 | I38: =Pivots!H50 -> 361975 | J38: =IFERROR(E38/E37-1,"") -> -0.11117519 | K38: =IFERROR(C38/C37-1,"") -> -0.076923077 | L38: =IFERROR(E38-F38,"") -> -11833.333
B39: =Pivots!A51 -> 45931 | C39: =Pivots!B51 -> 13 | D39: =Pivots!C51 -> 5222000 | E39: =Pivots!D51 -> 401692.31 | F39: =Pivots!E51 -> 422000 | G39: =Pivots!F51 -> 45.461538 | H39: =Pivots!G51 -> 0.99006871 | I39: =Pivots!H51 -> 386631.58 | J39: =IFERROR(E39/E38-1,"") -> 0.12940668 | K39: =IFERROR(C39/C38-1,"") -> 0.083333333 | L39: =IFERROR(E39-F39,"") -> -20307.692
B40: =Pivots!A52 -> 45962 | C40: =Pivots!B52 -> 11 | D40: =Pivots!C52 -> 4221000 | E40: =Pivots!D52 -> 383727.27 | F40: =Pivots!E52 -> 329000 | G40: =Pivots!F52 -> 96.5 | H40: =Pivots!G52 -> 0.96472888 | I40: =Pivots!H52 -> 380861.11 | J40: =IFERROR(E40/E39-1,"") -> -0.044723373 | K40: =IFERROR(C40/C39-1,"") -> -0.15384615 | L40: =IFERROR(E40-F40,"") -> 54727.273
B41: =Pivots!A53 -> 45992 | C41: =Pivots!B53 -> 7 | D41: =Pivots!C53 -> 2504000 | E41: =Pivots!D53 -> 357714.29 | F41: =Pivots!E53 -> 401000 | G41: =Pivots!F53 -> 63.714286 | H41: =Pivots!G53 -> 0.97114191 | I41: =Pivots!H53 -> 385387.1 | J41: =IFERROR(E41/E40-1,"") -> -0.0677903 | K41: =IFERROR(C41/C40-1,"") -> -0.36363636 | L41: =IFERROR(E41-F41,"") -> -43285.714
B42: =Pivots!A54 -> 46023 | C42: =Pivots!B54 -> 18 | D42: =Pivots!C54 -> 7468000 | E42: =Pivots!D54 -> 414888.89 | F42: =Pivots!E54 -> 383000 | G42: =Pivots!F54 -> 59.294118 | H42: =Pivots!G54 -> 0.98047141 | I42: =Pivots!H54 -> 394250 | J42: =IFERROR(E42/E41-1,"") -> 0.15983316 | K42: =IFERROR(C42/C41-1,"") -> 1.5714286 | L42: =IFERROR(E42-F42,"") -> 31888.889
... B49: =Pivots!A61 -> 46235 | C49: =Pivots!B61 -> 5 | D49: =Pivots!C61 -> 2119000 | E49: =Pivots!D61 -> 423800 | F49: =Pivots!E61 -> 355000 | G49: =Pivots!F61 -> 60.8 | H49: =Pivots!G61 -> 0.98830453 | I49: =Pivots!H61 -> 350314.29 | J49: =IFERROR(E49/E48-1,"") -> 0.28146868 | K49: =IFERROR(C49/C48-1,"") -> -0.76190476 | L49: =IFERROR(E49-F49,"") -> 68800
B50: Total / Average | C50: =SUM(C30:C49) -> 250 | D50: =SUM(D30:D49) -> 97600000 | E50: =AVERAGE(d_price) -> 390400 | F50: =MEDIAN(d_price) -> 366000 | G50: =AVERAGE(d_dom) -> 57.371901 | H50: =AVERAGE(d_stl) -> 0.97491351
B51: =" Note: "&TEXT(B49,"mmm-yy")&" is a partial month (data ends "&TEXT(MAX(d_date),"d mmm yyyy")&")." -> Note: Aug-26 is a partial month (data ends 23 Aug 2026).

Sheet D2_Neighborhood
B1: 2 ▸ NEIGHBORHOOD PRICING — DRILL-DOWN
B2: How each neighborhood prices: average vs. median, premium to market, and price per square foot.
B3: ◂ Back to Dashboard | C3: ◂ Previous graph | E3: Next graph ▸ | G3: Graph 2 of 8 • use the buttons to move between graphs or return to the dashboard
B5: HIGHEST-PRICED AREA | E5: MOST AFFORDABLE AREA | H5: PRICE SPREAD (TOP vs BOTTOM) | K5: MARKET AVG PRICE
B6: =INDEX($B$30:$B$34,MATCH(MAX($E$30:$E$34),$E$30:$E$34,0)) -> Oak Hill | E6: =INDEX($B$30:$B$34,MATCH(MIN($E$30:$E$34),$E$30:$E$34,0)) -> Cedar Park | H6: =MAX($E$30:$E$34)/MIN($E$30:$E$34)-1 -> 0.72461462 | K6: =E35 -> 390400
B7: =TEXT(MAX($E$30:$E$34),"$#,##0")&" avg price" -> $4,92,621 avg price | E7: =TEXT(MIN($E$30:$E$34),"$#,##0")&" avg price" -> $2,85,641 avg price | H7: ="premium of priciest over cheapest area" -> premium of priciest over cheapest area | K7: ="Median "&TEXT(F35,"$#,##0") -> Median $3,66,000
B9: THE GRAPH | I9: KEY TAKEAWAYS (auto-generated)
I10: ="Priciest: "&INDEX($B$30:$B$34,MATCH(MAX($E$30:$E$34),$E$30:$E$34,0))&" ("&TEXT(MAX($E$30:$E$34),"$#,##0")&"); most affordable: "&INDEX($B$30:$B$34,MATCH(MIN($E$30:$E$34),$E$30:$E$34,0))&" ("&TEXT(MIN($E$30:$E$34),"$#,##0")&") — a "&TEXT(MAX($E$30:$E$34)/MIN($E$30:$E$34)-1,"0%")&" spread." -> Priciest: Oak Hill ($4,92,621); most affordable: Cedar Park ($2,85,641) — a 72% spread.
I13: ="Largest share of sales: "&INDEX($B$30:$B$34,MATCH(MAX($C$30:$C$34),$C$30:$C$34,0))&" ("&TEXT(MAX($D$30:$D$34),"0.0%")&" of all sales)." -> Largest share of sales: Riverside (24.8% of all sales).
I16: ="Widest average-vs-median gap: "&INDEX($B$30:$B$34,MATCH(MAX($G$30:$G$34),$G$30:$G$34,0))&" ("&TEXT(MAX($G$30:$G$34),"$#,##0")&") — a few expensive sales lift its average." -> Widest average-vs-median gap: Oak Hill ($42,121) — a few expensive sales lift its average.
I19: ="Best value per sq ft: "&INDEX($B$30:$B$34,MATCH(MIN($I$30:$I$34),$I$30:$I$34,0))&" ("&TEXT(MIN($I$30:$I$34),"$#,##0")&") vs "&INDEX($B$30:$B$34,MATCH(MAX($I$30:$I$34),$I$30:$I$34,0))&" ("&TEXT(MAX($I$30:$I$34),"$#,##0")&")." -> Best value per sq ft: Cedar Park ($172) vs Downtown ($297).
I22: =COUNTIF($H$30:$H$34,">0")&" of "&COUNT($H$30:$H$34)&" neighborhoods price above the market average." -> 2 of 5 neighborhoods price above the market average.
B28: DATA BEHIND THE GRAPH
B29: Neighborhood | C29: Sales | D29: % of Sales | E29: Avg Price | F29: Median Price | G29: Avg − Median | H29: Avg vs Market | I29: Avg $/sqft | J29: Avg Sq Ft | K29: Price Rank
B30: Cedar Park | C30: =COUNTIFS(d_nbhd,$B30) -> 39 | D30: =C30/C$35 -> 0.156 | E30: =IFERROR(AVERAGEIFS(d_price,d_nbhd,$B30),"") -> 285641.03 | F30: {=IFERROR(MEDIAN(IF(d_nbhd=$B30,d_price)),"")} -> 306000 | G30: =IFERROR(E30-F30,"") -> -20358.974 | H30: =IFERROR(E30/E$35-1,"") -> -0.26833754 | I30: =IFERROR(AVERAGEIFS(d_psf,d_nbhd,$B30),"") -> 172.14713 | J30: =IFERROR(AVERAGEIFS(d_sqft,d_nbhd,$B30),"") -> 1668.7179 | K30: =RANK(E30,E$30:E$34) -> 5
B31: Downtown | C31: =COUNTIFS(d_nbhd,$B31) -> 36 | D31: =C31/C$35 -> 0.144 | E31: =IFERROR(AVERAGEIFS(d_price,d_nbhd,$B31),"") -> 429972.22 | F31: {=IFERROR(MEDIAN(IF(d_nbhd=$B31,d_price)),"")} -> 407000 | G31: =IFERROR(E31-F31,"") -> 22972.222 | H31: =IFERROR(E31/E$35-1,"") -> 0.10136327 | I31: =IFERROR(AVERAGEIFS(d_psf,d_nbhd,$B31),"") -> 296.95506 | J31: =IFERROR(AVERAGEIFS(d_sqft,d_nbhd,$B31),"") -> 1458.8889 | K31: =RANK(E31,E$30:E$34) -> 2
B32: Maple Heights | C32: =COUNTIFS(d_nbhd,$B32) -> 51 | D32: =C32/C$35 -> 0.204 | E32: =IFERROR(AVERAGEIFS(d_price,d_nbhd,$B32),"") -> 336588.24 | F32: {=IFERROR(MEDIAN(IF(d_nbhd=$B32,d_price)),"")} -> 339000 | G32: =IFERROR(E32-F32,"") -> -2411.7647 | H32: =IFERROR(E32/E$35-1,"") -> -0.13783751 | I32: =IFERROR(AVERAGEIFS(d_psf,d_nbhd,$B32),"") -> 193.36796 | J32: =IFERROR(AVERAGEIFS(d_sqft,d_nbhd,$B32),"") -> 1758.2353 | K32: =RANK(E32,E$30:E$34) -> 4
B33: Oak Hill | C33: =COUNTIFS(d_nbhd,$B33) -> 58 | D33: =C33/C$35 -> 0.232 | E33: =IFERROR(AVERAGEIFS(d_price,d_nbhd,$B33),"") -> 492620.69 | F33: {=IFERROR(MEDIAN(IF(d_nbhd=$B33,d_price)),"")} -> 450500 | G33: =IFERROR(E33-F33,"") -> 42120.69 | H33: =IFERROR(E33/E$35-1,"") -> 0.26183578 | I33: =IFERROR(AVERAGEIFS(d_psf,d_nbhd,$B33),"") -> 252.82582 | J33: =IFERROR(AVERAGEIFS(d_sqft,d_nbhd,$B33),"") -> 1877.931 | K33: =RANK(E33,E$30:E$34) -> 1
B34: Riverside | C34: =COUNTIFS(d_nbhd,$B34) -> 62 | D34: =C34/C$35 -> 0.248 | E34: =IFERROR(AVERAGEIFS(d_price,d_nbhd,$B34),"") -> 383145.16 | F34: {=IFERROR(MEDIAN(IF(d_nbhd=$B34,d_price)),"")} -> 381500 | G34: =IFERROR(E34-F34,"") -> 1645.1613 | H34: =IFERROR(E34/E$35-1,"") -> -0.018583091 | I34: =IFERROR(AVERAGEIFS(d_psf,d_nbhd,$B34),"") -> 221.25059 | J34: =IFERROR(AVERAGEIFS(d_sqft,d_nbhd,$B34),"") -> 1745.1613 | K34: =RANK(E34,E$30:E$34) -> 3
B35: Market (all sales) | C35: =COUNT(d_price) -> 250 | D35: =C35/C$35 -> 1 | E35: =AVERAGE(d_price) -> 390400 | F35: =MEDIAN(d_price) -> 366000 | G35: =IFERROR(E35-F35,"") -> 24400 | H35: — | I35: =AVERAGE(d_psf) -> 225.90432 | J35: =AVERAGE(d_sqft) -> 1727.04 | K35: —
B36: ="Note: "&COUNTIF(d_nbhd,"Unknown")&" sales have an unknown neighborhood — they count in the Market row only." -> Note: 4 sales have an unknown neighborhood — they count in the Market row only.
B38: DRILL-DOWN ▸ pick a neighborhood to see its full profile
B39: Choose neighborhood ▸ | C39: Oak Hill
B41: Metric | C41: Selected | D41: Market | E41: Difference | G41: Type mix | H41: Sales | I41: Avg price | J41: Avg $/sqft
B42: Sales (n) | C42: =COUNTIFS(d_nbhd,$C$39) -> 58 | D42: =COUNT(d_price) -> 250 | E42: =IFERROR(C42-D42,"") -> -192 | G42: Condo | H42: =COUNTIFS(d_nbhd,$C$39,d_type,G42) -> 11 | I42: =IFERROR(AVERAGEIFS(d_price,d_nbhd,$C$39,d_type,G42),"—") -> 308090.91 | J42: =IFERROR(AVERAGEIFS(d_psf,d_nbhd,$C$39,d_type,G42),"—") -> 236.25446
B43: Avg price | C43: =IFERROR(AVERAGEIFS(d_price,d_nbhd,$C$39),"") -> 492620.69 | D43: =AVERAGE(d_price) -> 390400 | E43: =IFERROR(C43-D43,"") -> 102220.69 | G43: Single Family | H43: =COUNTIFS(d_nbhd,$C$39,d_type,G43) -> 37 | I43: =IFERROR(AVERAGEIFS(d_price,d_nbhd,$C$39,d_type,G43),"—") -> 572756.76 | J43: =IFERROR(AVERAGEIFS(d_psf,d_nbhd,$C$39,d_type,G43),"—") -> 258.38389
B44: Median price | C44: {=IFERROR(MEDIAN(IF(d_nbhd=$C$39,d_price)),"")} -> 450500 | D44: =MEDIAN(d_price) -> 366000 | E44: =IFERROR(C44-D44,"") -> 84500 | G44: Townhouse | H44: =COUNTIFS(d_nbhd,$C$39,d_type,G44) -> 10 | I44: =IFERROR(AVERAGEIFS(d_price,d_nbhd,$C$39,d_type,G44),"—") -> 399100 | J44: =IFERROR(AVERAGEIFS(d_psf,d_nbhd,$C$39,d_type,G44),"—") -> 250.48942
B45: Avg $/sqft | C45: =IFERROR(AVERAGEIFS(d_psf,d_nbhd,$C$39),"") -> 252.82582 | D45: =AVERAGE(d_psf) -> 225.90432 | E45: =IFERROR(C45-D45,"") -> 26.921492
B46: Avg sq ft | C46: =IFERROR(AVERAGEIFS(d_sqft,d_nbhd,$C$39),"") -> 1877.931 | D46: =AVERAGE(d_sqft) -> 1727.04 | E46: =IFERROR(C46-D46,"") -> 150.89103 | G46: ="Top type: "&INDEX(G42:G44,MATCH(MAX(H42:H44),H42:H44,0))&" ("&TEXT(MAX(H42:H44)/C42,"0%")&" of this area's sales)" -> Top type: Single Family (64% of this area's sales)
B47: Avg bedrooms | C47: =IFERROR(AVERAGEIFS(d_beds,d_nbhd,$C$39),"") -> 3.1896552 | D47: =AVERAGE(d_beds) -> 2.988 | E47: =IFERROR(C47-D47,"") -> 0.20165517
B48: Avg days on market | C48: =IFERROR(AVERAGEIFS(d_dom,d_nbhd,$C$39),"") -> 58.142857 | D48: =AVERAGE(d_dom) -> 57.371901 | E48: =IFERROR(C48-D48,"") -> 0.77095632
B49: Sale-to-list | C49: =IFERROR(AVERAGEIFS(d_stl,d_nbhd,$C$39),"") -> 0.97342954 | D49: =AVERAGE(d_stl) -> 0.97491351 | E49: =IFERROR(C49-D49,"") -> -0.0014839709
B50: % sold above list | C50: =IFERROR(COUNTIFS(d_nbhd,$C$39,d_stl,">1")/COUNTIFS(d_nbhd,$C$39),"") -> 0.13793103 | D50: =COUNTIF(d_stl,">1")/COUNT(d_stl) -> 0.192 | E50: =IFERROR(C50-D50,"") -> -0.054068966

Sheet D3_Speed_Negotiation
B1: 3 ▸ SPEED & NEGOTIATION — DRILL-DOWN
B2: How fast each neighborhood sells and how much room buyers have to negotiate.
B3: ◂ Back to Dashboard | C3: ◂ Previous graph | E3: Next graph ▸ | G3: Graph 3 of 8 • use the buttons to move between graphs or return to the dashboard
B5: FASTEST-SELLING AREA | E5: SLOWEST-SELLING AREA | H5: MARKET SALE-TO-LIST | K5: % SOLD ABOVE ASKING
B6: =INDEX($B$30:$B$34,MATCH(MIN($D$30:$D$34),$D$30:$D$34,0)) -> Downtown | E6: =INDEX($B$30:$B$34,MATCH(MAX($D$30:$D$34),$D$30:$D$34,0)) -> Cedar Park | H6: =F35 -> 0.97491351 | K6: =G35 -> 0.192
B7: =TEXT(MIN($D$30:$D$34),"0.0")&" days on market" -> 52.8 days on market | E7: =TEXT(MAX($D$30:$D$34),"0.0")&" days on market" -> 67.6 days on market | H7: ="Median DOM "&TEXT(E35,"0")&" days" -> Median DOM 53 days | K7: =TEXT(H35,"0%")&" sold below" -> 79% sold below
B9: THE GRAPH | I9: KEY TAKEAWAYS (auto-generated)
I10: ="Fastest: "&INDEX($B$30:$B$34,MATCH(MIN($D$30:$D$34),$D$30:$D$34,0))&" ("&TEXT(MIN($D$30:$D$34),"0.0")&" days); slowest: "&INDEX($B$30:$B$34,MATCH(MAX($D$30:$D$34),$D$30:$D$34,0))&" ("&TEXT(MAX($D$30:$D$34),"0.0")&" days) — a "&TEXT(MAX($D$30:$D$34)-MIN($D$30:$D$34),"0")&"-day difference." -> Fastest: Downtown (52.8 days); slowest: Cedar Park (67.6 days) — a 15-day difference.
I13: ="Sale-to-list runs from "&TEXT(MIN($F$30:$F$34),"0.0%")&" ("&INDEX($B$30:$B$34,MATCH(MIN($F$30:$F$34),$F$30:$F$34,0))&") to "&TEXT(MAX($F$30:$F$34),"0.0%")&" ("&INDEX($B$30:$B$34,MATCH(MAX($F$30:$F$34),$F$30:$F$34,0))&") — a "&TEXT((MAX($F$30:$F$34)-MIN($F$30:$F$34))*100,"0.0")&"-point spread." -> Sale-to-list runs from 97.1% (Maple Heights) to 97.7% (Downtown) — a 0.6-point spread.
I16: ="Most above-asking sales: "&INDEX($B$30:$B$34,MATCH(MAX($G$30:$G$34),$G$30:$G$34,0))&" ("&TEXT(MAX($G$30:$G$34),"0%")&" of its sales closed over list)." -> Most above-asking sales: Riverside (26% of its sales closed over list).
I19: ="Market median time on market is "&TEXT(E35,"0")&" days vs a mean of "&TEXT(D35,"0.0")&IF(D35>E35," — a few very slow listings pull the mean up.",".") -> Market median time on market is 53 days vs a mean of 57.4 — a few very slow listings pull the mean up.
I22: ="When homes sell below list, the average discount is "&TEXT(-Analysis!B64,"$#,##0")&"." -> When homes sell below list, the average discount is $14,782.
B28: DATA BEHIND THE GRAPH
B29: Neighborhood | C29: Sales | D29: Avg DOM (days) | E29: Median DOM | F29: Sale-to-List | G29: % Sold Above List | H29: % Sold Below List | I29: Avg $ vs List | J29: Avg Comm. %
B30: Cedar Park | C30: =COUNTIFS(d_nbhd,$B30) -> 39 | D30: =IFERROR(AVERAGEIFS(d_dom,d_nbhd,$B30),"") -> 67.578947 | E30: {=IFERROR(MEDIAN(IF((d_nbhd=$B30)*(d_dom<>""),d_dom)),"")} -> 59.5 | F30: =IFERROR(AVERAGEIFS(d_stl,d_nbhd,$B30),"") -> 0.97450341 | G30: =IFERROR(COUNTIFS(d_nbhd,$B30,d_stl,">1")/COUNTIFS(d_nbhd,$B30),"") -> 0.15384615 | H30: =IFERROR(COUNTIFS(d_nbhd,$B30,d_stl,"<1")/COUNTIFS(d_nbhd,$B30),"") -> 0.79487179 | I30: =IFERROR(AVERAGEIFS(d_diff,d_nbhd,$B30),"") -> -7512.8205 | J30: =IFERROR(AVERAGEIFS(d_comm,d_nbhd,$B30),"") -> 2.9064865
B31: Downtown | C31: =COUNTIFS(d_nbhd,$B31) -> 36 | D31: =IFERROR(AVERAGEIFS(d_dom,d_nbhd,$B31),"") -> 52.777778 | E31: {=IFERROR(MEDIAN(IF((d_nbhd=$B31)*(d_dom<>""),d_dom)),"")} -> 49 | F31: =IFERROR(AVERAGEIFS(d_stl,d_nbhd,$B31),"") -> 0.97717766 | G31: =IFERROR(COUNTIFS(d_nbhd,$B31,d_stl,">1")/COUNTIFS(d_nbhd,$B31),"") -> 0.19444444 | H31: =IFERROR(COUNTIFS(d_nbhd,$B31,d_stl,"<1")/COUNTIFS(d_nbhd,$B31),"") -> 0.80555556 | I31: =IFERROR(AVERAGEIFS(d_diff,d_nbhd,$B31),"") -> -10805.556 | J31: =IFERROR(AVERAGEIFS(d_comm,d_nbhd,$B31),"") -> 2.8785714
B32: Maple Heights | C32: =COUNTIFS(d_nbhd,$B32) -> 51 | D32: =IFERROR(AVERAGEIFS(d_dom,d_nbhd,$B32),"") -> 54.170213 | E32: {=IFERROR(MEDIAN(IF((d_nbhd=$B32)*(d_dom<>""),d_dom)),"")} -> 52 | F32: =IFERROR(AVERAGEIFS(d_stl,d_nbhd,$B32),"") -> 0.97104751 | G32: =IFERROR(COUNTIFS(d_nbhd,$B32,d_stl,">1")/COUNTIFS(d_nbhd,$B32),"") -> 0.19607843 | H32: =IFERROR(COUNTIFS(d_nbhd,$B32,d_stl,"<1")/COUNTIFS(d_nbhd,$B32),"") -> 0.78431373 | I32: =IFERROR(AVERAGEIFS(d_diff,d_nbhd,$B32),"") -> -9921.5686 | J32: =IFERROR(AVERAGEIFS(d_comm,d_nbhd,$B32),"") -> 2.9588636
B33: Oak Hill | C33: =COUNTIFS(d_nbhd,$B33) -> 58 | D33: =IFERROR(AVERAGEIFS(d_dom,d_nbhd,$B33),"") -> 58.142857 | E33: {=IFERROR(MEDIAN(IF((d_nbhd=$B33)*(d_dom<>""),d_dom)),"")} -> 57 | F33: =IFERROR(AVERAGEIFS(d_stl,d_nbhd,$B33),"") -> 0.97342954 | G33: =IFERROR(COUNTIFS(d_nbhd,$B33,d_stl,">1")/COUNTIFS(d_nbhd,$B33),"") -> 0.13793103 | H33: =IFERROR(COUNTIFS(d_nbhd,$B33,d_stl,"<1")/COUNTIFS(d_nbhd,$B33),"") -> 0.84482759 | I33: =IFERROR(AVERAGEIFS(d_diff,d_nbhd,$B33),"") -> -14172.414 | J33: =IFERROR(AVERAGEIFS(d_comm,d_nbhd,$B33),"") -> 2.9075439
B34: Riverside | C34: =COUNTIFS(d_nbhd,$B34) -> 62 | D34: =IFERROR(AVERAGEIFS(d_dom,d_nbhd,$B34),"") -> 54.770492 | E34: {=IFERROR(MEDIAN(IF((d_nbhd=$B34)*(d_dom<>""),d_dom)),"")} -> 48 | F34: =IFERROR(AVERAGEIFS(d_stl,d_nbhd,$B34),"") -> 0.97690998 | G34: =IFERROR(COUNTIFS(d_nbhd,$B34,d_stl,">1")/COUNTIFS(d_nbhd,$B34),"") -> 0.25806452 | H34: =IFERROR(COUNTIFS(d_nbhd,$B34,d_stl,"<1")/COUNTIFS(d_nbhd,$B34),"") -> 0.74193548 | I34: =IFERROR(AVERAGEIFS(d_diff,d_nbhd,$B34),"") -> -8451.6129 | J34: =IFERROR(AVERAGEIFS(d_comm,d_nbhd,$B34),"") -> 2.9426316
B35: Market (all sales) | C35: =COUNT(d_price) -> 250 | D35: =AVERAGE(d_dom) -> 57.371901 | E35: =MEDIAN(d_dom) -> 53 | F35: =AVERAGE(d_stl) -> 0.97491351 | G35: =COUNTIF(d_stl,">1")/COUNT(d_stl) -> 0.192 | H35: =COUNTIF(d_stl,"<1")/COUNT(d_stl) -> 0.788 | I35: =AVERAGE(d_diff) -> -10156 | J35: =AVERAGE(d_comm) -> 2.9224893
B37: Does waiting cost / save money? | C37: Sales | D37: Avg Sale-to-List | E37: Avg Price
B38: =Analysis!A67 -> Fast (≤ 40 days) | C38: =Analysis!D67 -> 56 | D38: =Analysis!E67 -> 0.97755475 | E38: =Analysis!F67 -> 385857.14
B39: =Analysis!A68 -> Normal (41-60) | C39: =Analysis!D68 -> 97 | D39: =Analysis!E68 -> 0.97814724 | E39: =Analysis!F68 -> 386391.75
B40: =Analysis!A69 -> Slow (61-90) | C40: =Analysis!D69 -> 69 | D40: =Analysis!E69 -> 0.96946971 | E40: =Analysis!F69 -> 408434.78
B41: =Analysis!A70 -> Very slow (> 90) | C41: =Analysis!D70 -> 20 | D41: =Analysis!E70 -> 0.97271204 | E41: =Analysis!F70 -> 381800

Sheet D4_Property_Type
B1: 4 ▸ PROPERTY TYPE — DRILL-DOWN
B2: Condos, single-family homes and townhouses compared on price, size, speed and negotiation.
B3: ◂ Back to Dashboard | C3: ◂ Previous graph | E3: Next graph ▸ | G3: Graph 4 of 8 • use the buttons to move between graphs or return to the dashboard
B5: LARGEST SEGMENT | E5: SINGLE FAMILY vs CONDO | H5: HIGHEST $/SQ FT | K5: MARKET MEDIAN PRICE
B6: =INDEX($B$30:$B$32,MATCH(MAX($C$30:$C$32),$C$30:$C$32,0)) -> Single Family | E6: =E31/E30-1 -> 0.68639567 | H6: =INDEX($B$30:$B$32,MATCH(MAX($G$30:$G$32),$G$30:$G$32,0)) -> Condo | K6: =F33 -> 366000
B7: =TEXT(MAX($D$30:$D$32),"0%")&" of all sales" -> 58% of all sales | E7: ="average price premium" -> average price premium | H7: =TEXT(MAX($G$30:$G$32),"$#,##0")&" per sq ft" -> $236 per sq ft | K7: ="Avg "&TEXT(E33,"$#,##0") -> Avg $3,90,400
B9: THE GRAPH | I9: KEY TAKEAWAYS (auto-generated)
I10: ="Largest segment: "&INDEX($B$30:$B$32,MATCH(MAX($C$30:$C$32),$C$30:$C$32,0))&" — "&TEXT(MAX($D$30:$D$32),"0%")&" of sales ("&MAX($C$30:$C$32)&" homes)." -> Largest segment: Single Family — 58% of sales (146 homes).
I13: ="Single Family averages "&TEXT(E31,"$#,##0")&", "&TEXT(E31/E30-1,"0%")&" above condos ("&TEXT(E30,"$#,##0")&"); townhouses sit at "&TEXT(E32,"$#,##0")&"." -> Single Family averages $4,52,575, 69% above condos ($2,68,368); townhouses sit at $3,45,255.
I16: ="Part of that gap is space: Single Family homes average "&TEXT(H31,"#,##0")&" sq ft vs "&TEXT(H30,"#,##0")&" for condos. Per sq ft, "&INDEX($B$30:$B$32,MATCH(MAX($G$30:$G$32),$G$30:$G$32,0))&" leads ("&TEXT(MAX($G$30:$G$32),"$#,##0")&")." -> Part of that gap is space: Single Family homes average 1,981 sq ft vs 1,158 for condos. Per sq ft, Condo leads ($236).
I19: ="Fastest to sell: "&INDEX($B$30:$B$32,MATCH(MIN($J$30:$J$32),$J$30:$J$32,0))&" ("&TEXT(MIN($J$30:$J$32),"0.0")&" days on market)." -> Fastest to sell: Townhouse (54.3 days on market).
I22: ="Highest sale-to-list: "&INDEX($B$30:$B$32,MATCH(MAX($K$30:$K$32),$K$30:$K$32,0))&" ("&TEXT(MAX($K$30:$K$32),"0.0%")&"); lowest: "&INDEX($B$30:$B$32,MATCH(MIN($K$30:$K$32),$K$30:$K$32,0))&" ("&TEXT(MIN($K$30:$K$32),"0.0%")&")." -> Highest sale-to-list: Townhouse (97.6%); lowest: Condo (97.3%).
B28: DATA BEHIND THE GRAPH
B29: Property Type | C29: Sales | D29: % of Sales | E29: Avg Price | F29: Median Price | G29: Avg $/sqft | H29: Avg Sq Ft | I29: Avg Beds | J29: Avg DOM (days) | K29: Sale-to-List | L29: Price Rank
B30: Condo | C30: =COUNTIFS(d_type,$B30) -> 57 | D30: =C30/C$33 -> 0.228 | E30: =IFERROR(AVERAGEIFS(d_price,d_type,$B30),"") -> 268368.42 | F30: {=IFERROR(MEDIAN(IF(d_type=$B30,d_price)),"")} -> 263000 | G30: =IFERROR(AVERAGEIFS(d_psf,d_type,$B30),"") -> 235.81426 | H30: =IFERROR(AVERAGEIFS(d_sqft,d_type,$B30),"") -> 1157.5439 | I30: =IFERROR(AVERAGEIFS(d_beds,d_type,$B30),"") -> 1.6315789 | J30: =IFERROR(AVERAGEIFS(d_dom,d_type,$B30),"") -> 59.636364 | K30: =IFERROR(AVERAGEIFS(d_stl,d_type,$B30),"") -> 0.97307063 | L30: =RANK(E30,E$30:E$32) -> 3
B31: Single Family | C31: =COUNTIFS(d_type,$B31) -> 146 | D31: =C31/C$33 -> 0.584 | E31: =IFERROR(AVERAGEIFS(d_price,d_type,$B31),"") -> 452575.34 | F31: {=IFERROR(MEDIAN(IF(d_type=$B31,d_price)),"")} -> 428500 | G31: =IFERROR(AVERAGEIFS(d_psf,d_type,$B31),"") -> 225.45494 | H31: =IFERROR(AVERAGEIFS(d_sqft,d_type,$B31),"") -> 1980.8219 | I31: =IFERROR(AVERAGEIFS(d_beds,d_type,$B31),"") -> 3.5821918 | J31: =IFERROR(AVERAGEIFS(d_dom,d_type,$B31),"") -> 57.471831 | K31: =IFERROR(AVERAGEIFS(d_stl,d_type,$B31),"") -> 0.97535231 | L31: =RANK(E31,E$30:E$32) -> 1
B32: Townhouse | C32: =COUNTIFS(d_type,$B32) -> 47 | D32: =C32/C$33 -> 0.188 | E32: =IFERROR(AVERAGEIFS(d_price,d_type,$B32),"") -> 345255.32 | F32: {=IFERROR(MEDIAN(IF(d_type=$B32,d_price)),"")} -> 339000 | G32: =IFERROR(AVERAGEIFS(d_psf,d_type,$B32),"") -> 215.28185 | H32: =IFERROR(AVERAGEIFS(d_sqft,d_type,$B32),"") -> 1629.3617 | I32: =IFERROR(AVERAGEIFS(d_beds,d_type,$B32),"") -> 2.787234 | J32: =IFERROR(AVERAGEIFS(d_dom,d_type,$B32),"") -> 54.288889 | K32: =IFERROR(AVERAGEIFS(d_stl,d_type,$B32),"") -> 0.97578539 | L32: =RANK(E32,E$30:E$32) -> 2
B33: Market (all sales) | C33: =COUNT(d_price) -> 250 | D33: =C33/C$33 -> 1 | E33: =AVERAGE(d_price) -> 390400 | F33: =MEDIAN(d_price) -> 366000 | G33: =AVERAGE(d_psf) -> 225.90432 | H33: =AVERAGE(d_sqft) -> 1727.04 | I33: =AVERAGE(d_beds) -> 2.988 | J33: =AVERAGE(d_dom) -> 57.371901 | K33: =AVERAGE(d_stl) -> 0.97491351 | L33: —
B36: DRILL-DOWN ▸ pick a property type to see where it sells
B37: Choose property type ▸ | C37: Single Family
B39: Neighborhood | C39: Sales | D39: % of this type | E39: Avg Price | F39: Avg $/sqft | G39: Avg DOM | H39: Sale-to-List
B40: Cedar Park | C40: =COUNTIFS(d_type,$C$37,d_nbhd,$B40) -> 25 | D40: =C40/COUNTIFS(d_type,$C$37) -> 0.17123288 | E40: =IFERROR(AVERAGEIFS(d_price,d_type,$C$37,d_nbhd,$B40),"—") -> 333120 | F40: =IFERROR(AVERAGEIFS(d_psf,d_type,$C$37,d_nbhd,$B40),"—") -> 177.64611 | G40: =IFERROR(AVERAGEIFS(d_dom,d_type,$C$37,d_nbhd,$B40),"—") -> 60.24 | H40: =IFERROR(AVERAGEIFS(d_stl,d_type,$C$37,d_nbhd,$B40),"—") -> 0.97720659
B41: Downtown | C41: =COUNTIFS(d_type,$C$37,d_nbhd,$B41) -> 13 | D41: =C41/COUNTIFS(d_type,$C$37) -> 0.089041096 | E41: =IFERROR(AVERAGEIFS(d_price,d_type,$C$37,d_nbhd,$B41),"—") -> 576692.31 | F41: =IFERROR(AVERAGEIFS(d_psf,d_type,$C$37,d_nbhd,$B41),"—") -> 305.97859 | G41: =IFERROR(AVERAGEIFS(d_dom,d_type,$C$37,d_nbhd,$B41),"—") -> 52.846154 | H41: =IFERROR(AVERAGEIFS(d_stl,d_type,$C$37,d_nbhd,$B41),"—") -> 0.97881131
B42: Maple Heights | C42: =COUNTIFS(d_type,$C$37,d_nbhd,$B42) -> 30 | D42: =C42/COUNTIFS(d_type,$C$37) -> 0.20547945 | E42: =IFERROR(AVERAGEIFS(d_price,d_type,$C$37,d_nbhd,$B42),"—") -> 376633.33 | F42: =IFERROR(AVERAGEIFS(d_psf,d_type,$C$37,d_nbhd,$B42),"—") -> 197.9114 | G42: =IFERROR(AVERAGEIFS(d_dom,d_type,$C$37,d_nbhd,$B42),"—") -> 53.035714 | H42: =IFERROR(AVERAGEIFS(d_stl,d_type,$C$37,d_nbhd,$B42),"—") -> 0.97223216
B43: Oak Hill | C43: =COUNTIFS(d_type,$C$37,d_nbhd,$B43) -> 37 | D43: =C43/COUNTIFS(d_type,$C$37) -> 0.25342466 | E43: =IFERROR(AVERAGEIFS(d_price,d_type,$C$37,d_nbhd,$B43),"—") -> 572756.76 | F43: =IFERROR(AVERAGEIFS(d_psf,d_type,$C$37,d_nbhd,$B43),"—") -> 258.38389 | G43: =IFERROR(AVERAGEIFS(d_dom,d_type,$C$37,d_nbhd,$B43),"—") -> 58.571429 | H43: =IFERROR(AVERAGEIFS(d_stl,d_type,$C$37,d_nbhd,$B43),"—") -> 0.97163473
B44: Riverside | C44: =COUNTIFS(d_type,$C$37,d_nbhd,$B44) -> 39 | D44: =C44/COUNTIFS(d_type,$C$37) -> 0.26712329 | E44: =IFERROR(AVERAGEIFS(d_price,d_type,$C$37,d_nbhd,$B44),"—") -> 434128.21 | F44: =IFERROR(AVERAGEIFS(d_psf,d_type,$C$37,d_nbhd,$B44),"—") -> 221.06576 | G44: =IFERROR(AVERAGEIFS(d_dom,d_type,$C$37,d_nbhd,$B44),"—") -> 58.435897 | H44: =IFERROR(AVERAGEIFS(d_stl,d_type,$C$37,d_nbhd,$B44),"—") -> 0.97775109

Sheet D5_Price_Distribution
B1: 5 ▸ PRICE DISTRIBUTION — DRILL-DOWN
B2: How sale prices are distributed across bands, with percentiles and the skew created by luxury sales.
B3: ◂ Back to Dashboard | C3: ◂ Previous graph | E3: Next graph ▸ | G3: Graph 5 of 8 • use the buttons to move between graphs or return to the dashboard
B5: MOST COMMON PRICE BAND | E5: MEDIAN PRICE | H5: SHARE UNDER $300K | K5: SHARE $600K AND UP
B6: =INDEX(B30:B36,MATCH(MAX(C30:C36),C30:C36,0)) -> $300-400K | E6: =L32 -> 366000 | H6: =COUNTIF(d_price,"<300000")/COUNT(d_price) -> 0.256 | K6: =COUNTIF(d_price,">=600000")/COUNT(d_price) -> 0.06
B7: =MAX(C30:C36)&" homes ("&TEXT(MAX(C30:C36)/C37,"0%")&")" -> 89 homes (36%) | E7: ="Mean "&TEXT(L35,"$#,##0") -> Mean $3,90,400 | H7: ="entry-level homes" -> entry-level homes | K7: ="90th percentile = "&TEXT(L34,"$#,##0") -> 90th percentile = $5,28,800
B9: THE GRAPH | I9: KEY TAKEAWAYS (auto-generated)
I10: ="Most common band: "&INDEX(B30:B36,MATCH(MAX(C30:C36),C30:C36,0))&" ("&MAX(C30:C36)&" homes, "&TEXT(MAX(C30:C36)/C37,"0%")&" of sales)." -> Most common band: $300-400K (89 homes, 36% of sales).
I13: ="The middle 50% of homes sold between "&TEXT(L31,"$#,##0")&" and "&TEXT(L33,"$#,##0")&" (IQR "&TEXT(L37,"$#,##0")&")." -> The middle 50% of homes sold between $2,97,250 and $4,50,000 (IQR $1,52,750).
I16: ="Mean ("&TEXT(L35,"$#,##0")&") is "&TEXT(L35/L32-1,"0.0%")&IF(L35>L32," above"," below")&" the median ("&TEXT(L32,"$#,##0")&"); skewness "&TEXT(L38,"0.0")&IF(L38>1," = strong right tail from luxury sales."," = fairly balanced.") -> Mean ($3,90,400) is 6.7% above the median ($3,66,000); skewness 9.2 = strong right tail from luxury sales.
I19: ="Entry-level (<$300K) is "&TEXT(COUNTIF(d_price,"<300000")/COUNT(d_price),"0%")&" of sales vs only "&TEXT(COUNTIF(d_price,">=600000")/COUNT(d_price),"0%")&" at $600K+." -> Entry-level (<$300K) is 26% of sales vs only 6% at $600K+.
I22: ="Price per sq ft goes from "&TEXT(F30,"$#,##0")&" in the lowest band to "&TEXT(F36,"$#,##0")&" in the top band." -> Price per sq ft goes from $209 in the lowest band to $416 in the top band.
B28: DATA BEHIND THE GRAPH
B29: Price Band | C29: Sales | D29: % of Sales | E29: Cumulative % | F29: Avg $/sqft | G29: Avg DOM | H29: Avg Sq Ft | J29: Price statistic | L29: Value
B30: =Pivots!A66 -> Under $200K | C30: =Pivots!C66 -> 17 | D30: =Pivots!D66 -> 0.068 | E30: =SUM(D$30:D30) -> 0.068 | F30: =Pivots!E66 -> 208.59442 | G30: =Pivots!F66 -> 69.705882 | H30: =IFERROR(AVERAGEIFS(d_sqft,d_band,B30),"") -> 821.76471 | J30: 10th percentile | L30: =PERCENTILE(d_price,0.1) -> 231800
B31: =Pivots!A67 -> $200-300K | C31: =Pivots!C67 -> 47 | D31: =Pivots!D67 -> 0.188 | E31: =SUM(D$30:D31) -> 0.256 | F31: =Pivots!E67 -> 200.79541 | G31: =Pivots!F67 -> 64.744186 | H31: =IFERROR(AVERAGEIFS(d_sqft,d_band,B31),"") -> 1350.6383 | J31: 25th percentile (Q1) | L31: =QUARTILE(d_price,1) -> 297250
B32: =Pivots!A68 -> $300-400K | C32: =Pivots!C68 -> 89 | D32: =Pivots!D68 -> 0.356 | E32: =SUM(D$30:D32) -> 0.612 | F32: =Pivots!E68 -> 216.53975 | G32: =Pivots!F68 -> 54.747126 | H32: =IFERROR(AVERAGEIFS(d_sqft,d_band,B32),"") -> 1668.0899 | J32: Median | L32: =MEDIAN(d_price) -> 366000
B33: =Pivots!A69 -> $400-500K | C33: =Pivots!C69 -> 57 | D33: =Pivots!D69 -> 0.228 | E33: =SUM(D$30:D33) -> 0.84 | F33: =Pivots!E69 -> 239.24878 | G33: =Pivots!F69 -> 53.836364 | H33: =IFERROR(AVERAGEIFS(d_sqft,d_band,B33),"") -> 1938.0702 | J33: 75th percentile (Q3) | L33: =QUARTILE(d_price,3) -> 450000
B34: =Pivots!A70 -> $500-600K | C34: =Pivots!C70 -> 25 | D34: =Pivots!D70 -> 0.1 | E34: =SUM(D$30:D34) -> 0.94 | F34: =Pivots!E70 -> 248.82454 | G34: =Pivots!F70 -> 54.92 | H34: =IFERROR(AVERAGEIFS(d_sqft,d_band,B34),"") -> 2184 | J34: 90th percentile | L34: =PERCENTILE(d_price,0.9) -> 528800
B35: =Pivots!A71 -> $600-800K | C35: =Pivots!C71 -> 13 | D35: =Pivots!D71 -> 0.052 | E35: =SUM(D$30:D35) -> 0.992 | F35: =Pivots!E71 -> 271.61688 | G35: =Pivots!F71 -> 54.769231 | H35: =IFERROR(AVERAGEIFS(d_sqft,d_band,B35),"") -> 2438.4615 | J35: Mean | L35: =AVERAGE(d_price) -> 390400
B36: =Pivots!A72 -> $800K+ | C36: =Pivots!C72 -> 2 | D36: =Pivots!D72 -> 0.008 | E36: =SUM(D$30:D36) -> 1 | F36: =Pivots!E72 -> 415.86987 | G36: =Pivots!F72 -> 53 | H36: =IFERROR(AVERAGEIFS(d_sqft,d_band,B36),"") -> 4540 | J36: Std deviation | L36: =STDEV(d_price) -> 222755.98
B37: Total | C37: =SUM(C30:C36) -> 250 | D37: =SUM(D30:D36) -> 1 | J37: Interquartile range | L37: =QUARTILE(d_price,3)-QUARTILE(d_price,1) -> 152750
B38: Band limits are editable (blue cells) on the Pivots sheet, section 6. | J38: Skewness | L38: =SKEW(d_price) -> 9.1541078

Sheet D6_Size_vs_Price
B1: 6 ▸ SIZE VS. PRICE — DRILL-DOWN
B2: How living area relates to price: size bands, regression, correlations and a price estimator.
B3: ◂ Back to Dashboard | C3: ◂ Previous graph | E3: Next graph ▸ | G3: Graph 6 of 8 • use the buttons to move between graphs or return to the dashboard
B5: CORRELATION (SQ FT vs PRICE) | E5: EXTRA PRICE PER SQ FT | H5: R² (EXCL. OUTLIERS) | K5: MEDIAN LIVING AREA
B6: =Analysis!B30 -> 0.79506555 | E6: =Analysis!C42 -> 183.53507 | H6: =Analysis!C44 -> 0.5861835 | K6: =MEDIAN(d_sqft) -> 1740
B7: =Analysis!C30&" relationship" -> Strong relationship | E7: ="outliers excluded" -> outliers excluded | H7: ="of price variation explained by size" -> of price variation explained by size | K7: ="sq ft (typical home)" -> sq ft (typical home)
B9: THE GRAPH | I9: KEY TAKEAWAYS (auto-generated)
I10: ="Square footage explains about "&TEXT(Analysis!C44,"0%")&" of price variation; each extra sq ft adds ≈ "&TEXT(Analysis!C42,"$#,##0")&"." -> Square footage explains about 59% of price variation; each extra sq ft adds ≈ $184.
I13: ="Average $/sq ft goes from "&TEXT(G30,"$#,##0")&" (under 1,000 sq ft) to "&TEXT(G34,"$#,##0")&" (2,500+)"&IF(G34>G30,": bigger homes also carry a higher price per sq ft.",": smaller homes carry a higher price per sq ft (typical of condos).") -> Average $/sq ft goes from $245 (under 1,000 sq ft) to $227 (2,500+): smaller homes carry a higher price per sq ft (typical of condos).
I16: ="Lot size (r = "&TEXT(Analysis!B31,"0.00")&") and bedrooms (r = "&TEXT(Analysis!B32,"0.00")&") also track price, but they overlap with size." -> Lot size (r = 0.78) and bedrooms (r = 0.54) also track price, but they overlap with size.
I19: ="Year built shows "&IF(ABS(Analysis!B35)<0.2,"almost no","some")&" relationship with price (r = "&TEXT(Analysis!B35,"0.00")&")." -> Year built shows almost no relationship with price (r = 0.12).
I22: ="Even with sq ft, estimates are off by ≈ "&TEXT(Analysis!C45,"$#,##0")&" on average — location and type matter too." -> Even with sq ft, estimates are off by ≈ $74,997 on average — location and type matter too.
B28: DATA BEHIND THE GRAPH
B29: Size Band | C29: From (sq ft) | D29: To (sq ft) | E29: Sales | F29: Avg Price | G29: Avg $/sqft | H29: Avg Beds | I29: Avg DOM | J29: Δ Price vs prev band
B30: Under 1,000 | C30: 0 | D30: 999 | E30: =COUNTIFS(d_sqft,">="&$C30,d_sqft,"<="&$D30) -> 24 | F30: =IFERROR(AVERAGEIFS(d_price,d_sqft,">="&$C30,d_sqft,"<="&$D30),"") -> 201541.67 | G30: =IFERROR(AVERAGEIFS(d_psf,d_sqft,">="&$C30,d_sqft,"<="&$D30),"") -> 245.00888 | H30: =IFERROR(AVERAGEIFS(d_beds,d_sqft,">="&$C30,d_sqft,"<="&$D30),"") -> 1.0833333 | I30: =IFERROR(AVERAGEIFS(d_dom,d_sqft,">="&$C30,d_sqft,"<="&$D30),"") -> 66.916667 | J30: —
B31: 1,000 - 1,499 | C31: 1000 | D31: 1499 | E31: =COUNTIFS(d_sqft,">="&$C31,d_sqft,"<="&$D31) -> 56 | F31: =IFERROR(AVERAGEIFS(d_price,d_sqft,">="&$C31,d_sqft,"<="&$D31),"") -> 308196.43 | G31: =IFERROR(AVERAGEIFS(d_psf,d_sqft,">="&$C31,d_sqft,"<="&$D31),"") -> 239.87885 | H31: =IFERROR(AVERAGEIFS(d_beds,d_sqft,">="&$C31,d_sqft,"<="&$D31),"") -> 2.0178571 | I31: =IFERROR(AVERAGEIFS(d_dom,d_sqft,">="&$C31,d_sqft,"<="&$D31),"") -> 56.351852 | J31: =IFERROR(F31-F30,"") -> 106654.76
B32: 1,500 - 1,999 | C32: 1500 | D32: 1999 | E32: =COUNTIFS(d_sqft,">="&$C32,d_sqft,"<="&$D32) -> 105 | F32: =IFERROR(AVERAGEIFS(d_price,d_sqft,">="&$C32,d_sqft,"<="&$D32),"") -> 382342.86 | G32: =IFERROR(AVERAGEIFS(d_psf,d_sqft,">="&$C32,d_sqft,"<="&$D32),"") -> 217.45631 | H32: =IFERROR(AVERAGEIFS(d_beds,d_sqft,">="&$C32,d_sqft,"<="&$D32),"") -> 3.1142857 | I32: =IFERROR(AVERAGEIFS(d_dom,d_sqft,">="&$C32,d_sqft,"<="&$D32),"") -> 57.752475 | J32: =IFERROR(F32-F31,"") -> 74146.429
B33: 2,000 - 2,499 | C33: 2000 | D33: 2499 | E33: =COUNTIFS(d_sqft,">="&$C33,d_sqft,"<="&$D33) -> 48 | F33: =IFERROR(AVERAGEIFS(d_price,d_sqft,">="&$C33,d_sqft,"<="&$D33),"") -> 480979.17 | G33: =IFERROR(AVERAGEIFS(d_psf,d_sqft,">="&$C33,d_sqft,"<="&$D33),"") -> 218.26821 | H33: =IFERROR(AVERAGEIFS(d_beds,d_sqft,">="&$C33,d_sqft,"<="&$D33),"") -> 4.0833333 | I33: =IFERROR(AVERAGEIFS(d_dom,d_sqft,">="&$C33,d_sqft,"<="&$D33),"") -> 54.489362 | J33: =IFERROR(F33-F32,"") -> 98636.31
B34: 2,500+ | C34: 2500 | D34: 99999 | E34: =COUNTIFS(d_sqft,">="&$C34,d_sqft,"<="&$D34) -> 17 | F34: =IFERROR(AVERAGEIFS(d_price,d_sqft,">="&$C34,d_sqft,"<="&$D34),"") -> 721823.53 | G34: =IFERROR(AVERAGEIFS(d_psf,d_sqft,">="&$C34,d_sqft,"<="&$D34),"") -> 226.63915 | H34: =IFERROR(AVERAGEIFS(d_beds,d_sqft,">="&$C34,d_sqft,"<="&$D34),"") -> 5 | I34: =IFERROR(AVERAGEIFS(d_dom,d_sqft,">="&$C34,d_sqft,"<="&$D34),"") -> 52.5625 | J34: =IFERROR(F34-F33,"") -> 240844.36
B36: Regression: price = a + b × sq ft | C36: All sales | D36: Excl. outliers | F36: Correlation with price | H36: r | I36: Strength
B37: Slope b ($ per sq ft) | C37: =Analysis!B42 -> 308.03596 | D37: =Analysis!C42 -> 183.53507 | F37: =Analysis!A30 -> Living area (sq ft) | H37: =Analysis!B30 -> 0.79506555 | I37: =Analysis!C30 -> Strong
B38: Intercept a ($) | C38: =Analysis!B43 -> -141590.43 | D38: =Analysis!C43 -> 62313.48 | F38: =Analysis!A31 -> Lot size (sq ft) | H38: =Analysis!B31 -> 0.77804607 | I38: =Analysis!C31 -> Strong
B39: R² | C39: =Analysis!B44 -> 0.63212922 | D39: =Analysis!C44 -> 0.5861835 | F39: =Analysis!A32 -> Bedrooms | H39: =Analysis!B32 -> 0.53605537 | I39: =Analysis!C32 -> Moderate
B40: Std error of estimate ($) | C40: =Analysis!B45 -> 135378.86 | D40: =Analysis!C45 -> 74997.114 | F40: =Analysis!A33 -> Bathrooms | H40: =Analysis!B33 -> 0.50530782 | I40: =Analysis!C33 -> Moderate
F41: =Analysis!A34 -> Garage spaces | H41: =Analysis!B34 -> 0.32863542 | I41: =Analysis!C34 -> Weak
B42: PRICE ESTIMATOR ▸ sq ft | C42: 2000 | F42: =Analysis!A35 -> Year built | H42: =Analysis!B35 -> 0.11917736 | I42: =Analysis!C35 -> Negligible
B43: Estimated price | C43: =Analysis!C43+Analysis!C42*C42 -> 429383.61 | F43: =Analysis!A36 -> Days on market | H43: =Analysis!B36 -> -0.063011286 | I43: =Analysis!C36 -> Negligible (neg.)
B44: Likely range (±1 SE) | C44: =TEXT(C43-Analysis!C45,"$#,##0")&" – "&TEXT(C43+Analysis!C45,"$#,##0") -> $3,54,386 – $5,04,381 | F44: =Analysis!A37 -> Agent commission (%) | H44: =Analysis!B37 -> -0.18523087 | I44: =Analysis!C37 -> Negligible (neg.)
B45: Uses the outlier-free model; sq ft only — neighborhood and type would sharpen it.

Sheet D7_Condition
B1: 7 ▸ CONDITION — DRILL-DOWN
B2: How property condition relates to price, size, speed and negotiation (descriptive, not causal).
B3: ◂ Back to Dashboard | C3: ◂ Previous graph | E3: Next graph ▸ | G3: Graph 7 of 8 • use the buttons to move between graphs or return to the dashboard
B5: EXCELLENT vs POOR PRICE | E5: EXCELLENT vs POOR $/SQ FT | H5: DAYS FASTER (EXCELLENT) | K5: MOST COMMON CONDITION
B6: =E30/E33-1 -> 0.44406972 | E6: =H30/H33-1 -> 0.38972627 | H6: =I33-I30 -> 26.398361 | K6: =INDEX($B$30:$B$33,MATCH(MAX($C$30:$C$33),$C$30:$C$33,0)) -> Good
B7: =TEXT(E30,"$#,##0")&" vs "&TEXT(E33,"$#,##0") -> $4,58,952 vs $3,17,818 | E7: ="size-adjusted premium" -> size-adjusted premium | H7: ="vs Poor-condition homes" -> vs Poor-condition homes | K7: =TEXT(MAX($D$30:$D$33),"0%")&" of sales" -> 42% of sales
B9: THE GRAPH | I9: KEY TAKEAWAYS (auto-generated)
I10: ="Excellent homes average "&TEXT(E30,"$#,##0")&" vs "&TEXT(E33,"$#,##0")&" for Poor — a "&TEXT(E30/E33-1,"0%")&" gap." -> Excellent homes average $4,58,952 vs $3,17,818 for Poor — a 44% gap.
I13: =IF(G30>1.05*G33,"Part of the gap is size: Excellent homes are bigger ("&TEXT(G30,"#,##0")&" vs "&TEXT(G33,"#,##0")&" sq ft); per sq ft the gap is "&TEXT(H30/H33-1,"0%")&".","Size does not explain it: Excellent homes average "&TEXT(G30,"#,##0")&" sq ft vs "&TEXT(G33,"#,##0")&" for Poor, and the per-sq-ft gap is still "&TEXT(H30/H33-1,"0%")&".") -> Size does not explain it: Excellent homes average 1,750 sq ft vs 1,762 for Poor, and the per-sq-ft gap is still 39%.
I16: ="Time on market: Excellent "&TEXT(I30,"0")&" days vs Poor "&TEXT(I33,"0")&" days." -> Time on market: Excellent 49 days vs Poor 75 days.
I19: ="Sale-to-list: "&TEXT(J30,"0.0%")&" (Excellent) vs "&TEXT(J33,"0.0%")&" (Poor)"&IF(J30>J33+0.005," — better-condition homes keep more of their asking price.",IF(J33>J30+0.005," — poor-condition homes hold more of their asking price."," — virtually no difference in negotiating outcome.")) -> Sale-to-list: 98.0% (Excellent) vs 98.1% (Poor) — virtually no difference in negotiating outcome.
I22: ="Poor-condition homes are only "&TEXT(D33,"0.0%")&" of sales (n = "&C33&") — treat with caution. "&C34&" homes have unknown condition." -> Poor-condition homes are only 4.4% of sales (n = 11) — treat with caution. 12 homes have unknown condition.
B28: DATA BEHIND THE GRAPH
B29: Condition | C29: Sales | D29: % of Sales | E29: Avg Price | F29: Median Price | G29: Avg Sq Ft | H29: Avg $/sqft | I29: Avg DOM (days) | J29: Sale-to-List | K29: % Sold Above List
B30: Excellent | C30: =COUNTIFS(d_cond,$B30) -> 62 | D30: =C30/C$35 -> 0.248 | E30: =IFERROR(AVERAGEIFS(d_price,d_cond,$B30),"") -> 458951.61 | F30: {=IFERROR(MEDIAN(IF(d_cond=$B30,d_price)),"")} -> 405000 | G30: =IFERROR(AVERAGEIFS(d_sqft,d_cond,$B30),"") -> 1750 | H30: =IFERROR(AVERAGEIFS(d_psf,d_cond,$B30),"") -> 252.55274 | I30: =IFERROR(AVERAGEIFS(d_dom,d_cond,$B30),"") -> 48.901639 | J30: =IFERROR(AVERAGEIFS(d_stl,d_cond,$B30),"") -> 0.97978707 | K30: =IFERROR(COUNTIFS(d_cond,$B30,d_stl,">1")/COUNTIFS(d_cond,$B30),"") -> 0.22580645
B31: Good | C31: =COUNTIFS(d_cond,$B31) -> 105 | D31: =C31/C$35 -> 0.42 | E31: =IFERROR(AVERAGEIFS(d_price,d_cond,$B31),"") -> 372628.57 | F31: {=IFERROR(MEDIAN(IF(d_cond=$B31,d_price)),"")} -> 364000 | G31: =IFERROR(AVERAGEIFS(d_sqft,d_cond,$B31),"") -> 1710.9524 | H31: =IFERROR(AVERAGEIFS(d_psf,d_cond,$B31),"") -> 222.75656 | I31: =IFERROR(AVERAGEIFS(d_dom,d_cond,$B31),"") -> 52.128713 | J31: =IFERROR(AVERAGEIFS(d_stl,d_cond,$B31),"") -> 0.97112013 | K31: =IFERROR(COUNTIFS(d_cond,$B31,d_stl,">1")/COUNTIFS(d_cond,$B31),"") -> 0.16190476
B32: Fair | C32: =COUNTIFS(d_cond,$B32) -> 60 | D32: =C32/C$35 -> 0.24 | E32: =IFERROR(AVERAGEIFS(d_price,d_cond,$B32),"") -> 360083.33 | F32: {=IFERROR(MEDIAN(IF(d_cond=$B32,d_price)),"")} -> 346000 | G32: =IFERROR(AVERAGEIFS(d_sqft,d_cond,$B32),"") -> 1703.5 | H32: =IFERROR(AVERAGEIFS(d_psf,d_cond,$B32),"") -> 212.47926 | I32: =IFERROR(AVERAGEIFS(d_dom,d_cond,$B32),"") -> 72.396552 | J32: =IFERROR(AVERAGEIFS(d_stl,d_cond,$B32),"") -> 0.97609542 | K32: =IFERROR(COUNTIFS(d_cond,$B32,d_stl,">1")/COUNTIFS(d_cond,$B32),"") -> 0.2
B33: Poor | C33: =COUNTIFS(d_cond,$B33) -> 11 | D33: =C33/C$35 -> 0.044 | E33: =IFERROR(AVERAGEIFS(d_price,d_cond,$B33),"") -> 317818.18 | F33: {=IFERROR(MEDIAN(IF(d_cond=$B33,d_price)),"")} -> 315000 | G33: =IFERROR(AVERAGEIFS(d_sqft,d_cond,$B33),"") -> 1761.8182 | H33: =IFERROR(AVERAGEIFS(d_psf,d_cond,$B33),"") -> 181.72841 | I33: =IFERROR(AVERAGEIFS(d_dom,d_cond,$B33),"") -> 75.3 | J33: =IFERROR(AVERAGEIFS(d_stl,d_cond,$B33),"") -> 0.98119221 | K33: =IFERROR(COUNTIFS(d_cond,$B33,d_stl,">1")/COUNTIFS(d_cond,$B33),"") -> 0.36363636
B34: Unknown | C34: =COUNTIFS(d_cond,$B34) -> 12 | D34: =C34/C$35 -> 0.048 | E34: =IFERROR(AVERAGEIFS(d_price,d_cond,$B34),"") -> 409833.33 | F34: {=IFERROR(MEDIAN(IF(d_cond=$B34,d_price)),"")} -> 427500 | G34: =IFERROR(AVERAGEIFS(d_sqft,d_cond,$B34),"") -> 1835 | H34: =IFERROR(AVERAGEIFS(d_psf,d_cond,$B34),"") -> 223.38364 | I34: =IFERROR(AVERAGEIFS(d_dom,d_cond,$B34),"") -> 57 | J34: =IFERROR(AVERAGEIFS(d_stl,d_cond,$B34),"") -> 0.97126045 | K34: =IFERROR(COUNTIFS(d_cond,$B34,d_stl,">1")/COUNTIFS(d_cond,$B34),"") -> 0.083333333
B35: Market (all sales) | C35: =COUNT(d_price) -> 250 | D35: =C35/C$35 -> 1 | E35: =AVERAGE(d_price) -> 390400 | F35: =MEDIAN(d_price) -> 366000 | G35: =AVERAGE(d_sqft) -> 1727.04 | H35: =AVERAGE(d_psf) -> 225.90432 | I35: =AVERAGE(d_dom) -> 57.371901 | J35: =AVERAGE(d_stl) -> 0.97491351 | K35: =COUNTIF(d_stl,">1")/COUNT(d_stl) -> 0.192

Sheet D8_Bedrooms
B1: 8 ▸ BEDROOMS — DRILL-DOWN
B2: How the number of bedrooms shapes price, size and price per square foot.
B3: ◂ Back to Dashboard | C3: ◂ Previous graph | E3: Next graph ▸ | G3: Graph 8 of 8 • use the buttons to move between graphs or return to the dashboard
B5: MOST COMMON | E5: AVG STEP PER EXTRA BEDROOM | H5: 5 BR vs 3 BR PREMIUM | K5: MARKET AVG BEDROOMS
B6: =INDEX($B$30:$B$35,MATCH(MAX($C$30:$C$35),$C$30:$C$35,0))&" bedrooms" -> 3 bedrooms | E6: =AVERAGE(K31:K34) -> 85794.613 | H6: =E34/E32-1 -> 0.48625952 | K6: =AVERAGE(d_beds) -> 2.988
B7: =MAX($C$30:$C$35)&" homes ("&TEXT(MAX($D$30:$D$35),"0%")&")" -> 94 homes (38%) | E7: ="average, 1 → 5 bedrooms" -> average, 1 → 5 bedrooms | H7: =TEXT(E34,"$#,##0")&" vs "&TEXT(E32,"$#,##0") -> $5,65,364 vs $3,80,394 | K7: ="bedrooms per home" -> bedrooms per home
B9: THE GRAPH | I9: KEY TAKEAWAYS (auto-generated)
I10: ="Most homes have "&INDEX($B$30:$B$35,MATCH(MAX($C$30:$C$35),$C$30:$C$35,0))&" bedrooms ("&TEXT(MAX($D$30:$D$35),"0%")&" of sales)." -> Most homes have 3 bedrooms (38% of sales).
I13: ="Each extra bedroom adds ≈ "&TEXT(AVERAGE(K31:K34),"$#,##0")&" on average (1 → 5 BR)." -> Each extra bedroom adds ≈ $85,795 on average (1 → 5 BR).
I16: ="Living area grows from "&TEXT(G30,"#,##0")&" sq ft (1 BR) to "&TEXT(G34,"#,##0")&" sq ft (5 BR), so part of the step is simply more space." -> Living area grows from 870 sq ft (1 BR) to 2,576 sq ft (5 BR), so part of the step is simply more space.
I19: ="Price per sq ft "&IF(H34>H30,"rises","falls")&" from "&TEXT(H30,"$#,##0")&" (1 BR) to "&TEXT(H34,"$#,##0")&" (5 BR)." -> Price per sq ft falls from $252 (1 BR) to $220 (5 BR).
I22: ="Bathrooms rise from "&TEXT(I30,"0.0")&" (1 BR) to "&TEXT(I34,"0.0")&" (5 BR); the 6-BR row is a single sale ("&TEXT(E35,"$#,##0")&")." -> Bathrooms rise from 1.2 (1 BR) to 3.7 (5 BR); the 6-BR row is a single sale ($33,10,000).
B28: DATA BEHIND THE GRAPH
B29: Bedrooms | C29: Sales | D29: % of Sales | E29: Avg Price | F29: Median Price | G29: Avg Sq Ft | H29: Avg $/sqft | I29: Avg Baths | J29: Avg DOM (days) | K29: Δ Price vs prev BR | L29: Δ % vs prev BR
B30: 1 | C30: =COUNTIFS(d_beds,$B30) -> 27 | D30: =C30/C$36 -> 0.108 | E30: =IFERROR(AVERAGEIFS(d_price,d_beds,$B30),"") -> 222185.19 | F30: {=IFERROR(MEDIAN(IF(d_beds=$B30,d_price)),"")} -> 199000 | G30: =IFERROR(AVERAGEIFS(d_sqft,d_beds,$B30),"") -> 869.62963 | H30: =IFERROR(AVERAGEIFS(d_psf,d_beds,$B30),"") -> 252.12408 | I30: =IFERROR(AVERAGEIFS(d_baths,d_beds,$B30),"") -> 1.2037037 | J30: =IFERROR(AVERAGEIFS(d_dom,d_beds,$B30),"") -> 63.555556 | K30: — | L30: —
B31: 2 | C31: =COUNTIFS(d_beds,$B31) -> 51 | D31: =C31/C$36 -> 0.204 | E31: =IFERROR(AVERAGEIFS(d_price,d_beds,$B31),"") -> 302431.37 | F31: {=IFERROR(MEDIAN(IF(d_beds=$B31,d_price)),"")} -> 301000 | G31: =IFERROR(AVERAGEIFS(d_sqft,d_beds,$B31),"") -> 1301.5686 | H31: =IFERROR(AVERAGEIFS(d_psf,d_beds,$B31),"") -> 233.88435 | I31: =IFERROR(AVERAGEIFS(d_baths,d_beds,$B31),"") -> 1.7058824 | J31: =IFERROR(AVERAGEIFS(d_dom,d_beds,$B31),"") -> 57.795918 | K31: =IFERROR(E31-E30,"") -> 80246.187 | L31: =IFERROR(E31/E30-1,"") -> 0.36116804
B32: 3 | C32: =COUNTIFS(d_beds,$B32) -> 94 | D32: =C32/C$36 -> 0.376 | E32: =IFERROR(AVERAGEIFS(d_price,d_beds,$B32),"") -> 380393.62 | F32: {=IFERROR(MEDIAN(IF(d_beds=$B32,d_price)),"")} -> 372000 | G32: =IFERROR(AVERAGEIFS(d_sqft,d_beds,$B32),"") -> 1727.6596 | H32: =IFERROR(AVERAGEIFS(d_psf,d_beds,$B32),"") -> 220.32431 | I32: =IFERROR(AVERAGEIFS(d_baths,d_beds,$B32),"") -> 2.4468085 | J32: =IFERROR(AVERAGEIFS(d_dom,d_beds,$B32),"") -> 59.133333 | K32: =IFERROR(E32-E31,"") -> 77962.244 | L32: =IFERROR(E32/E31-1,"") -> 0.25778491
B33: 4 | C33: =COUNTIFS(d_beds,$B33) -> 55 | D33: =C33/C$36 -> 0.22 | E33: =IFERROR(AVERAGEIFS(d_price,d_beds,$B33),"") -> 448581.82 | F33: {=IFERROR(MEDIAN(IF(d_beds=$B33,d_price)),"")} -> 444000 | G33: =IFERROR(AVERAGEIFS(d_sqft,d_beds,$B33),"") -> 2116.7273 | H33: =IFERROR(AVERAGEIFS(d_psf,d_beds,$B33),"") -> 212.24755 | I33: =IFERROR(AVERAGEIFS(d_baths,d_beds,$B33),"") -> 3.0272727 | J33: =IFERROR(AVERAGEIFS(d_dom,d_beds,$B33),"") -> 53.111111 | K33: =IFERROR(E33-E32,"") -> 68188.201 | L33: =IFERROR(E33/E32-1,"") -> 0.17925695
B34: 5 | C34: =COUNTIFS(d_beds,$B34) -> 22 | D34: =C34/C$36 -> 0.088 | E34: =IFERROR(AVERAGEIFS(d_price,d_beds,$B34),"") -> 565363.64 | F34: {=IFERROR(MEDIAN(IF(d_beds=$B34,d_price)),"")} -> 541000 | G34: =IFERROR(AVERAGEIFS(d_sqft,d_beds,$B34),"") -> 2576.3636 | H34: =IFERROR(AVERAGEIFS(d_psf,d_beds,$B34),"") -> 219.97003 | I34: =IFERROR(AVERAGEIFS(d_baths,d_beds,$B34),"") -> 3.7045455 | J34: =IFERROR(AVERAGEIFS(d_dom,d_beds,$B34),"") -> 51.666667 | K34: =IFERROR(E34-E33,"") -> 116781.82 | L34: =IFERROR(E34/E33-1,"") -> 0.2603356
B35: 6 | C35: =COUNTIFS(d_beds,$B35) -> 1 | D35: =C35/C$36 -> 0.004 | E35: =IFERROR(AVERAGEIFS(d_price,d_beds,$B35),"") -> 3310000 | F35: {=IFERROR(MEDIAN(IF(d_beds=$B35,d_price)),"")} -> 3310000 | G35: =IFERROR(AVERAGEIFS(d_sqft,d_beds,$B35),"") -> 6400 | H35: =IFERROR(AVERAGEIFS(d_psf,d_beds,$B35),"") -> 517.1875 | I35: =IFERROR(AVERAGEIFS(d_baths,d_beds,$B35),"") -> 5.5 | J35: =IFERROR(AVERAGEIFS(d_dom,d_beds,$B35),"") -> 61 | K35: =IFERROR(E35-E34,"") -> 2744636.4 | L35: =IFERROR(E35/E34-1,"") -> 4.854639
B36: Market (all sales) | C36: =COUNT(d_price) -> 250 | D36: =C36/C$36 -> 1 | E36: =AVERAGE(d_price) -> 390400 | F36: =MEDIAN(d_price) -> 366000 | G36: =AVERAGE(d_sqft) -> 1727.04 | H36: =AVERAGE(d_psf) -> 225.90432 | I36: =AVERAGE(d_baths) -> 2.412 | J36: =AVERAGE(d_dom) -> 57.371901 | K36: — | L36: —
B37: 6 bedrooms = one sale only (the $3.31M luxury home) — ignore that row when judging trends.

Sheet Analysis
A1: STATISTICAL ANALYSIS
A2: Descriptive statistics, outlier fences, correlations, a price-per-sqft regression and negotiation analysis — all live formulas.
A4: A ▸ DESCRIPTIVE STATISTICS
A5: Metric | B5: Count | C5: Mean | D5: Median | E5: Std Dev | F5: Min | G5: Q1 | H5: Q3 | I5: Max | J5: Skew
A6: Sale price ($) | B6: =COUNT(d_price) -> 250 | C6: =AVERAGE(d_price) -> 390400 | D6: =MEDIAN(d_price) -> 366000 | E6: =STDEV(d_price) -> 222755.98 | F6: =MIN(d_price) -> 116000 | G6: =QUARTILE(d_price,1) -> 297250 | H6: =QUARTILE(d_price,3) -> 450000 | I6: =MAX(d_price) -> 3310000 | J6: =SKEW(d_price) -> 9.1541078
A7: List price ($) | B7: =COUNT(d_list) -> 250 | C7: =AVERAGE(d_list) -> 400556 | D7: =MEDIAN(d_list) -> 375500 | E7: =STDEV(d_list) -> 230885.81 | F7: =MIN(d_list) -> 118000 | G7: =QUARTILE(d_list,1) -> 309500 | H7: =QUARTILE(d_list,3) -> 464000 | I7: =MAX(d_list) -> 3450000 | J7: =SKEW(d_list) -> 9.364731
A8: Living area (sq ft) | B8: =COUNT(d_sqft) -> 250 | C8: =AVERAGE(d_sqft) -> 1727.04 | D8: =MEDIAN(d_sqft) -> 1740 | E8: =STDEV(d_sqft) -> 574.95105 | F8: =MIN(d_sqft) -> 520 | G8: =QUARTILE(d_sqft,1) -> 1380 | H8: =QUARTILE(d_sqft,3) -> 2010 | I8: =MAX(d_sqft) -> 6400 | J8: =SKEW(d_sqft) -> 2.095602
A9: Price per sq ft ($) | B9: =COUNT(d_psf) -> 250 | C9: =AVERAGE(d_psf) -> 225.90432 | D9: =MEDIAN(d_psf) -> 218.86378 | E9: =STDEV(d_psf) -> 51.538627 | F9: =MIN(d_psf) -> 125.13089 | G9: =QUARTILE(d_psf,1) -> 189.31159 | H9: =QUARTILE(d_psf,3) -> 260.2529 | I9: =MAX(d_psf) -> 517.1875 | J9: =SKEW(d_psf) -> 1.0872285
A10: Lot size (sq ft) | B10: =COUNT(d_lot) -> 250 | C10: =AVERAGE(d_lot) -> 4214.6 | D10: =MEDIAN(d_lot) -> 4520 | E10: =STDEV(d_lot) -> 3864.0458 | F10: =MIN(d_lot) -> 0 | G10: =QUARTILE(d_lot,1) -> 1362.5 | H10: =QUARTILE(d_lot,3) -> 6547.5 | I10: =MAX(d_lot) -> 41000 | J10: =SKEW(d_lot) -> 3.4564825
A11: Bedrooms | B11: =COUNT(d_beds) -> 250 | C11: =AVERAGE(d_beds) -> 2.988 | D11: =MEDIAN(d_beds) -> 3 | E11: =STDEV(d_beds) -> 1.1175202 | F11: =MIN(d_beds) -> 1 | G11: =QUARTILE(d_beds,1) -> 2 | H11: =QUARTILE(d_beds,3) -> 4 | I11: =MAX(d_beds) -> 6 | J11: =SKEW(d_beds) -> 0.0063677245
A12: Bathrooms | B12: =COUNT(d_baths) -> 250 | C12: =AVERAGE(d_baths) -> 2.412 | D12: =MEDIAN(d_baths) -> 2.5 | E12: =STDEV(d_baths) -> 0.87597106 | F12: =MIN(d_baths) -> 1 | G12: =QUARTILE(d_baths,1) -> 2 | H12: =QUARTILE(d_baths,3) -> 3 | I12: =MAX(d_baths) -> 5.5 | J12: =SKEW(d_baths) -> 0.37560781
A13: Days on market | B13: =COUNT(d_dom) -> 242 | C13: =AVERAGE(d_dom) -> 57.371901 | D13: =MEDIAN(d_dom) -> 53 | E13: =STDEV(d_dom) -> 30.655666 | F13: =MIN(d_dom) -> 18 | G13: =QUARTILE(d_dom,1) -> 41 | H13: =QUARTILE(d_dom,3) -> 67 | I13: =MAX(d_dom) -> 412 | J13: =SKEW(d_dom) -> 6.6353885
A14: Sale-to-list ratio | B14: =COUNT(d_stl) -> 250 | C14: =AVERAGE(d_stl) -> 0.97491351 | D14: =MEDIAN(d_stl) -> 0.97473511 | E14: =STDEV(d_stl) -> 0.031105613 | F14: =MIN(d_stl) -> 0.85882353 | G14: =QUARTILE(d_stl,1) -> 0.95496964 | H14: =QUARTILE(d_stl,3) -> 0.99281181 | I14: =MAX(d_stl) -> 1.0610687 | J14: =SKEW(d_stl) -> -0.079457089
A15: Agent commission (%) | B15: =COUNT(d_comm) -> 233 | C15: =AVERAGE(d_comm) -> 2.9224893 | D15: =MEDIAN(d_comm) -> 2.98 | E15: =STDEV(d_comm) -> 0.23489136 | F15: =MIN(d_comm) -> 2.41 | G15: =QUARTILE(d_comm,1) -> 2.75 | H15: =QUARTILE(d_comm,3) -> 3.05 | I15: =MAX(d_comm) -> 3.33 | J15: =SKEW(d_comm) -> -0.4951464
A17: Skew > 1 means a long right tail (a few very expensive homes / very slow sales) — use the Median rather than the Mean for typical values.
A19: B ▸ OUTLIER DETECTION (Tukey IQR fences: Q1 − k·IQR, Q3 + k·IQR)
A20: IQR multiplier k | B20: 1.5 | C20: Blue input — standard Tukey value is 1.5
A21: Metric | B21: Q1 | C21: Q3 | D21: IQR | E21: Lower fence | F21: Upper fence | G21: Rows flagged
A22: Sale price ($) | B22: =QUARTILE(d_price,1) -> 297250 | C22: =QUARTILE(d_price,3) -> 450000 | D22: =C22-B22 -> 152750 | E22: =B22-$B$20*D22 -> 68125 | F22: =C22+$B$20*D22 -> 679125 | G22: =COUNTIF(d_flag,"*High price*") -> 4
A23: Days on market | B23: =QUARTILE(d_dom,1) -> 41 | C23: =QUARTILE(d_dom,3) -> 67 | D23: =C23-B23 -> 26 | E23: =B23-$B$20*D23 -> 2 | F23: =C23+$B$20*D23 -> 106 | G23: =COUNTIF(d_flag,"*Long DOM*") -> 5
A24: Price per sq ft ($) | B24: =QUARTILE(d_psf,1) -> 189.31159 | C24: =QUARTILE(d_psf,3) -> 260.2529 | D24: =C24-B24 -> 70.941304 | E24: =B24-$B$20*D24 -> 82.899638 | F24: =C24+$B$20*D24 -> 366.66485 | G24: =COUNTIF(d_flag,"*$/sqft*") -> 2
A25: Total rows with any flag | G25: =COUNTIF(d_flag,"?*") -> 10
A26: Flagged rows are KEPT (they are real sales) and labelled in Data_Clean › outlier_flag. Filter that column to exclude them.
A28: C ▸ WHAT DRIVES SALE PRICE? (Pearson correlation with sale price)
A29: Variable | B29: Correlation (r) | C29: Strength | D29: R² (shared variance)
A30: Living area (sq ft) | B30: =CORREL(d_sqft,d_price) -> 0.79506555 | C30: =IF(ABS(B30)>=0.7,"Strong",IF(ABS(B30)>=0.4,"Moderate",IF(ABS(B30)>=0.2,"Weak","Negligible")))&IF(B30<0," (neg.)","") -> Strong | D30: =B30^2 -> 0.63212922
A31: Lot size (sq ft) | B31: =CORREL(d_lot,d_price) -> 0.77804607 | C31: =IF(ABS(B31)>=0.7,"Strong",IF(ABS(B31)>=0.4,"Moderate",IF(ABS(B31)>=0.2,"Weak","Negligible")))&IF(B31<0," (neg.)","") -> Strong | D31: =B31^2 -> 0.60535568
A32: Bedrooms | B32: =CORREL(d_beds,d_price) -> 0.53605537 | C32: =IF(ABS(B32)>=0.7,"Strong",IF(ABS(B32)>=0.4,"Moderate",IF(ABS(B32)>=0.2,"Weak","Negligible")))&IF(B32<0," (neg.)","") -> Moderate | D32: =B32^2 -> 0.28735536
A33: Bathrooms | B33: =CORREL(d_baths,d_price) -> 0.50530782 | C33: =IF(ABS(B33)>=0.7,"Strong",IF(ABS(B33)>=0.4,"Moderate",IF(ABS(B33)>=0.2,"Weak","Negligible")))&IF(B33<0," (neg.)","") -> Moderate | D33: =B33^2 -> 0.255336
A34: Garage spaces | B34: =CORREL(d_garage,d_price) -> 0.32863542 | C34: =IF(ABS(B34)>=0.7,"Strong",IF(ABS(B34)>=0.4,"Moderate",IF(ABS(B34)>=0.2,"Weak","Negligible")))&IF(B34<0," (neg.)","") -> Weak | D34: =B34^2 -> 0.10800124
A35: Year built | B35: =CORREL(d_year,d_price) -> 0.11917736 | C35: =IF(ABS(B35)>=0.7,"Strong",IF(ABS(B35)>=0.4,"Moderate",IF(ABS(B35)>=0.2,"Weak","Negligible")))&IF(B35<0," (neg.)","") -> Negligible | D35: =B35^2 -> 0.014203243
A36: Days on market | B36: =CORREL(d_dom,d_price) -> -0.063011286 | C36: =IF(ABS(B36)>=0.7,"Strong",IF(ABS(B36)>=0.4,"Moderate",IF(ABS(B36)>=0.2,"Weak","Negligible")))&IF(B36<0," (neg.)","") -> Negligible (neg.) | D36: =B36^2 -> 0.0039704222
A37: Agent commission (%) | B37: =CORREL(d_comm,d_price) -> -0.18523087 | C37: =IF(ABS(B37)>=0.7,"Strong",IF(ABS(B37)>=0.4,"Moderate",IF(ABS(B37)>=0.2,"Weak","Negligible")))&IF(B37<0," (neg.)","") -> Negligible (neg.) | D37: =B37^2 -> 0.034310474
A38: Correlation is not causation: sq ft, lot size, bedrooms and bathrooms all move together (multicollinearity).
A40: D ▸ SIMPLE LINEAR REGRESSION: Sale price = Intercept + Slope × Sq ft
A41: Statistic | B41: All sales | C41: Excl. flagged outliers
A42: Slope ($ per extra sq ft) | B42: =SLOPE(d_price,d_sqft) -> 308.03596 | C42: {=SLOPE(IF(d_flag="",d_price),IF(d_flag="",d_sqft))} -> 183.53507
A43: Intercept ($) | B43: =INTERCEPT(d_price,d_sqft) -> -141590.43 | C43: {=INTERCEPT(IF(d_flag="",d_price),IF(d_flag="",d_sqft))} -> 62313.48
A44: R² (goodness of fit) | B44: =RSQ(d_price,d_sqft) -> 0.63212922 | C44: {=RSQ(IF(d_flag="",d_price),IF(d_flag="",d_sqft))} -> 0.5861835
A45: Std error of estimate ($) | B45: =STEYX(d_price,d_sqft) -> 135378.86 | C45: {=STEYX(IF(d_flag="",d_price),IF(d_flag="",d_sqft))} -> 74997.114
A47: PRICE ESTIMATOR ▸ enter sq ft → | B47: 2000
A48: Estimated sale price (excl. outliers model) | B48: =C43+C42*B47 -> 429383.61
A49: Approx. range (± 1 std error) | B49: =TEXT(B48-C45,"$#,##0")&" – "&TEXT(B48+C45,"$#,##0") -> $3,54,386 – $5,04,381
A50: The single $3.3M / 6,400 sq ft mansion inflates the "All sales" slope, so the outlier-free model (col C) is used for the estimator, dashboard text and trend line.
A51: Trend-line points (for dashboard chart) | B51: Sq ft (x) | C51: Est. price (y)
A52: Point 1 | B52: 500 | C52: =$C$43+$C$42*B52 -> 154081.01
A53: Point 2 | B53: 3500 | C53: =$C$43+$C$42*B53 -> 704686.21
A56: E ▸ NEGOTIATION POWER — sale price vs. list price
A57: Metric | B57: Value
A58: Avg sale-to-list ratio | B58: =AVERAGE(d_stl) -> 0.97491351
A59: Median sale-to-list ratio | B59: =MEDIAN(d_stl) -> 0.97473511
A60: % sold ABOVE list | B60: =COUNTIF(d_stl,">1")/COUNT(d_stl) -> 0.192
A61: % sold AT list | B61: =COUNTIF(d_stl,1)/COUNT(d_stl) -> 0.02
A62: % sold BELOW list | B62: =COUNTIF(d_stl,"<1")/COUNT(d_stl) -> 0.788
A63: Avg $ below list (all sales) | B63: =AVERAGE(d_diff) -> -10156
A64: Avg $ below list (sold under list only) | B64: =AVERAGEIF(d_diff,"<0") -> -14781.726
A66: Time on market | B66: From (days) | C66: To (days) | D66: Sales | E66: Avg Sale-to-List | F66: Avg Price
A67: Fast (≤ 40 days) | B67: 0 | C67: 40 | D67: =COUNTIFS(d_dom,">="&$B67,d_dom,"<="&$C67) -> 56 | E67: =IFERROR(AVERAGEIFS(d_stl,d_dom,">="&$B67,d_dom,"<="&$C67),"") -> 0.97755475 | F67: =IFERROR(AVERAGEIFS(d_price,d_dom,">="&$B67,d_dom,"<="&$C67),"") -> 385857.14
A68: Normal (41-60) | B68: 41 | C68: 60 | D68: =COUNTIFS(d_dom,">="&$B68,d_dom,"<="&$C68) -> 97 | E68: =IFERROR(AVERAGEIFS(d_stl,d_dom,">="&$B68,d_dom,"<="&$C68),"") -> 0.97814724 | F68: =IFERROR(AVERAGEIFS(d_price,d_dom,">="&$B68,d_dom,"<="&$C68),"") -> 386391.75
A69: Slow (61-90) | B69: 61 | C69: 90 | D69: =COUNTIFS(d_dom,">="&$B69,d_dom,"<="&$C69) -> 69 | E69: =IFERROR(AVERAGEIFS(d_stl,d_dom,">="&$B69,d_dom,"<="&$C69),"") -> 0.96946971 | F69: =IFERROR(AVERAGEIFS(d_price,d_dom,">="&$B69,d_dom,"<="&$C69),"") -> 408434.78
A70: Very slow (> 90) | B70: 91 | C70: 9999 | D70: =COUNTIFS(d_dom,">="&$B70,d_dom,"<="&$C70) -> 20 | E70: =IFERROR(AVERAGEIFS(d_stl,d_dom,">="&$B70,d_dom,"<="&$C70),"") -> 0.97271204 | F70: =IFERROR(AVERAGEIFS(d_price,d_dom,">="&$B70,d_dom,"<="&$C70),"") -> 381800
A72: F ▸ ANALYST NOTES & CAVEATS
A73: • Sample is 250 sales (Jan-2025 → 23-Aug-2026); Aug-2026 is a partial month and Unknown-neighborhood (4) / 6-bedroom (1) groups are too small for conclusions.
A74: • 8 living-area, 7 bathroom, 9 lot-size and 16 garage values were imputed with group medians (see Cleaning_Log) — $/sqft for those 8 rows is an estimate.
A75: • Days-on-market, commission % and year built were NOT imputed (blank = unknown) so averages use only rows that have a value.
A76: • Condition is entangled with neighborhood and property-type mix — the condition premium is descriptive, not a controlled effect.
A77: • Regression is a single-variable model: R² shows how much of price variation sq ft alone explains; neighborhood and type would add more.
A80: G ▸ DASHBOARD FILTER HELPERS (used by the KPI cards — do not edit)
A81: Neighborhood criterion | B81: =IF(Dashboard!$D$4="All","*",Dashboard!$D$4) -> *
A82: Property-type criterion | B82: =IF(Dashboard!$H$4="All","*",Dashboard!$H$4) -> *

Sheet Cleaning_Log
A1: DATA CLEANING LOG
A2: Every transformation applied to Data_Raw to produce Data_Clean. Counts are live formulas against both sheets.
A4: A ▸ BEFORE vs AFTER
A5: Metric | B5: Note | C5: Raw | D5: Clean | E5: Comment
A6: Records | B6: Rows of data | C6: =COUNTA(Data_Raw!A2:A251) -> 250 | D6: =COUNTA(Data_Clean!A2:A251) -> 250 | E6: No rows dropped — all 250 sales retained
A7: Duplicate sale_ids | B7: Same ID appearing >1× | C7: =SUMPRODUCT(--(COUNTIF(Data_Raw!A2:A251,Data_Raw!A2:A251)>1)) -> 0 | D7: =SUMPRODUCT(--(COUNTIF(Data_Clean!A2:A251,Data_Clean!A2:A251)>1)) -> 0 | E7: None found
A8: Blank cells (fields C:O) | B8: Missing values | C8: =COUNTBLANK(Data_Raw!C2:O251) -> 98 | D8: =COUNTBLANK(Data_Clean!C2:O251) -> 38 | E8: Remaining blanks are intentional (year_built, DOM, commission)
A9: Neighborhood labels | B9: Distinct spellings | C9: 19 | D9: =SUMPRODUCT(1/COUNTIF(Data_Clean!C2:C251,Data_Clean!C2:C251)) -> 6 | E9: 5 real areas + "Unknown"
A10: Property-type labels | B10: Distinct spellings | C10: 13 | D10: =SUMPRODUCT(1/COUNTIF(Data_Clean!D2:D251,Data_Clean!D2:D251)) -> 3 | E10: Condo / Single Family / Townhouse
A11: Condition labels | B11: Distinct spellings | C11: 11 | D11: =SUMPRODUCT(1/COUNTIF(Data_Clean!K2:K251,Data_Clean!K2:K251)) -> 5 | E11: Excellent / Good / Fair / Poor + "Unknown"
A13: B ▸ FIELD-BY-FIELD ISSUES AND TREATMENT
A14: Field | B14: Issue found | C14: Rows affected | D14: Treatment | E14: Rationale
A15: sale_date | B15: Stored as text (yyyy-mm-dd) | C15: =COUNTA(Data_Raw!B2:B251) -> 250 | D15: Converted to true Excel dates | E15: Enables month grouping and time-series charts
A16: neighborhood | B16: Case, spacing, punctuation and typo variants (e.g. "OakHill", "Oak Hl.", "Cedar Pk") | C16: =COUNTIF(Data_Clean!$X$2:$X$251,"*neighborhood standardised*") -> 38 | D16: Mapped to 5 canonical names | E16: Prevents one area being split into many pivot rows
A17: neighborhood | B17: Blank values | C17: =COUNTIF(Data_Clean!$X$2:$X$251,"*neighborhood missing*") -> 4 | D17: Set to "Unknown" | E17: Cannot be inferred from other fields; keeps the sale in overall totals
A18: property_type | B18: 13 variants (SFH, Condominium, TH, single fam …) | C18: =COUNTIF(Data_Clean!$X$2:$X$251,"*property_type standardised*") -> 41 | D18: Mapped to Condo / Single Family / Townhouse | E18: Consistent grouping
A19: condition | B19: Case variants, "Exc.", literal "unknown" | C19: =COUNTIF(Data_Clean!$X$2:$X$251,"*condition standardised*") -> 36 | D19: Mapped to 4 levels; "unknown" → "Unknown" | E19: Consistent grouping
A20: condition | B20: Blank values | C20: =COUNTIF(Data_Clean!$X$2:$X$251,"*condition missing*") -> 11 | D20: Set to "Unknown" | E20: Not guessed — condition is subjective
A21: bathrooms | B21: Missing | C21: =COUNTIF(Data_Clean!$X$2:$X$251,"*bathrooms imputed*") -> 7 | D21: Imputed: median of same bedrooms × property type (rounded to 0.5) | E21: Structural attribute strongly tied to bedrooms/type
A22: sqft | B22: Missing | C22: =COUNTIF(Data_Clean!$X$2:$X$251,"*living sqft imputed*") -> 8 | D22: Imputed: median of same bedrooms × property type (rounded to 10) | E22: Needed so every row has a $/sqft value
A23: lot_size_sqft | B23: 0 for condos = genuinely no lot (NOT an error); some values missing | C23: =COUNTIF(Data_Clean!$X$2:$X$251,"*lot size set to 0*") -> 5 | D23: Missing condo lots set to 0 | E23: Condos do not own land
A24: lot_size_sqft | B24: Missing for houses/townhouses | C24: =COUNTIF(Data_Clean!$X$2:$X$251,"*lot size imputed*") -> 9 | D24: Imputed: median lot size for the property type | E24: Structural attribute
A25: garage_spaces | B25: Missing | C25: =COUNTIF(Data_Clean!$X$2:$X$251,"*garage imputed*") -> 16 | D25: Imputed: median for the property type | E25: Structural attribute
A26: year_built | B26: Missing | C26: =COUNTIF(Data_Clean!$X$2:$X$251,"*year_built left blank*") -> 13 | D26: LEFT BLANK | E26: No reliable basis to invent a build year; age metrics skip these rows
A27: days_on_market | B27: Missing | C27: =COUNTIF(Data_Clean!$X$2:$X$251,"*days_on_market left blank*") -> 8 | D27: LEFT BLANK | E27: Market-timing outcome — imputing would bias speed metrics
A28: agent_commission_pct | B28: Missing | C28: =COUNTIF(Data_Clean!$X$2:$X$251,"*commission left blank*") -> 17 | D28: LEFT BLANK | E28: Not needed for core analysis; avoids fabricated commissions
A29: sale_price / list_price | B29: No missing values, but extreme values exist (e.g. a $3.31M / 6,400 sq ft sale; a 412-day listing) | C29: =Analysis!G25 -> 10 | D29: FLAGGED via IQR fences in outlier_flag (rows affected = rows flagged); NOT removed | E29: Real transactions; Median is used for “typical” values
A31: C ▸ STANDARDISATION MAP (raw value → clean value, with case-sensitive counts from Data_Raw)
A32: Field | B32: Raw value (exact, incl. spaces/case) | C32: Rows in raw | D32: Standardised to
A33: neighborhood | B33: Cedar Park | C33: =SUMPRODUCT(--EXACT(Data_Raw!$C$2:$C$251,B33)) -> 34 | D33: Cedar Park
A34: neighborhood | B34: Cedar Pk | C34: =SUMPRODUCT(--EXACT(Data_Raw!$C$2:$C$251,B34)) -> 3 | D34: Cedar Park
A35: neighborhood | B35: CedarPark | C35: =SUMPRODUCT(--EXACT(Data_Raw!$C$2:$C$251,B35)) -> 2 | D35: Cedar Park
A36: neighborhood | B36: DOWNTOWN | C36: =SUMPRODUCT(--EXACT(Data_Raw!$C$2:$C$251,B36)) -> 3 | D36: Downtown
A37: neighborhood | B37: Down Town | C37: =SUMPRODUCT(--EXACT(Data_Raw!$C$2:$C$251,B37)) -> 1 | D37: Downtown
A38: neighborhood | B38: Downtown | C38: =SUMPRODUCT(--EXACT(Data_Raw!$C$2:$C$251,B38)) -> 31 | D38: Downtown
A39: neighborhood | B39: downtown | C39: =SUMPRODUCT(--EXACT(Data_Raw!$C$2:$C$251,B39)) -> 1 | D39: Downtown
A40: neighborhood | B40: Maple Heights | C40: =SUMPRODUCT(--EXACT(Data_Raw!$C$2:$C$251,B40)) -> 44 | D40: Maple Heights
A41: neighborhood | B41: Maple Heights. | C41: =SUMPRODUCT(--EXACT(Data_Raw!$C$2:$C$251,B41)) -> 4 | D41: Maple Heights
A42: neighborhood | B42: Maple Hts | C42: =SUMPRODUCT(--EXACT(Data_Raw!$C$2:$C$251,B42)) -> 1 | D42: Maple Heights
A43: neighborhood | B43: maple heights | C43: =SUMPRODUCT(--EXACT(Data_Raw!$C$2:$C$251,B43)) -> 2 | D43: Maple Heights
A44: neighborhood | B44: OAK HILL | C44: =SUMPRODUCT(--EXACT(Data_Raw!$C$2:$C$251,B44)) -> 5 | D44: Oak Hill
... A49: neighborhood | B49: Riverside | C49: =SUMPRODUCT(--EXACT(Data_Raw!$C$2:$C$251,B49)) -> 49 | D49: Riverside
A50: neighborhood | B50: Riverside | C50: =SUMPRODUCT(--EXACT(Data_Raw!$C$2:$C$251,B50)) -> 6 | D50: Riverside | E50: ↑ contains leading/trailing space
A51: neighborhood | B51: riverside | C51: =SUMPRODUCT(--EXACT(Data_Raw!$C$2:$C$251,B51)) -> 4 | D51: Riverside
A52: neighborhood | B52: (blank) | C52: =COUNTBLANK(Data_Raw!$C$2:$C$251) -> 4 | D52: Unknown
A53: property_type | B53: CONDO | C53: =SUMPRODUCT(--EXACT(Data_Raw!$D$2:$D$251,B53)) -> 3 | D53: Condo
A54: property_type | B54: Condo | C54: =SUMPRODUCT(--EXACT(Data_Raw!$D$2:$D$251,B54)) -> 51 | D54: Condo
A55: property_type | B55: Condominium | C55: =SUMPRODUCT(--EXACT(Data_Raw!$D$2:$D$251,B55)) -> 2 | D55: Condo
A56: property_type | B56: condo | C56: =SUMPRODUCT(--EXACT(Data_Raw!$D$2:$D$251,B56)) -> 1 | D56: Condo
A57: property_type | B57: SFH | C57: =SUMPRODUCT(--EXACT(Data_Raw!$D$2:$D$251,B57)) -> 5 | D57: Single Family
A58: property_type | B58: Single Family | C58: =SUMPRODUCT(--EXACT(Data_Raw!$D$2:$D$251,B58)) -> 119 | D58: Single Family
A59: property_type | B59: Single family | C59: =SUMPRODUCT(--EXACT(Data_Raw!$D$2:$D$251,B59)) -> 6 | D59: Single Family
A60: property_type | B60: single fam | C60: =SUMPRODUCT(--EXACT(Data_Raw!$D$2:$D$251,B60)) -> 6 | D60: Single Family
A61: property_type | B61: single-family | C61: =SUMPRODUCT(--EXACT(Data_Raw!$D$2:$D$251,B61)) -> 10 | D61: Single Family
A62: property_type | B62: TH | C62: =SUMPRODUCT(--EXACT(Data_Raw!$D$2:$D$251,B62)) -> 2 | D62: Townhouse
A63: property_type | B63: Townhome | C63: =SUMPRODUCT(--EXACT(Data_Raw!$D$2:$D$251,B63)) -> 5 | D63: Townhouse
A64: property_type | B64: Townhouse | C64: =SUMPRODUCT(--EXACT(Data_Raw!$D$2:$D$251,B64)) -> 39 | D64: Townhouse
A65: property_type | B65: townhouse | C65: =SUMPRODUCT(--EXACT(Data_Raw!$D$2:$D$251,B65)) -> 1 | D65: Townhouse
A66: property_type | B66: (blank) | C66: =COUNTBLANK(Data_Raw!$D$2:$D$251) -> 0 | D66: Unknown
A67: condition | B67: Exc. | C67: =SUMPRODUCT(--EXACT(Data_Raw!$K$2:$K$251,B67)) -> 2 | D67: Excellent
A68: condition | B68: Excellent | C68: =SUMPRODUCT(--EXACT(Data_Raw!$K$2:$K$251,B68)) -> 54 | D68: Excellent
A69: condition | B69: excellent | C69: =SUMPRODUCT(--EXACT(Data_Raw!$K$2:$K$251,B69)) -> 6 | D69: Excellent
A70: condition | B70: Fair | C70: =SUMPRODUCT(--EXACT(Data_Raw!$K$2:$K$251,B70)) -> 51 | D70: Fair
A71: condition | B71: fair | C71: =SUMPRODUCT(--EXACT(Data_Raw!$K$2:$K$251,B71)) -> 9 | D71: Fair
A72: condition | B72: GOOD | C72: =SUMPRODUCT(--EXACT(Data_Raw!$K$2:$K$251,B72)) -> 8 | D72: Good
A73: condition | B73: Good | C73: =SUMPRODUCT(--EXACT(Data_Raw!$K$2:$K$251,B73)) -> 89 | D73: Good
A74: condition | B74: good | C74: =SUMPRODUCT(--EXACT(Data_Raw!$K$2:$K$251,B74)) -> 8 | D74: Good
A75: condition | B75: Poor | C75: =SUMPRODUCT(--EXACT(Data_Raw!$K$2:$K$251,B75)) -> 9 | D75: Poor
A76: condition | B76: poor | C76: =SUMPRODUCT(--EXACT(Data_Raw!$K$2:$K$251,B76)) -> 2 | D76: Poor
A77: condition | B77: unknown | C77: =SUMPRODUCT(--EXACT(Data_Raw!$K$2:$K$251,B77)) -> 1 | D77: Unknown
A78: condition | B78: (blank) | C78: =COUNTBLANK(Data_Raw!$K$2:$K$251) -> 11 | D78: Unknown

Sheet Data_Clean
A1: sale_id | B1: sale_date | C1: neighborhood | D1: property_type | E1: bedrooms | F1: bathrooms | G1: sqft | H1: lot_size_sqft | I1: year_built | J1: garage_spaces | K1: condition | L1: list_price | M1: sale_price | N1: days_on_market | O1: agent_commission_pct | P1: sale_month | Q1: price_per_sqft | R1: sale_to_list | S1: price_vs_list | T1: commission_usd | U1: home_age_at_sale | V1: price_band | W1: outlier_flag | X1: cleaning_notes
A2: 10144 | B2: 45658 | C2: Maple Heights | D2: Townhouse | E2: 3 | F2: 3 | G2: 1500 | H2: 1400 | I2: 2004 | J2: 3 | K2: Fair | L2: 297000 | M2: 290000 | N2: 82 | O2: 2.57 | P2: =DATE(YEAR(B2),MONTH(B2),1) -> 45658 | Q2: =M2/G2 -> 193.33333 | R2: =M2/L2 -> 0.97643098 | S2: =M2-L2 -> -7000 | T2: =IF(O2="","",M2*O2/100) -> 7453 | U2: =IF(I2="","",YEAR(B2)-I2) -> 21 | V2: =LOOKUP(M2,bin_lo,bin_lbl) -> $200-300K | W2: =TRIM(IF(M2>f_price_hi,"High price ","")&IF(AND(N2<>"",N2>f_dom_hi),"Long DOM ","")&IF(OR(Q2>f_psf_hi,Q2<f_psf_lo),"$/sqft ",""))
A3: 10067 | B3: 45659 | C3: Maple Heights | D3: Single Family | E3: 4 | F3: 2.5 | G3: 2370 | H3: 7660 | I3: 1996 | J3: 3 | K3: Fair | L3: 446000 | M3: 451000 | N3: 53 | O3: 2.71 | P3: =DATE(YEAR(B3),MONTH(B3),1) -> 45658 | Q3: =M3/G3 -> 190.29536 | R3: =M3/L3 -> 1.0112108 | S3: =M3-L3 -> 5000 | T3: =IF(O3="","",M3*O3/100) -> 12222.1 | U3: =IF(I3="","",YEAR(B3)-I3) -> 29 | V3: =LOOKUP(M3,bin_lo,bin_lbl) -> $400-500K | W3: =TRIM(IF(M3>f_price_hi,"High price ","")&IF(AND(N3<>"",N3>f_dom_hi),"Long DOM ","")&IF(OR(Q3>f_psf_hi,Q3<f_psf_lo),"$/sqft ",""))
A4: 10028 | B4: 45661 | C4: Oak Hill | D4: Single Family | E4: 3 | F4: 2.5 | G4: 1510 | H4: 4520 | I4: 2006 | J4: 2 | K4: Good | L4: 404000 | M4: 384000 | N4: 40 | O4: 2.79 | P4: =DATE(YEAR(B4),MONTH(B4),1) -> 45658 | Q4: =M4/G4 -> 254.30464 | R4: =M4/L4 -> 0.95049505 | S4: =M4-L4 -> -20000 | T4: =IF(O4="","",M4*O4/100) -> 10713.6 | U4: =IF(I4="","",YEAR(B4)-I4) -> 19 | V4: =LOOKUP(M4,bin_lo,bin_lbl) -> $300-400K | W4: =TRIM(IF(M4>f_price_hi,"High price ","")&IF(AND(N4<>"",N4>f_dom_hi),"Long DOM ","")&IF(OR(Q4>f_psf_hi,Q4<f_psf_lo),"$/sqft ",""))
A5: 10082 | B5: 45661 | C5: Riverside | D5: Single Family | E5: 3 | F5: 2.5 | G5: 1880 | H5: 5670 | I5: 1978 | J5: 1 | K5: Good | L5: 434000 | M5: 442000 | N5: 45 | P5: =DATE(YEAR(B5),MONTH(B5),1) -> 45658 | Q5: =M5/G5 -> 235.10638 | R5: =M5/L5 -> 1.0184332 | S5: =M5-L5 -> 8000 | T5: =IF(O5="","",M5*O5/100) | U5: =IF(I5="","",YEAR(B5)-I5) -> 47 | V5: =LOOKUP(M5,bin_lo,bin_lbl) -> $400-500K | W5: =TRIM(IF(M5>f_price_hi,"High price ","")&IF(AND(N5<>"",N5>f_dom_hi),"Long DOM ","")&IF(OR(Q5>f_psf_hi,Q5<f_psf_lo),"$/sqft ","")) | X5: property_type standardised; condition standardised; commission left blank
A6: 10043 | B6: 45664 | C6: Downtown | D6: Condo | E6: 1 | F6: 1 | G6: 1110 | H6: 0 | I6: 1962 | J6: 0 | K6: Excellent | L6: 364000 | M6: 355000 | N6: 81 | O6: 3.02 | P6: =DATE(YEAR(B6),MONTH(B6),1) -> 45658 | Q6: =M6/G6 -> 319.81982 | R6: =M6/L6 -> 0.97527473 | S6: =M6-L6 -> -9000 | T6: =IF(O6="","",M6*O6/100) -> 10721 | U6: =IF(I6="","",YEAR(B6)-I6) -> 63 | V6: =LOOKUP(M6,bin_lo,bin_lbl) -> $300-400K | W6: =TRIM(IF(M6>f_price_hi,"High price ","")&IF(AND(N6<>"",N6>f_dom_hi),"Long DOM ","")&IF(OR(Q6>f_psf_hi,Q6<f_psf_lo),"$/sqft ","")) | X6: neighborhood standardised
A7: 10095 | B7: 45669 | C7: Riverside | D7: Townhouse | E7: 3 | F7: 2.5 | G7: 1510 | H7: 1240 | I7: 2022 | J7: 2 | K7: Good | L7: 373000 | M7: 358000 | N7: 61 | O7: 2.51 | P7: =DATE(YEAR(B7),MONTH(B7),1) -> 45658 | Q7: =M7/G7 -> 237.08609 | R7: =M7/L7 -> 0.95978552 | S7: =M7-L7 -> -15000 | T7: =IF(O7="","",M7*O7/100) -> 8985.8 | U7: =IF(I7="","",YEAR(B7)-I7) -> 3 | V7: =LOOKUP(M7,bin_lo,bin_lbl) -> $300-400K | W7: =TRIM(IF(M7>f_price_hi,"High price ","")&IF(AND(N7<>"",N7>f_dom_hi),"Long DOM ","")&IF(OR(Q7>f_psf_hi,Q7<f_psf_lo),"$/sqft ",""))
A8: 10041 | B8: 45672 | C8: Riverside | D8: Condo | E8: 1 | F8: 1 | G8: 780 | H8: 0 | I8: 1982 | J8: 1 | K8: Good | L8: 178000 | M8: 180000 | N8: 25 | P8: =DATE(YEAR(B8),MONTH(B8),1) -> 45658 | Q8: =M8/G8 -> 230.76923 | R8: =M8/L8 -> 1.011236 | S8: =M8-L8 -> 2000 | T8: =IF(O8="","",M8*O8/100) | U8: =IF(I8="","",YEAR(B8)-I8) -> 43 | V8: =LOOKUP(M8,bin_lo,bin_lbl) -> Under $200K | W8: =TRIM(IF(M8>f_price_hi,"High price ","")&IF(AND(N8<>"",N8>f_dom_hi),"Long DOM ","")&IF(OR(Q8>f_psf_hi,Q8<f_psf_lo),"$/sqft ","")) | X8: property_type standardised; condition standardised; commission left blank
A9: 10178 | B9: 45672 | C9: Cedar Park | D9: Condo | E9: 3 | F9: 2.5 | G9: 1910 | H9: 0 | I9: 1959 | J9: 1 | K9: Good | L9: 242000 | M9: 239000 | N9: 35 | O9: 3.04 | P9: =DATE(YEAR(B9),MONTH(B9),1) -> 45658 | Q9: =M9/G9 -> 125.13089 | R9: =M9/L9 -> 0.98760331 | S9: =M9-L9 -> -3000 | T9: =IF(O9="","",M9*O9/100) -> 7265.6 | U9: =IF(I9="","",YEAR(B9)-I9) -> 66 | V9: =LOOKUP(M9,bin_lo,bin_lbl) -> $200-300K | W9: =TRIM(IF(M9>f_price_hi,"High price ","")&IF(AND(N9<>"",N9>f_dom_hi),"Long DOM ","")&IF(OR(Q9>f_psf_hi,Q9<f_psf_lo),"$/sqft ",""))
A10: 10142 | B10: 45673 | C10: Maple Heights | D10: Single Family | E10: 4 | F10: 3.5 | G10: 2360 | H10: 5700 | I10: 2008 | J10: 2 | K10: Good | L10: 489000 | M10: 442000 | N10: 60 | P10: =DATE(YEAR(B10),MONTH(B10),1) -> 45658 | Q10: =M10/G10 -> 187.28814 | R10: =M10/L10 -> 0.90388548 | S10: =M10-L10 -> -47000 | T10: =IF(O10="","",M10*O10/100) | U10: =IF(I10="","",YEAR(B10)-I10) -> 17 | V10: =LOOKUP(M10,bin_lo,bin_lbl) -> $400-500K | W10: =TRIM(IF(M10>f_price_hi,"High price ","")&IF(AND(N10<>"",N10>f_dom_hi),"Long DOM ","")&IF(OR(Q10>f_psf_hi,Q10<f_psf_lo),"$/sqft ","")) | X10: condition standardised; commission left blank
A11: 10027 | B11: 45674 | C11: Riverside | D11: Single Family | E11: 3 | F11: 2 | G11: 1890 | H11: 6400 | I11: 2002 | J11: 1 | K11: Poor | L11: 406000 | M11: 411000 | N11: 80 | O11: 2.95 | P11: =DATE(YEAR(B11),MONTH(B11),1) -> 45658 | Q11: =M11/G11 -> 217.46032 | R11: =M11/L11 -> 1.0123153 | S11: =M11-L11 -> 5000 | T11: =IF(O11="","",M11*O11/100) -> 12124.5 | U11: =IF(I11="","",YEAR(B11)-I11) -> 23 | V11: =LOOKUP(M11,bin_lo,bin_lbl) -> $400-500K | W11: =TRIM(IF(M11>f_price_hi,"High price ","")&IF(AND(N11<>"",N11>f_dom_hi),"Long DOM ","")&IF(OR(Q11>f_psf_hi,Q11<f_psf_lo),"$/sqft ","")) | X11: condition standardised
A12: 10014 | B12: 45676 | C12: Cedar Park | D12: Single Family | E12: 5 | F12: 5 | G12: 2220 | H12: 8020 | J12: 2 | K12: Good | L12: 435000 | M12: 425000 | N12: 50 | O12: 2.7 | P12: =DATE(YEAR(B12),MONTH(B12),1) -> 45658 | Q12: =M12/G12 -> 191.44144 | R12: =M12/L12 -> 0.97701149 | S12: =M12-L12 -> -10000 | T12: =IF(O12="","",M12*O12/100) -> 11475 | U12: =IF(I12="","",YEAR(B12)-I12) | V12: =LOOKUP(M12,bin_lo,bin_lbl) -> $400-500K | W12: =TRIM(IF(M12>f_price_hi,"High price ","")&IF(AND(N12<>"",N12>f_dom_hi),"Long DOM ","")&IF(OR(Q12>f_psf_hi,Q12<f_psf_lo),"$/sqft ","")) | X12: year_built left blank
A13: 10149 | B13: 45676 | C13: Riverside | D13: Single Family | E13: 4 | F13: 3.5 | G13: 2120 | H13: 8600 | I13: 2009 | J13: 2 | K13: Unknown | L13: 453000 | M13: 450000 | N13: 65 | O13: 2.75 | P13: =DATE(YEAR(B13),MONTH(B13),1) -> 45658 | Q13: =M13/G13 -> 212.26415 | R13: =M13/L13 -> 0.99337748 | S13: =M13-L13 -> -3000 | T13: =IF(O13="","",M13*O13/100) -> 12375 | U13: =IF(I13="","",YEAR(B13)-I13) -> 16 | V13: =LOOKUP(M13,bin_lo,bin_lbl) -> $400-500K | W13: =TRIM(IF(M13>f_price_hi,"High price ","")&IF(AND(N13<>"",N13>f_dom_hi),"Long DOM ","")&IF(OR(Q13>f_psf_hi,Q13<f_psf_lo),"$/sqft ","")) | X13: condition missing -> Unknown; living sqft imputed (group median); garage imputed (group median)
A14: 10193 | B14: 45676 | C14: Oak Hill | D14: Townhouse | E14: 4 | F14: 3.5 | G14: 2260 | H14: 1850 | I14: 1941 | J14: 2 | K14: Poor | L14: 395000 | M14: 389000 | N14: 76 | O14: 2.5 | P14: =DATE(YEAR(B14),MONTH(B14),1) -> 45658 | Q14: =M14/G14 -> 172.12389 | R14: =M14/L14 -> 0.98481013 | S14: =M14-L14 -> -6000 | T14: =IF(O14="","",M14*O14/100) -> 9725 | U14: =IF(I14="","",YEAR(B14)-I14) -> 84 | V14: =LOOKUP(M14,bin_lo,bin_lbl) -> $300-400K | W14: =TRIM(IF(M14>f_price_hi,"High price ","")&IF(AND(N14<>"",N14>f_dom_hi),"Long DOM ","")&IF(OR(Q14>f_psf_hi,Q14<f_psf_lo),"$/sqft ",""))
A15: 10083 | B15: 45681 | C15: Downtown | D15: Condo | E15: 2 | F15: 2 | G15: 1350 | H15: 0 | I15: 1961 | J15: 0 | K15: Good | L15: 371000 | M15: 359000 | N15: 43 | O15: 2.79 | P15: =DATE(YEAR(B15),MONTH(B15),1) -> 45658 | Q15: =M15/G15 -> 265.92593 | R15: =M15/L15 -> 0.96765499 | S15: =M15-L15 -> -12000 | T15: =IF(O15="","",M15*O15/100) -> 10016.1 | U15: =IF(I15="","",YEAR(B15)-I15) -> 64 | V15: =LOOKUP(M15,bin_lo,bin_lbl) -> $300-400K | W15: =TRIM(IF(M15>f_price_hi,"High price ","")&IF(AND(N15<>"",N15>f_dom_hi),"Long DOM ","")&IF(OR(Q15>f_psf_hi,Q15<f_psf_lo),"$/sqft ",""))
A16: 10105 | B16: 45682 | C16: Downtown | D16: Single Family | E16: 4 | F16: 3.5 | G16: 2010 | H16: 5170 | I16: 1980 | J16: 1 | K16: Fair | L16: 549000 | M16: 542000 | N16: 45 | O16: 2.97 | P16: =DATE(YEAR(B16),MONTH(B16),1) -> 45658 | Q16: =M16/G16 -> 269.65174 | R16: =M16/L16 -> 0.98724954 | S16: =M16-L16 -> -7000 | T16: =IF(O16="","",M16*O16/100) -> 16097.4 | U16: =IF(I16="","",YEAR(B16)-I16) -> 45 | V16: =LOOKUP(M16,bin_lo,bin_lbl) -> $500-600K | W16: =TRIM(IF(M16>f_price_hi,"High price ","")&IF(AND(N16<>"",N16>f_dom_hi),"Long DOM ","")&IF(OR(Q16>f_psf_hi,Q16<f_psf_lo),"$/sqft ",""))
A17: 10019 | B17: 45684 | C17: Cedar Park | D17: Single Family | E17: 3 | F17: 2.5 | G17: 1670 | H17: 4630 | I17: 2001 | J17: 2 | K17: Good | L17: 302000 | M17: 298000 | N17: 69 | O17: 2.55 | P17: =DATE(YEAR(B17),MONTH(B17),1) -> 45658 | Q17: =M17/G17 -> 178.44311 | R17: =M17/L17 -> 0.98675497 | S17: =M17-L17 -> -4000 | T17: =IF(O17="","",M17*O17/100) -> 7599 | U17: =IF(I17="","",YEAR(B17)-I17) -> 24 | V17: =LOOKUP(M17,bin_lo,bin_lbl) -> $200-300K | W17: =TRIM(IF(M17>f_price_hi,"High price ","")&IF(AND(N17<>"",N17>f_dom_hi),"Long DOM ","")&IF(OR(Q17>f_psf_hi,Q17<f_psf_lo),"$/sqft ","")) | X17: condition standardised
A18: 10057 | B18: 45685 | C18: Riverside | D18: Single Family | E18: 4 | F18: 2.5 | G18: 2050 | H18: 5760 | I18: 2005 | J18: 2 | K18: Good | L18: 462000 | M18: 441000 | N18: 39 | O18: 3.02 | P18: =DATE(YEAR(B18),MONTH(B18),1) -> 45658 | Q18: =M18/G18 -> 215.12195 | R18: =M18/L18 -> 0.95454545 | S18: =M18-L18 -> -21000 | T18: =IF(O18="","",M18*O18/100) -> 13318.2 | U18: =IF(I18="","",YEAR(B18)-I18) -> 20 | V18: =LOOKUP(M18,bin_lo,bin_lbl) -> $400-500K | W18: =TRIM(IF(M18>f_price_hi,"High price ","")&IF(AND(N18<>"",N18>f_dom_hi),"Long DOM ","")&IF(OR(Q18>f_psf_hi,Q18<f_psf_lo),"$/sqft ","")) | X18: neighborhood standardised; condition standardised
A19: 10229 | B19: 45689 | C19: Maple Heights | D19: Townhouse | E19: 4 | F19: 3 | G19: 2150 | H19: 1740 | J19: 1 | K19: Good | L19: 350000 | M19: 342000 | N19: 40 | P19: =DATE(YEAR(B19),MONTH(B19),1) -> 45689 | Q19: =M19/G19 -> 159.06977 | R19: =M19/L19 -> 0.97714286 | S19: =M19-L19 -> -8000 | T19: =IF(O19="","",M19*O19/100) | U19: =IF(I19="","",YEAR(B19)-I19) | V19: =LOOKUP(M19,bin_lo,bin_lbl) -> $300-400K | W19: =TRIM(IF(M19>f_price_hi,"High price ","")&IF(AND(N19<>"",N19>f_dom_hi),"Long DOM ","")&IF(OR(Q19>f_psf_hi,Q19<f_psf_lo),"$/sqft ","")) | X19: year_built left blank; commission left blank
A20: 10110 | B20: 45691 | C20: Cedar Park | D20: Single Family | E20: 3 | F20: 2.5 | G20: 1470 | H20: 3280 | I20: 1972 | J20: 1 | K20: Good | L20: 273000 | M20: 264000 | N20: 66 | O20: 3.05 | P20: =DATE(YEAR(B20),MONTH(B20),1) -> 45689 | Q20: =M20/G20 -> 179.59184 | R20: =M20/L20 -> 0.96703297 | S20: =M20-L20 -> -9000 | T20: =IF(O20="","",M20*O20/100) -> 8052 | U20: =IF(I20="","",YEAR(B20)-I20) -> 53 | V20: =LOOKUP(M20,bin_lo,bin_lbl) -> $200-300K | W20: =TRIM(IF(M20>f_price_hi,"High price ","")&IF(AND(N20<>"",N20>f_dom_hi),"Long DOM ","")&IF(OR(Q20>f_psf_hi,Q20<f_psf_lo),"$/sqft ",""))
A21: 10131 | B21: 45692 | C21: Oak Hill | D21: Single Family | E21: 3 | F21: 2 | G21: 1500 | H21: 5130 | I21: 1986 | J21: 1 | K21: Fair | L21: 393000 | M21: 403000 | N21: 60 | O21: 2.45 | P21: =DATE(YEAR(B21),MONTH(B21),1) -> 45689 | Q21: =M21/G21 -> 268.66667 | R21: =M21/L21 -> 1.0254453 | S21: =M21-L21 -> 10000 | T21: =IF(O21="","",M21*O21/100) -> 9873.5 | U21: =IF(I21="","",YEAR(B21)-I21) -> 39 | V21: =LOOKUP(M21,bin_lo,bin_lbl) -> $400-500K | W21: =TRIM(IF(M21>f_price_hi,"High price ","")&IF(AND(N21<>"",N21>f_dom_hi),"Long DOM ","")&IF(OR(Q21>f_psf_hi,Q21<f_psf_lo),"$/sqft ",""))
A22: 10124 | B22: 45695 | C22: Riverside | D22: Single Family | E22: 4 | F22: 3.5 | G22: 2050 | H22: 4930 | I22: 1974 | J22: 1 | K22: Good | L22: 487000 | M22: 452000 | N22: 43 | O22: 3.02 | P22: =DATE(YEAR(B22),MONTH(B22),1) -> 45689 | Q22: =M22/G22 -> 220.4878 | R22: =M22/L22 -> 0.92813142 | S22: =M22-L22 -> -35000 | T22: =IF(O22="","",M22*O22/100) -> 13650.4 | U22: =IF(I22="","",YEAR(B22)-I22) -> 51 | V22: =LOOKUP(M22,bin_lo,bin_lbl) -> $400-500K | W22: =TRIM(IF(M22>f_price_hi,"High price ","")&IF(AND(N22<>"",N22>f_dom_hi),"Long DOM ","")&IF(OR(Q22>f_psf_hi,Q22<f_psf_lo),"$/sqft ",""))
A23: 10081 | B23: 45696 | C23: Maple Heights | D23: Townhouse | E23: 2 | F23: 1 | G23: 1320 | H23: 2300 | I23: 1988 | J23: 1 | K23: Excellent | L23: 250000 | M23: 239000 | N23: 40 | O23: 3.08 | P23: =DATE(YEAR(B23),MONTH(B23),1) -> 45689 | Q23: =M23/G23 -> 181.06061 | R23: =M23/L23 -> 0.956 | S23: =M23-L23 -> -11000 | T23: =IF(O23="","",M23*O23/100) -> 7361.2 | U23: =IF(I23="","",YEAR(B23)-I23) -> 37 | V23: =LOOKUP(M23,bin_lo,bin_lbl) -> $200-300K | W23: =TRIM(IF(M23>f_price_hi,"High price ","")&IF(AND(N23<>"",N23>f_dom_hi),"Long DOM ","")&IF(OR(Q23>f_psf_hi,Q23<f_psf_lo),"$/sqft ","")) | X23: condition standardised; living sqft imputed (group median)
A24: 10100 | B24: 45696 | C24: Cedar Park | D24: Single Family | E24: 3 | F24: 3 | G24: 1720 | H24: 6180 | I24: 1941 | J24: 1 | K24: Excellent | L24: 337000 | M24: 332000 | N24: 80 | O24: 2.68 | P24: =DATE(YEAR(B24),MONTH(B24),1) -> 45689 | Q24: =M24/G24 -> 193.02326 | R24: =M24/L24 -> 0.9851632 | S24: =M24-L24 -> -5000 | T24: =IF(O24="","",M24*O24/100) -> 8897.6 | U24: =IF(I24="","",YEAR(B24)-I24) -> 84 | V24: =LOOKUP(M24,bin_lo,bin_lbl) -> $300-400K | W24: =TRIM(IF(M24>f_price_hi,"High price ","")&IF(AND(N24<>"",N24>f_dom_hi),"Long DOM ","")&IF(OR(Q24>f_psf_hi,Q24<f_psf_lo),"$/sqft ",""))
A25: 10061 | B25: 45702 | C25: Maple Heights | D25: Single Family | E25: 3 | F25: 2.5 | G25: 1520 | H25: 6600 | I25: 1984 | J25: 0 | K25: Excellent | L25: 350000 | M25: 334000 | N25: 61 | O25: 3.03 | P25: =DATE(YEAR(B25),MONTH(B25),1) -> 45689 | Q25: =M25/G25 -> 219.73684 | R25: =M25/L25 -> 0.95428571 | S25: =M25-L25 -> -16000 | T25: =IF(O25="","",M25*O25/100) -> 10120.2 | U25: =IF(I25="","",YEAR(B25)-I25) -> 41 | V25: =LOOKUP(M25,bin_lo,bin_lbl) -> $300-400K | W25: =TRIM(IF(M25>f_price_hi,"High price ","")&IF(AND(N25<>"",N25>f_dom_hi),"Long DOM ","")&IF(OR(Q25>f_psf_hi,Q25<f_psf_lo),"$/sqft ",""))
A26: 10205 | B26: 45710 | C26: Oak Hill | D26: Single Family | E26: 3 | F26: 3 | G26: 1940 | H26: 4730 | I26: 2002 | J26: 1 | K26: Good | L26: 479000 | M26: 451000 | N26: 62 | O26: 2.71 | P26: =DATE(YEAR(B26),MONTH(B26),1) -> 45689 | Q26: =M26/G26 -> 232.47423 | R26: =M26/L26 -> 0.94154489 | S26: =M26-L26 -> -28000 | T26: =IF(O26="","",M26*O26/100) -> 12222.1 | U26: =IF(I26="","",YEAR(B26)-I26) -> 23 | V26: =LOOKUP(M26,bin_lo,bin_lbl) -> $400-500K | W26: =TRIM(IF(M26>f_price_hi,"High price ","")&IF(AND(N26<>"",N26>f_dom_hi),"Long DOM ","")&IF(OR(Q26>f_psf_hi,Q26<f_psf_lo),"$/sqft ",""))
A27: 10143 | B27: 45711 | C27: Cedar Park | D27: Single Family | E27: 3 | F27: 2.5 | G27: 1950 | H27: 8750 | I27: 2013 | J27: 2 | K27: Good | L27: 383000 | M27: 377000 | N27: 54 | O27: 3.11 | P27: =DATE(YEAR(B27),MONTH(B27),1) -> 45689 | Q27: =M27/G27 -> 193.33333 | R27: =M27/L27 -> 0.9843342 | S27: =M27-L27 -> -6000 | T27: =IF(O27="","",M27*O27/100) -> 11724.7 | U27: =IF(I27="","",YEAR(B27)-I27) -> 12 | V27: =LOOKUP(M27,bin_lo,bin_lbl) -> $300-400K | W27: =TRIM(IF(M27>f_price_hi,"High price ","")&IF(AND(N27<>"",N27>f_dom_hi),"Long DOM ","")&IF(OR(Q27>f_psf_hi,Q27<f_psf_lo),"$/sqft ",""))
A28: 10052 | B28: 45713 | C28: Oak Hill | D28: Single Family | E28: 4 | F28: 3 | G28: 2260 | H28: 10060 | I28: 1940 | J28: 0 | K28: Good | L28: 531000 | M28: 512000 | N28: 20 | O28: 3.07 | P28: =DATE(YEAR(B28),MONTH(B28),1) -> 45689 | Q28: =M28/G28 -> 226.54867 | R28: =M28/L28 -> 0.96421846 | S28: =M28-L28 -> -19000 | T28: =IF(O28="","",M28*O28/100) -> 15718.4 | U28: =IF(I28="","",YEAR(B28)-I28) -> 85 | V28: =LOOKUP(M28,bin_lo,bin_lbl) -> $500-600K | W28: =TRIM(IF(M28>f_price_hi,"High price ","")&IF(AND(N28<>"",N28>f_dom_hi),"Long DOM ","")&IF(OR(Q28>f_psf_hi,Q28<f_psf_lo),"$/sqft ",""))
A29: 10120 | B29: 45715 | C29: Maple Heights | D29: Condo | E29: 1 | F29: 1 | G29: 940 | H29: 0 | I29: 1997 | J29: 0 | K29: Good | L29: 185000 | M29: 177000 | N29: 41 | O29: 3.07 | P29: =DATE(YEAR(B29),MONTH(B29),1) -> 45689 | Q29: =M29/G29 -> 188.29787 | R29: =M29/L29 -> 0.95675676 | S29: =M29-L29 -> -8000 | T29: =IF(O29="","",M29*O29/100) -> 5433.9 | U29: =IF(I29="","",YEAR(B29)-I29) -> 28 | V29: =LOOKUP(M29,bin_lo,bin_lbl) -> Under $200K | W29: =TRIM(IF(M29>f_price_hi,"High price ","")&IF(AND(N29<>"",N29>f_dom_hi),"Long DOM ","")&IF(OR(Q29>f_psf_hi,Q29<f_psf_lo),"$/sqft ","")) | X29: neighborhood standardised
A30: 10135 | B30: 45716 | C30: Maple Heights | D30: Single Family | E30: 5 | F30: 3 | G30: 2660 | H30: 11020 | I30: 1964 | J30: 1 | K30: Good | L30: 501000 | M30: 478000 | O30: 3.05 | P30: =DATE(YEAR(B30),MONTH(B30),1) -> 45689 | Q30: =M30/G30 -> 179.69925 | R30: =M30/L30 -> 0.95409182 | S30: =M30-L30 -> -23000 | T30: =IF(O30="","",M30*O30/100) -> 14579 | U30: =IF(I30="","",YEAR(B30)-I30) -> 61 | V30: =LOOKUP(M30,bin_lo,bin_lbl) -> $400-500K | W30: =TRIM(IF(M30>f_price_hi,"High price ","")&IF(AND(N30<>"",N30>f_dom_hi),"Long DOM ","")&IF(OR(Q30>f_psf_hi,Q30<f_psf_lo),"$/sqft ","")) | X30: days_on_market left blank
A31: 10202 | B31: 45718 | C31: Cedar Park | D31: Condo | E31: 1 | F31: 1.5 | G31: 690 | H31: 0 | I31: 2018 | J31: 0 | K31: Good | L31: 131000 | M31: 131000 | N31: 37 | O31: 2.74 | P31: =DATE(YEAR(B31),MONTH(B31),1) -> 45717 | Q31: =M31/G31 -> 189.85507 | R31: =M31/L31 -> 1 | S31: =M31-L31 -> 0 | T31: =IF(O31="","",M31*O31/100) -> 3589.4 | U31: =IF(I31="","",YEAR(B31)-I31) -> 7 | V31: =LOOKUP(M31,bin_lo,bin_lbl) -> Under $200K | W31: =TRIM(IF(M31>f_price_hi,"High price ","")&IF(AND(N31<>"",N31>f_dom_hi),"Long DOM ","")&IF(OR(Q31>f_psf_hi,Q31<f_psf_lo),"$/sqft ","")) | X31: lot size set to 0 (condo, no lot)
A32: 10106 | B32: 45721 | C32: Downtown | D32: Single Family | E32: 2 | F32: 1.5 | G32: 1200 | H32: 4070 | I32: 2018 | J32: 2 | K32: Good | L32: 407000 | M32: 419000 | N32: 38 | O32: 2.52 | P32: =DATE(YEAR(B32),MONTH(B32),1) -> 45717 | Q32: =M32/G32 -> 349.16667 | R32: =M32/L32 -> 1.029484 | S32: =M32-L32 -> 12000 | T32: =IF(O32="","",M32*O32/100) -> 10558.8 | U32: =IF(I32="","",YEAR(B32)-I32) -> 7 | V32: =LOOKUP(M32,bin_lo,bin_lbl) -> $400-500K | W32: =TRIM(IF(M32>f_price_hi,"High price ","")&IF(AND(N32<>"",N32>f_dom_hi),"Long DOM ","")&IF(OR(Q32>f_psf_hi,Q32<f_psf_lo),"$/sqft ","")) | X32: property_type standardised
A33: 10003 | B33: 45723 | C33: Cedar Park | D33: Single Family | E33: 3 | F33: 3 | G33: 1590 | H33: 4020 | I33: 2021 | J33: 1 | K33: Excellent | L33: 350000 | M33: 352000 | N33: 41 | O33: 2.54 | P33: =DATE(YEAR(B33),MONTH(B33),1) -> 45717 | Q33: =M33/G33 -> 221.38365 | R33: =M33/L33 -> 1.0057143 | S33: =M33-L33 -> 2000 | T33: =IF(O33="","",M33*O33/100) -> 8940.8 | U33: =IF(I33="","",YEAR(B33)-I33) -> 4 | V33: =LOOKUP(M33,bin_lo,bin_lbl) -> $300-400K | W33: =TRIM(IF(M33>f_price_hi,"High price ","")&IF(AND(N33<>"",N33>f_dom_hi),"Long DOM ","")&IF(OR(Q33>f_psf_hi,Q33<f_psf_lo),"$/sqft ",""))
A34: 10104 | B34: 45724 | C34: Cedar Park | D34: Single Family | E34: 3 | F34: 2.5 | G34: 1550 | H34: 4630 | J34: 2 | K34: Fair | L34: 262000 | M34: 247000 | N34: 100 | O34: 3.02 | P34: =DATE(YEAR(B34),MONTH(B34),1) -> 45717 | Q34: =M34/G34 -> 159.35484 | R34: =M34/L34 -> 0.94274809 | S34: =M34-L34 -> -15000 | T34: =IF(O34="","",M34*O34/100) -> 7459.4 | U34: =IF(I34="","",YEAR(B34)-I34) | V34: =LOOKUP(M34,bin_lo,bin_lbl) -> $200-300K | W34: =TRIM(IF(M34>f_price_hi,"High price ","")&IF(AND(N34<>"",N34>f_dom_hi),"Long DOM ","")&IF(OR(Q34>f_psf_hi,Q34<f_psf_lo),"$/sqft ","")) | X34: year_built left blank
A35: 10210 | B35: 45724 | C35: Maple Heights | D35: Townhouse | E35: 3 | F35: 2 | G35: 1620 | H35: 1550 | I35: 2016 | J35: 1 | K35: Excellent | L35: 343000 | M35: 333000 | N35: 37 | O35: 3.04 | P35: =DATE(YEAR(B35),MONTH(B35),1) -> 45717 | Q35: =M35/G35 -> 205.55556 | R35: =M35/L35 -> 0.97084548 | S35: =M35-L35 -> -10000 | T35: =IF(O35="","",M35*O35/100) -> 10123.2 | U35: =IF(I35="","",YEAR(B35)-I35) -> 9 | V35: =LOOKUP(M35,bin_lo,bin_lbl) -> $300-400K | W35: =TRIM(IF(M35>f_price_hi,"High price ","")&IF(AND(N35<>"",N35>f_dom_hi),"Long DOM ","")&IF(OR(Q35>f_psf_hi,Q35<f_psf_lo),"$/sqft ",""))
A36: 10186 | B36: 45725 | C36: Maple Heights | D36: Single Family | E36: 5 | F36: 3.5 | G36: 2580 | H36: 6430 | I36: 2022 | J36: 2 | K36: Poor | L36: 476000 | M36: 443000 | N36: 87 | O36: 3.03 | P36: =DATE(YEAR(B36),MONTH(B36),1) -> 45717 | Q36: =M36/G36 -> 171.70543 | R36: =M36/L36 -> 0.93067227 | S36: =M36-L36 -> -33000 | T36: =IF(O36="","",M36*O36/100) -> 13422.9 | U36: =IF(I36="","",YEAR(B36)-I36) -> 3 | V36: =LOOKUP(M36,bin_lo,bin_lbl) -> $400-500K | W36: =TRIM(IF(M36>f_price_hi,"High price ","")&IF(AND(N36<>"",N36>f_dom_hi),"Long DOM ","")&IF(OR(Q36>f_psf_hi,Q36<f_psf_lo),"$/sqft ","")) | X36: living sqft imputed (group median)
A37: 10015 | B37: 45734 | C37: Riverside | D37: Condo | E37: 3 | F37: 3 | G37: 1890 | H37: 0 | I37: 1966 | J37: 1 | K37: Good | L37: 358000 | M37: 334000 | N37: 43 | O37: 3 | P37: =DATE(YEAR(B37),MONTH(B37),1) -> 45717 | Q37: =M37/G37 -> 176.71958 | R37: =M37/L37 -> 0.93296089 | S37: =M37-L37 -> -24000 | T37: =IF(O37="","",M37*O37/100) -> 10020 | U37: =IF(I37="","",YEAR(B37)-I37) -> 59 | V37: =LOOKUP(M37,bin_lo,bin_lbl) -> $300-400K | W37: =TRIM(IF(M37>f_price_hi,"High price ","")&IF(AND(N37<>"",N37>f_dom_hi),"Long DOM ","")&IF(OR(Q37>f_psf_hi,Q37<f_psf_lo),"$/sqft ","")) | X37: neighborhood standardised; living sqft imputed (group median)
A38: 10132 | B38: 45734 | C38: Cedar Park | D38: Condo | E38: 2 | F38: 2 | G38: 1070 | H38: 0 | I38: 1989 | J38: 0 | K38: Excellent | L38: 196000 | M38: 190000 | N38: 45 | O38: 2.97 | P38: =DATE(YEAR(B38),MONTH(B38),1) -> 45717 | Q38: =M38/G38 -> 177.57009 | R38: =M38/L38 -> 0.96938776 | S38: =M38-L38 -> -6000 | T38: =IF(O38="","",M38*O38/100) -> 5643 | U38: =IF(I38="","",YEAR(B38)-I38) -> 36 | V38: =LOOKUP(M38,bin_lo,bin_lbl) -> Under $200K | W38: =TRIM(IF(M38>f_price_hi,"High price ","")&IF(AND(N38<>"",N38>f_dom_hi),"Long DOM ","")&IF(OR(Q38>f_psf_hi,Q38<f_psf_lo),"$/sqft ","")) | X38: condition standardised
A39: 10062 | B39: 45735 | C39: Oak Hill | D39: Single Family | E39: 6 | F39: 5.5 | G39: 6400 | H39: 41000 | I39: 2019 | J39: 4 | K39: Excellent | L39: 3450000 | M39: 3310000 | N39: 61 | O39: 2.49 | P39: =DATE(YEAR(B39),MONTH(B39),1) -> 45717 | Q39: =M39/G39 -> 517.1875 | R39: =M39/L39 -> 0.95942029 | S39: =M39-L39 -> -140000 | T39: =IF(O39="","",M39*O39/100) -> 82419 | U39: =IF(I39="","",YEAR(B39)-I39) -> 6 | V39: =LOOKUP(M39,bin_lo,bin_lbl) -> $800K+ | W39: =TRIM(IF(M39>f_price_hi,"High price ","")&IF(AND(N39<>"",N39>f_dom_hi),"Long DOM ","")&IF(OR(Q39>f_psf_hi,Q39<f_psf_lo),"$/sqft ","")) -> High price $/sqft
A40: 10031 | B40: 45737 | C40: Downtown | D40: Single Family | E40: 3 | F40: 2.5 | G40: 1640 | H40: 6560 | I40: 1998 | J40: 2 | K40: Excellent | L40: 535000 | M40: 489000 | N40: 41 | O40: 2.99 | P40: =DATE(YEAR(B40),MONTH(B40),1) -> 45717 | Q40: =M40/G40 -> 298.17073 | R40: =M40/L40 -> 0.91401869 | S40: =M40-L40 -> -46000 | T40: =IF(O40="","",M40*O40/100) -> 14621.1 | U40: =IF(I40="","",YEAR(B40)-I40) -> 27 | V40: =LOOKUP(M40,bin_lo,bin_lbl) -> $400-500K | W40: =TRIM(IF(M40>f_price_hi,"High price ","")&IF(AND(N40<>"",N40>f_dom_hi),"Long DOM ","")&IF(OR(Q40>f_psf_hi,Q40<f_psf_lo),"$/sqft ",""))
A41: 10237 | B41: 45737 | C41: Riverside | D41: Single Family | E41: 5 | F41: 3.5 | G41: 2520 | H41: 6390 | I41: 2015 | J41: 2 | K41: Fair | L41: 476000 | M41: 463000 | N41: 54 | O41: 3.04 | P41: =DATE(YEAR(B41),MONTH(B41),1) -> 45717 | Q41: =M41/G41 -> 183.73016 | R41: =M41/L41 -> 0.97268908 | S41: =M41-L41 -> -13000 | T41: =IF(O41="","",M41*O41/100) -> 14075.2 | U41: =IF(I41="","",YEAR(B41)-I41) -> 10 | V41: =LOOKUP(M41,bin_lo,bin_lbl) -> $400-500K | W41: =TRIM(IF(M41>f_price_hi,"High price ","")&IF(AND(N41<>"",N41>f_dom_hi),"Long DOM ","")&IF(OR(Q41>f_psf_hi,Q41<f_psf_lo),"$/sqft ","")) | X41: lot size imputed (group median)
A42: 10099 | B42: 45738 | C42: Oak Hill | D42: Single Family | E42: 3 | F42: 2.5 | G42: 1880 | H42: 8190 | I42: 2010 | J42: 2 | K42: Unknown | L42: 539000 | M42: 513000 | N42: 93 | O42: 3.25 | P42: =DATE(YEAR(B42),MONTH(B42),1) -> 45717 | Q42: =M42/G42 -> 272.87234 | R42: =M42/L42 -> 0.95176252 | S42: =M42-L42 -> -26000 | T42: =IF(O42="","",M42*O42/100) -> 16672.5 | U42: =IF(I42="","",YEAR(B42)-I42) -> 15 | V42: =LOOKUP(M42,bin_lo,bin_lbl) -> $500-600K | W42: =TRIM(IF(M42>f_price_hi,"High price ","")&IF(AND(N42<>"",N42>f_dom_hi),"Long DOM ","")&IF(OR(Q42>f_psf_hi,Q42<f_psf_lo),"$/sqft ","")) | X42: neighborhood standardised; condition missing -> Unknown
A43: 10235 | B43: 45740 | C43: Cedar Park | D43: Single Family | E43: 4 | F43: 3 | G43: 1960 | H43: 6730 | I43: 1998 | J43: 2 | K43: Good | L43: 335000 | M43: 320000 | N43: 64 | O43: 3.04 | P43: =DATE(YEAR(B43),MONTH(B43),1) -> 45717 | Q43: =M43/G43 -> 163.26531 | R43: =M43/L43 -> 0.95522388 | S43: =M43-L43 -> -15000 | T43: =IF(O43="","",M43*O43/100) -> 9728 | U43: =IF(I43="","",YEAR(B43)-I43) -> 27 | V43: =LOOKUP(M43,bin_lo,bin_lbl) -> $300-400K | W43: =TRIM(IF(M43>f_price_hi,"High price ","")&IF(AND(N43<>"",N43>f_dom_hi),"Long DOM ","")&IF(OR(Q43>f_psf_hi,Q43<f_psf_lo),"$/sqft ",""))
A44: 10116 | B44: 45742 | C44: Cedar Park | D44: Single Family | E44: 4 | F44: 3.5 | G44: 1960 | H44: 5550 | I44: 2017 | J44: 2 | K44: Good | L44: 408000 | M44: 392000 | N44: 49 | O44: 3.18 | P44: =DATE(YEAR(B44),MONTH(B44),1) -> 45717 | Q44: =M44/G44 -> 200 | R44: =M44/L44 -> 0.96078431 | S44: =M44-L44 -> -16000 | T44: =IF(O44="","",M44*O44/100) -> 12465.6 | U44: =IF(I44="","",YEAR(B44)-I44) -> 8 | V44: =LOOKUP(M44,bin_lo,bin_lbl) -> $300-400K | W44: =TRIM(IF(M44>f_price_hi,"High price ","")&IF(AND(N44<>"",N44>f_dom_hi),"Long DOM ","")&IF(OR(Q44>f_psf_hi,Q44<f_psf_lo),"$/sqft ",""))
A45: 10156 | B45: 45743 | C45: Maple Heights | D45: Condo | E45: 2 | F45: 2 | G45: 1400 | H45: 0 | I45: 2015 | J45: 1 | K45: Fair | L45: 270000 | M45: 264000 | O45: 2.95 | P45: =DATE(YEAR(B45),MONTH(B45),1) -> 45717 | Q45: =M45/G45 -> 188.57143 | R45: =M45/L45 -> 0.97777778 | S45: =M45-L45 -> -6000 | T45: =IF(O45="","",M45*O45/100) -> 7788 | U45: =IF(I45="","",YEAR(B45)-I45) -> 10 | V45: =LOOKUP(M45,bin_lo,bin_lbl) -> $200-300K | W45: =TRIM(IF(M45>f_price_hi,"High price ","")&IF(AND(N45<>"",N45>f_dom_hi),"Long DOM ","")&IF(OR(Q45>f_psf_hi,Q45<f_psf_lo),"$/sqft ","")) | X45: property_type standardised; days_on_market left blank
A46: 10113 | B46: 45744 | C46: Riverside | D46: Single Family | E46: 4 | F46: 4 | G46: 2230 | H46: 5110 | I46: 2016 | J46: 2 | K46: Fair | L46: 479000 | M46: 487000 | N46: 44 | O46: 3.33 | P46: =DATE(YEAR(B46),MONTH(B46),1) -> 45717 | Q46: =M46/G46 -> 218.38565 | R46: =M46/L46 -> 1.0167015 | S46: =M46-L46 -> 8000 | T46: =IF(O46="","",M46*O46/100) -> 16217.1 | U46: =IF(I46="","",YEAR(B46)-I46) -> 9 | V46: =LOOKUP(M46,bin_lo,bin_lbl) -> $400-500K | W46: =TRIM(IF(M46>f_price_hi,"High price ","")&IF(AND(N46<>"",N46>f_dom_hi),"Long DOM ","")&IF(OR(Q46>f_psf_hi,Q46<f_psf_lo),"$/sqft ","")) | X46: condition standardised
A47: 10218 | B47: 45745 | C47: Oak Hill | D47: Condo | E47: 1 | F47: 1 | G47: 940 | H47: 0 | I47: 1980 | J47: 0 | K47: Excellent | L47: 253000 | M47: 244000 | N47: 26 | O47: 3.32 | P47: =DATE(YEAR(B47),MONTH(B47),1) -> 45717 | Q47: =M47/G47 -> 259.57447 | R47: =M47/L47 -> 0.96442688 | S47: =M47-L47 -> -9000 | T47: =IF(O47="","",M47*O47/100) -> 8100.8 | U47: =IF(I47="","",YEAR(B47)-I47) -> 45 | V47: =LOOKUP(M47,bin_lo,bin_lbl) -> $200-300K | W47: =TRIM(IF(M47>f_price_hi,"High price ","")&IF(AND(N47<>"",N47>f_dom_hi),"Long DOM ","")&IF(OR(Q47>f_psf_hi,Q47<f_psf_lo),"$/sqft ","")) | X47: condition standardised
A48: 10018 | B48: 45746 | C48: Oak Hill | D48: Single Family | E48: 5 | F48: 3.5 | G48: 2350 | H48: 5240 | I48: 1981 | J48: 1 | K48: Unknown | L48: 555000 | M48: 548000 | N48: 69 | O48: 3.01 | P48: =DATE(YEAR(B48),MONTH(B48),1) -> 45717 | Q48: =M48/G48 -> 233.19149 | R48: =M48/L48 -> 0.98738739 | S48: =M48-L48 -> -7000 | T48: =IF(O48="","",M48*O48/100) -> 16494.8 | U48: =IF(I48="","",YEAR(B48)-I48) -> 44 | V48: =LOOKUP(M48,bin_lo,bin_lbl) -> $500-600K | W48: =TRIM(IF(M48>f_price_hi,"High price ","")&IF(AND(N48<>"",N48>f_dom_hi),"Long DOM ","")&IF(OR(Q48>f_psf_hi,Q48<f_psf_lo),"$/sqft ","")) | X48: property_type standardised; condition missing -> Unknown
A49: 10039 | B49: 45746 | C49: Riverside | D49: Single Family | E49: 3 | F49: 2.5 | G49: 1860 | H49: 8070 | I49: 1970 | J49: 1 | K49: Fair | L49: 379000 | M49: 370000 | N49: 50 | O49: 3.1 | P49: =DATE(YEAR(B49),MONTH(B49),1) -> 45717 | Q49: =M49/G49 -> 198.92473 | R49: =M49/L49 -> 0.9762533 | S49: =M49-L49 -> -9000 | T49: =IF(O49="","",M49*O49/100) -> 11470 | U49: =IF(I49="","",YEAR(B49)-I49) -> 55 | V49: =LOOKUP(M49,bin_lo,bin_lbl) -> $300-400K | W49: =TRIM(IF(M49>f_price_hi,"High price ","")&IF(AND(N49<>"",N49>f_dom_hi),"Long DOM ","")&IF(OR(Q49>f_psf_hi,Q49<f_psf_lo),"$/sqft ",""))
A50: 10060 | B50: 45751 | C50: Oak Hill | D50: Single Family | E50: 5 | F50: 5.5 | G50: 2270 | H50: 7210 | I50: 2000 | J50: 2 | K50: Excellent | L50: 674000 | M50: 697000 | N50: 32 | O50: 2.75 | P50: =DATE(YEAR(B50),MONTH(B50),1) -> 45748 | Q50: =M50/G50 -> 307.04846 | R50: =M50/L50 -> 1.0341246 | S50: =M50-L50 -> 23000 | T50: =IF(O50="","",M50*O50/100) -> 19167.5 | U50: =IF(I50="","",YEAR(B50)-I50) -> 25 | V50: =LOOKUP(M50,bin_lo,bin_lbl) -> $600-800K | W50: =TRIM(IF(M50>f_price_hi,"High price ","")&IF(AND(N50<>"",N50>f_dom_hi),"Long DOM ","")&IF(OR(Q50>f_psf_hi,Q50<f_psf_lo),"$/sqft ","")) -> High price
A51: 10065 | B51: 45753 | C51: Maple Heights | D51: Single Family | E51: 2 | F51: 2.5 | G51: 1240 | H51: 4170 | I51: 2024 | J51: 2 | K51: Fair | L51: 333000 | M51: 315000 | N51: 56 | P51: =DATE(YEAR(B51),MONTH(B51),1) -> 45748 | Q51: =M51/G51 -> 254.03226 | R51: =M51/L51 -> 0.94594595 | S51: =M51-L51 -> -18000 | T51: =IF(O51="","",M51*O51/100) | U51: =IF(I51="","",YEAR(B51)-I51) -> 1 | V51: =LOOKUP(M51,bin_lo,bin_lbl) -> $300-400K | W51: =TRIM(IF(M51>f_price_hi,"High price ","")&IF(AND(N51<>"",N51>f_dom_hi),"Long DOM ","")&IF(OR(Q51>f_psf_hi,Q51<f_psf_lo),"$/sqft ","")) | X51: property_type standardised; condition standardised; commission left blank
A52: 10199 | B52: 45753 | C52: Oak Hill | D52: Single Family | E52: 4 | F52: 3 | G52: 2300 | H52: 6040 | I52: 2013 | J52: 2 | K52: Good | L52: 643000 | M52: 636000 | N52: 59 | O52: 2.72 | P52: =DATE(YEAR(B52),MONTH(B52),1) -> 45748 | Q52: =M52/G52 -> 276.52174 | R52: =M52/L52 -> 0.98911353 | S52: =M52-L52 -> -7000 | T52: =IF(O52="","",M52*O52/100) -> 17299.2 | U52: =IF(I52="","",YEAR(B52)-I52) -> 12 | V52: =LOOKUP(M52,bin_lo,bin_lbl) -> $600-800K | W52: =TRIM(IF(M52>f_price_hi,"High price ","")&IF(AND(N52<>"",N52>f_dom_hi),"Long DOM ","")&IF(OR(Q52>f_psf_hi,Q52<f_psf_lo),"$/sqft ","")) | X52: garage imputed (group median)
A53: 10194 | B53: 45759 | C53: Cedar Park | D53: Single Family | E53: 2 | F53: 1.5 | G53: 1240 | H53: 3470 | I53: 1983 | J53: 1 | K53: Poor | L53: 204000 | M53: 201000 | N53: 69 | O53: 2.74 | P53: =DATE(YEAR(B53),MONTH(B53),1) -> 45748 | Q53: =M53/G53 -> 162.09677 | R53: =M53/L53 -> 0.98529412 | S53: =M53-L53 -> -3000 | T53: =IF(O53="","",M53*O53/100) -> 5507.4 | U53: =IF(I53="","",YEAR(B53)-I53) -> 42 | V53: =LOOKUP(M53,bin_lo,bin_lbl) -> $200-300K | W53: =TRIM(IF(M53>f_price_hi,"High price ","")&IF(AND(N53<>"",N53>f_dom_hi),"Long DOM ","")&IF(OR(Q53>f_psf_hi,Q53<f_psf_lo),"$/sqft ",""))
A54: 10182 | B54: 45760 | C54: Cedar Park | D54: Townhouse | E54: 2 | F54: 1.5 | G54: 1400 | H54: 2140 | I54: 1969 | J54: 1 | K54: Unknown | L54: 216000 | M54: 214000 | N54: 45 | O54: 2.71 | P54: =DATE(YEAR(B54),MONTH(B54),1) -> 45748 | Q54: =M54/G54 -> 152.85714 | R54: =M54/L54 -> 0.99074074 | S54: =M54-L54 -> -2000 | T54: =IF(O54="","",M54*O54/100) -> 5799.4 | U54: =IF(I54="","",YEAR(B54)-I54) -> 56 | V54: =LOOKUP(M54,bin_lo,bin_lbl) -> $200-300K | W54: =TRIM(IF(M54>f_price_hi,"High price ","")&IF(AND(N54<>"",N54>f_dom_hi),"Long DOM ","")&IF(OR(Q54>f_psf_hi,Q54<f_psf_lo),"$/sqft ","")) | X54: condition missing -> Unknown
A55: 10088 | B55: 45762 | C55: Riverside | D55: Townhouse | E55: 3 | F55: 2.5 | G55: 1600 | H55: 2360 | I55: 2003 | J55: 2 | K55: Excellent | L55: 380000 | M55: 382000 | N55: 48 | O55: 3.18 | P55: =DATE(YEAR(B55),MONTH(B55),1) -> 45748 | Q55: =M55/G55 -> 238.75 | R55: =M55/L55 -> 1.0052632 | S55: =M55-L55 -> 2000 | T55: =IF(O55="","",M55*O55/100) -> 12147.6 | U55: =IF(I55="","",YEAR(B55)-I55) -> 22 | V55: =LOOKUP(M55,bin_lo,bin_lbl) -> $300-400K | W55: =TRIM(IF(M55>f_price_hi,"High price ","")&IF(AND(N55<>"",N55>f_dom_hi),"Long DOM ","")&IF(OR(Q55>f_psf_hi,Q55<f_psf_lo),"$/sqft ","")) | X55: garage imputed (group median)
A56: 10093 | B56: 45763 | C56: Riverside | D56: Townhouse | E56: 2 | F56: 1.5 | G56: 1210 | H56: 2540 | I56: 1985 | J56: 1 | K56: Excellent | L56: 285000 | M56: 280000 | N56: 56 | O56: 3.02 | P56: =DATE(YEAR(B56),MONTH(B56),1) -> 45748 | Q56: =M56/G56 -> 231.40496 | R56: =M56/L56 -> 0.98245614 | S56: =M56-L56 -> -5000 | T56: =IF(O56="","",M56*O56/100) -> 8456 | U56: =IF(I56="","",YEAR(B56)-I56) -> 40 | V56: =LOOKUP(M56,bin_lo,bin_lbl) -> $200-300K | W56: =TRIM(IF(M56>f_price_hi,"High price ","")&IF(AND(N56<>"",N56>f_dom_hi),"Long DOM ","")&IF(OR(Q56>f_psf_hi,Q56<f_psf_lo),"$/sqft ",""))
A57: 10214 | B57: 45763 | C57: Downtown | D57: Single Family | E57: 3 | F57: 3 | G57: 1820 | H57: 7970 | I57: 1937 | J57: 1 | K57: Excellent | L57: 609000 | M57: 599000 | N57: 24 | O57: 2.55 | P57: =DATE(YEAR(B57),MONTH(B57),1) -> 45748 | Q57: =M57/G57 -> 329.12088 | R57: =M57/L57 -> 0.98357964 | S57: =M57-L57 -> -10000 | T57: =IF(O57="","",M57*O57/100) -> 15274.5 | U57: =IF(I57="","",YEAR(B57)-I57) -> 88 | V57: =LOOKUP(M57,bin_lo,bin_lbl) -> $500-600K | W57: =TRIM(IF(M57>f_price_hi,"High price ","")&IF(AND(N57<>"",N57>f_dom_hi),"Long DOM ","")&IF(OR(Q57>f_psf_hi,Q57<f_psf_lo),"$/sqft ","")) | X57: condition standardised
A58: 10094 | B58: 45764 | C58: Riverside | D58: Single Family | E58: 4 | F58: 3 | G58: 2110 | H58: 5240 | I58: 2021 | J58: 2 | K58: Excellent | L58: 585000 | M58: 590000 | N58: 61 | O58: 2.57 | P58: =DATE(YEAR(B58),MONTH(B58),1) -> 45748 | Q58: =M58/G58 -> 279.62085 | R58: =M58/L58 -> 1.008547 | S58: =M58-L58 -> 5000 | T58: =IF(O58="","",M58*O58/100) -> 15163 | U58: =IF(I58="","",YEAR(B58)-I58) -> 4 | V58: =LOOKUP(M58,bin_lo,bin_lbl) -> $500-600K | W58: =TRIM(IF(M58>f_price_hi,"High price ","")&IF(AND(N58<>"",N58>f_dom_hi),"Long DOM ","")&IF(OR(Q58>f_psf_hi,Q58<f_psf_lo),"$/sqft ","")) | X58: property_type standardised
A59: 10008 | B59: 45771 | C59: Downtown | D59: Single Family | E59: 4 | F59: 3 | G59: 1940 | H59: 4890 | I59: 1955 | J59: 0 | K59: Excellent | L59: 682000 | M59: 654000 | N59: 66 | O59: 2.96 | P59: =DATE(YEAR(B59),MONTH(B59),1) -> 45748 | Q59: =M59/G59 -> 337.1134 | R59: =M59/L59 -> 0.95894428 | S59: =M59-L59 -> -28000 | T59: =IF(O59="","",M59*O59/100) -> 19358.4 | U59: =IF(I59="","",YEAR(B59)-I59) -> 70 | V59: =LOOKUP(M59,bin_lo,bin_lbl) -> $600-800K | W59: =TRIM(IF(M59>f_price_hi,"High price ","")&IF(AND(N59<>"",N59>f_dom_hi),"Long DOM ","")&IF(OR(Q59>f_psf_hi,Q59<f_psf_lo),"$/sqft ",""))
A60: 10098 | B60: 45773 | C60: Oak Hill | D60: Single Family | E60: 3 | F60: 2.5 | G60: 1870 | H60: 7580 | I60: 1989 | J60: 0 | K60: Good | L60: 516000 | M60: 496000 | N60: 51 | O60: 3 | P60: =DATE(YEAR(B60),MONTH(B60),1) -> 45748 | Q60: =M60/G60 -> 265.24064 | R60: =M60/L60 -> 0.96124031 | S60: =M60-L60 -> -20000 | T60: =IF(O60="","",M60*O60/100) -> 14880 | U60: =IF(I60="","",YEAR(B60)-I60) -> 36 | V60: =LOOKUP(M60,bin_lo,bin_lbl) -> $400-500K | W60: =TRIM(IF(M60>f_price_hi,"High price ","")&IF(AND(N60<>"",N60>f_dom_hi),"Long DOM ","")&IF(OR(Q60>f_psf_hi,Q60<f_psf_lo),"$/sqft ","")) | X60: neighborhood standardised
A61: 10216 | B61: 45773 | C61: Downtown | D61: Condo | E61: 2 | F61: 1 | G61: 1040 | H61: 0 | I61: 1993 | J61: 0 | K61: Good | L61: 334000 | M61: 319000 | N61: 62 | O61: 2.71 | P61: =DATE(YEAR(B61),MONTH(B61),1) -> 45748 | Q61: =M61/G61 -> 306.73077 | R61: =M61/L61 -> 0.95508982 | S61: =M61-L61 -> -15000 | T61: =IF(O61="","",M61*O61/100) -> 8644.9 | U61: =IF(I61="","",YEAR(B61)-I61) -> 32 | V61: =LOOKUP(M61,bin_lo,bin_lbl) -> $300-400K | W61: =TRIM(IF(M61>f_price_hi,"High price ","")&IF(AND(N61<>"",N61>f_dom_hi),"Long DOM ","")&IF(OR(Q61>f_psf_hi,Q61<f_psf_lo),"$/sqft ","")) | X61: lot size set to 0 (condo, no lot)
A62: 10236 | B62: 45776 | C62: Downtown | D62: Single Family | E62: 2 | F62: 1 | G62: 1380 | H62: 3980 | I62: 1951 | J62: 1 | K62: Fair | L62: 365000 | M62: 373000 | N62: 62 | O62: 3.21 | P62: =DATE(YEAR(B62),MONTH(B62),1) -> 45748 | Q62: =M62/G62 -> 270.28986 | R62: =M62/L62 -> 1.0219178 | S62: =M62-L62 -> 8000 | T62: =IF(O62="","",M62*O62/100) -> 11973.3 | U62: =IF(I62="","",YEAR(B62)-I62) -> 74 | V62: =LOOKUP(M62,bin_lo,bin_lbl) -> $300-400K | W62: =TRIM(IF(M62>f_price_hi,"High price ","")&IF(AND(N62<>"",N62>f_dom_hi),"Long DOM ","")&IF(OR(Q62>f_psf_hi,Q62<f_psf_lo),"$/sqft ",""))
A63: 10056 | B63: 45780 | C63: Downtown | D63: Condo | E63: 1 | F63: 1 | G63: 920 | H63: 0 | I63: 2001 | J63: 0 | K63: Good | L63: 313000 | M63: 294000 | N63: 62 | O63: 3.1 | P63: =DATE(YEAR(B63),MONTH(B63),1) -> 45778 | Q63: =M63/G63 -> 319.56522 | R63: =M63/L63 -> 0.93929712 | S63: =M63-L63 -> -19000 | T63: =IF(O63="","",M63*O63/100) -> 9114 | U63: =IF(I63="","",YEAR(B63)-I63) -> 24 | V63: =LOOKUP(M63,bin_lo,bin_lbl) -> $200-300K | W63: =TRIM(IF(M63>f_price_hi,"High price ","")&IF(AND(N63<>"",N63>f_dom_hi),"Long DOM ","")&IF(OR(Q63>f_psf_hi,Q63<f_psf_lo),"$/sqft ",""))
A64: 10211 | B64: 45780 | C64: Downtown | D64: Single Family | E64: 4 | F64: 2.5 | G64: 2150 | H64: 5160 | I64: 1968 | J64: 2 | K64: Excellent | L64: 620000 | M64: 596000 | N64: 61 | O64: 3.05 | P64: =DATE(YEAR(B64),MONTH(B64),1) -> 45778 | Q64: =M64/G64 -> 277.2093 | R64: =M64/L64 -> 0.96129032 | S64: =M64-L64 -> -24000 | T64: =IF(O64="","",M64*O64/100) -> 18178 | U64: =IF(I64="","",YEAR(B64)-I64) -> 57 | V64: =LOOKUP(M64,bin_lo,bin_lbl) -> $500-600K | W64: =TRIM(IF(M64>f_price_hi,"High price ","")&IF(AND(N64<>"",N64>f_dom_hi),"Long DOM ","")&IF(OR(Q64>f_psf_hi,Q64<f_psf_lo),"$/sqft ",""))
A65: 10128 | B65: 45782 | C65: Oak Hill | D65: Single Family | E65: 4 | F65: 3 | G65: 2330 | H65: 10440 | I65: 2018 | J65: 1 | K65: Good | L65: 615000 | M65: 608000 | N65: 38 | O65: 3.18 | P65: =DATE(YEAR(B65),MONTH(B65),1) -> 45778 | Q65: =M65/G65 -> 260.94421 | R65: =M65/L65 -> 0.98861789 | S65: =M65-L65 -> -7000 | T65: =IF(O65="","",M65*O65/100) -> 19334.4 | U65: =IF(I65="","",YEAR(B65)-I65) -> 7 | V65: =LOOKUP(M65,bin_lo,bin_lbl) -> $600-800K | W65: =TRIM(IF(M65>f_price_hi,"High price ","")&IF(AND(N65<>"",N65>f_dom_hi),"Long DOM ","")&IF(OR(Q65>f_psf_hi,Q65<f_psf_lo),"$/sqft ","")) | X65: property_type standardised
A66: 10134 | B66: 45783 | C66: Riverside | D66: Single Family | E66: 5 | F66: 3.5 | G66: 2480 | H66: 9820 | I66: 2014 | J66: 2 | K66: Excellent | L66: 591000 | M66: 596000 | N66: 48 | O66: 2.95 | P66: =DATE(YEAR(B66),MONTH(B66),1) -> 45778 | Q66: =M66/G66 -> 240.32258 | R66: =M66/L66 -> 1.0084602 | S66: =M66-L66 -> 5000 | T66: =IF(O66="","",M66*O66/100) -> 17582 | U66: =IF(I66="","",YEAR(B66)-I66) -> 11 | V66: =LOOKUP(M66,bin_lo,bin_lbl) -> $500-600K | W66: =TRIM(IF(M66>f_price_hi,"High price ","")&IF(AND(N66<>"",N66>f_dom_hi),"Long DOM ","")&IF(OR(Q66>f_psf_hi,Q66<f_psf_lo),"$/sqft ","")) | X66: bathrooms imputed (group median)
A67: 10225 | B67: 45787 | C67: Riverside | D67: Single Family | E67: 4 | F67: 2.5 | G67: 2060 | H67: 7630 | I67: 2018 | J67: 2 | K67: Unknown | L67: 430000 | M67: 405000 | N67: 40 | O67: 2.93 | P67: =DATE(YEAR(B67),MONTH(B67),1) -> 45778 | Q67: =M67/G67 -> 196.60194 | R67: =M67/L67 -> 0.94186047 | S67: =M67-L67 -> -25000 | T67: =IF(O67="","",M67*O67/100) -> 11866.5 | U67: =IF(I67="","",YEAR(B67)-I67) -> 7 | V67: =LOOKUP(M67,bin_lo,bin_lbl) -> $400-500K | W67: =TRIM(IF(M67>f_price_hi,"High price ","")&IF(AND(N67<>"",N67>f_dom_hi),"Long DOM ","")&IF(OR(Q67>f_psf_hi,Q67<f_psf_lo),"$/sqft ","")) | X67: condition missing -> Unknown
A68: 10177 | B68: 45794 | C68: Riverside | D68: Single Family | E68: 3 | F68: 2 | G68: 1440 | H68: 6370 | I68: 2016 | J68: 2 | K68: Fair | L68: 351000 | M68: 336000 | N68: 78 | O68: 3.02 | P68: =DATE(YEAR(B68),MONTH(B68),1) -> 45778 | Q68: =M68/G68 -> 233.33333 | R68: =M68/L68 -> 0.95726496 | S68: =M68-L68 -> -15000 | T68: =IF(O68="","",M68*O68/100) -> 10147.2 | U68: =IF(I68="","",YEAR(B68)-I68) -> 9 | V68: =LOOKUP(M68,bin_lo,bin_lbl) -> $300-400K | W68: =TRIM(IF(M68>f_price_hi,"High price ","")&IF(AND(N68<>"",N68>f_dom_hi),"Long DOM ","")&IF(OR(Q68>f_psf_hi,Q68<f_psf_lo),"$/sqft ","")) | X68: neighborhood standardised
A69: 10166 | B69: 45800 | C69: Riverside | D69: Single Family | E69: 4 | F69: 2.5 | G69: 2360 | H69: 7460 | I69: 2000 | J69: 2 | K69: Good | L69: 511000 | M69: 514000 | N69: 51 | O69: 3.24 | P69: =DATE(YEAR(B69),MONTH(B69),1) -> 45778 | Q69: =M69/G69 -> 217.79661 | R69: =M69/L69 -> 1.0058708 | S69: =M69-L69 -> 3000 | T69: =IF(O69="","",M69*O69/100) -> 16653.6 | U69: =IF(I69="","",YEAR(B69)-I69) -> 25 | V69: =LOOKUP(M69,bin_lo,bin_lbl) -> $500-600K | W69: =TRIM(IF(M69>f_price_hi,"High price ","")&IF(AND(N69<>"",N69>f_dom_hi),"Long DOM ","")&IF(OR(Q69>f_psf_hi,Q69<f_psf_lo),"$/sqft ","")) | X69: property_type standardised; condition standardised; garage imputed (group median)
A70: 10073 | B70: 45803 | C70: Cedar Park | D70: Single Family | E70: 2 | F70: 1 | G70: 1480 | H70: 3890 | I70: 2016 | J70: 2 | K70: Fair | L70: 244000 | M70: 238000 | N70: 83 | O70: 2.54 | P70: =DATE(YEAR(B70),MONTH(B70),1) -> 45778 | Q70: =M70/G70 -> 160.81081 | R70: =M70/L70 -> 0.97540984 | S70: =M70-L70 -> -6000 | T70: =IF(O70="","",M70*O70/100) -> 6045.2 | U70: =IF(I70="","",YEAR(B70)-I70) -> 9 | V70: =LOOKUP(M70,bin_lo,bin_lbl) -> $200-300K | W70: =TRIM(IF(M70>f_price_hi,"High price ","")&IF(AND(N70<>"",N70>f_dom_hi),"Long DOM ","")&IF(OR(Q70>f_psf_hi,Q70<f_psf_lo),"$/sqft ",""))
A71: 10224 | B71: 45807 | C71: Cedar Park | D71: Single Family | E71: 3 | F71: 3 | G71: 1950 | H71: 4460 | I71: 1983 | J71: 2 | K71: Good | L71: 350000 | M71: 355000 | N71: 96 | O71: 2.69 | P71: =DATE(YEAR(B71),MONTH(B71),1) -> 45778 | Q71: =M71/G71 -> 182.05128 | R71: =M71/L71 -> 1.0142857 | S71: =M71-L71 -> 5000 | T71: =IF(O71="","",M71*O71/100) -> 9549.5 | U71: =IF(I71="","",YEAR(B71)-I71) -> 42 | V71: =LOOKUP(M71,bin_lo,bin_lbl) -> $300-400K | W71: =TRIM(IF(M71>f_price_hi,"High price ","")&IF(AND(N71<>"",N71>f_dom_hi),"Long DOM ","")&IF(OR(Q71>f_psf_hi,Q71<f_psf_lo),"$/sqft ",""))
A72: 10172 | B72: 45808 | C72: Maple Heights | D72: Single Family | E72: 3 | F72: 3 | G72: 1600 | H72: 5040 | I72: 1990 | J72: 0 | K72: Good | L72: 328000 | M72: 317000 | N72: 68 | O72: 2.99 | P72: =DATE(YEAR(B72),MONTH(B72),1) -> 45778 | Q72: =M72/G72 -> 198.125 | R72: =M72/L72 -> 0.96646341 | S72: =M72-L72 -> -11000 | T72: =IF(O72="","",M72*O72/100) -> 9478.3 | U72: =IF(I72="","",YEAR(B72)-I72) -> 35 | V72: =LOOKUP(M72,bin_lo,bin_lbl) -> $300-400K | W72: =TRIM(IF(M72>f_price_hi,"High price ","")&IF(AND(N72<>"",N72>f_dom_hi),"Long DOM ","")&IF(OR(Q72>f_psf_hi,Q72<f_psf_lo),"$/sqft ",""))
A73: 10180 | B73: 45810 | C73: Downtown | D73: Condo | E73: 2 | F73: 2 | G73: 1280 | H73: 0 | I73: 1974 | J73: 1 | K73: Fair | L73: 422000 | M73: 383000 | N73: 73 | O73: 2.98 | P73: =DATE(YEAR(B73),MONTH(B73),1) -> 45809 | Q73: =M73/G73 -> 299.21875 | R73: =M73/L73 -> 0.90758294 | S73: =M73-L73 -> -39000 | T73: =IF(O73="","",M73*O73/100) -> 11413.4 | U73: =IF(I73="","",YEAR(B73)-I73) -> 51 | V73: =LOOKUP(M73,bin_lo,bin_lbl) -> $300-400K | W73: =TRIM(IF(M73>f_price_hi,"High price ","")&IF(AND(N73<>"",N73>f_dom_hi),"Long DOM ","")&IF(OR(Q73>f_psf_hi,Q73<f_psf_lo),"$/sqft ","")) | X73: neighborhood standardised
A74: 10151 | B74: 45814 | C74: Cedar Park | D74: Single Family | E74: 3 | F74: 2.5 | G74: 1790 | H74: 7470 | I74: 2020 | J74: 2 | K74: Fair | L74: 375000 | M74: 355000 | N74: 60 | O74: 3.2 | P74: =DATE(YEAR(B74),MONTH(B74),1) -> 45809 | Q74: =M74/G74 -> 198.32402 | R74: =M74/L74 -> 0.94666667 | S74: =M74-L74 -> -20000 | T74: =IF(O74="","",M74*O74/100) -> 11360 | U74: =IF(I74="","",YEAR(B74)-I74) -> 5 | V74: =LOOKUP(M74,bin_lo,bin_lbl) -> $300-400K | W74: =TRIM(IF(M74>f_price_hi,"High price ","")&IF(AND(N74<>"",N74>f_dom_hi),"Long DOM ","")&IF(OR(Q74>f_psf_hi,Q74<f_psf_lo),"$/sqft ","")) | X74: bathrooms imputed (group median)
A75: 10051 | B75: 45817 | C75: Oak Hill | D75: Townhouse | E75: 3 | F75: 2 | G75: 1750 | H75: 1720 | I75: 2006 | J75: 2 | K75: Excellent | L75: 479000 | M75: 492000 | N75: 36 | O75: 2.54 | P75: =DATE(YEAR(B75),MONTH(B75),1) -> 45809 | Q75: =M75/G75 -> 281.14286 | R75: =M75/L75 -> 1.0271399 | S75: =M75-L75 -> 13000 | T75: =IF(O75="","",M75*O75/100) -> 12496.8 | U75: =IF(I75="","",YEAR(B75)-I75) -> 19 | V75: =LOOKUP(M75,bin_lo,bin_lbl) -> $400-500K | W75: =TRIM(IF(M75>f_price_hi,"High price ","")&IF(AND(N75<>"",N75>f_dom_hi),"Long DOM ","")&IF(OR(Q75>f_psf_hi,Q75<f_psf_lo),"$/sqft ",""))
A76: 10002 | B76: 45818 | C76: Riverside | D76: Condo | E76: 1 | F76: 1 | G76: 760 | H76: 0 | I76: 2021 | J76: 1 | K76: Good | L76: 200000 | M76: 198000 | N76: 67 | O76: 3.18 | P76: =DATE(YEAR(B76),MONTH(B76),1) -> 45809 | Q76: =M76/G76 -> 260.52632 | R76: =M76/L76 -> 0.99 | S76: =M76-L76 -> -2000 | T76: =IF(O76="","",M76*O76/100) -> 6296.4 | U76: =IF(I76="","",YEAR(B76)-I76) -> 4 | V76: =LOOKUP(M76,bin_lo,bin_lbl) -> Under $200K | W76: =TRIM(IF(M76>f_price_hi,"High price ","")&IF(AND(N76<>"",N76>f_dom_hi),"Long DOM ","")&IF(OR(Q76>f_psf_hi,Q76<f_psf_lo),"$/sqft ",""))
A77: 10072 | B77: 45820 | C77: Riverside | D77: Single Family | E77: 3 | F77: 2.5 | G77: 1790 | H77: 7960 | I77: 2006 | J77: 2 | K77: Excellent | L77: 443000 | M77: 440000 | N77: 36 | O77: 2.96 | P77: =DATE(YEAR(B77),MONTH(B77),1) -> 45809 | Q77: =M77/G77 -> 245.81006 | R77: =M77/L77 -> 0.99322799 | S77: =M77-L77 -> -3000 | T77: =IF(O77="","",M77*O77/100) -> 13024 | U77: =IF(I77="","",YEAR(B77)-I77) -> 19 | V77: =LOOKUP(M77,bin_lo,bin_lbl) -> $400-500K | W77: =TRIM(IF(M77>f_price_hi,"High price ","")&IF(AND(N77<>"",N77>f_dom_hi),"Long DOM ","")&IF(OR(Q77>f_psf_hi,Q77<f_psf_lo),"$/sqft ","")) | X77: neighborhood standardised
A78: 10069 | B78: 45827 | C78: Oak Hill | D78: Single Family | E78: 4 | F78: 2.5 | G78: 1810 | H78: 7540 | I78: 2014 | J78: 2 | K78: Good | L78: 475000 | M78: 466000 | N78: 44 | O78: 2.8 | P78: =DATE(YEAR(B78),MONTH(B78),1) -> 45809 | Q78: =M78/G78 -> 257.45856 | R78: =M78/L78 -> 0.98105263 | S78: =M78-L78 -> -9000 | T78: =IF(O78="","",M78*O78/100) -> 13048 | U78: =IF(I78="","",YEAR(B78)-I78) -> 11 | V78: =LOOKUP(M78,bin_lo,bin_lbl) -> $400-500K | W78: =TRIM(IF(M78>f_price_hi,"High price ","")&IF(AND(N78<>"",N78>f_dom_hi),"Long DOM ","")&IF(OR(Q78>f_psf_hi,Q78<f_psf_lo),"$/sqft ",""))
A79: 10230 | B79: 45827 | C79: Oak Hill | D79: Single Family | E79: 3 | F79: 2 | G79: 1890 | H79: 7410 | I79: 1972 | J79: 1 | K79: Fair | L79: 531000 | M79: 510000 | N79: 91 | O79: 3.28 | P79: =DATE(YEAR(B79),MONTH(B79),1) -> 45809 | Q79: =M79/G79 -> 269.84127 | R79: =M79/L79 -> 0.96045198 | S79: =M79-L79 -> -21000 | T79: =IF(O79="","",M79*O79/100) -> 16728 | U79: =IF(I79="","",YEAR(B79)-I79) -> 53 | V79: =LOOKUP(M79,bin_lo,bin_lbl) -> $500-600K | W79: =TRIM(IF(M79>f_price_hi,"High price ","")&IF(AND(N79<>"",N79>f_dom_hi),"Long DOM ","")&IF(OR(Q79>f_psf_hi,Q79<f_psf_lo),"$/sqft ",""))
A80: 10223 | B80: 45829 | C80: Maple Heights | D80: Single Family | E80: 3 | F80: 2 | G80: 1650 | H80: 3880 | I80: 1957 | J80: 2 | K80: Fair | L80: 284000 | M80: 278000 | N80: 100 | O80: 3.02 | P80: =DATE(YEAR(B80),MONTH(B80),1) -> 45809 | Q80: =M80/G80 -> 168.48485 | R80: =M80/L80 -> 0.97887324 | S80: =M80-L80 -> -6000 | T80: =IF(O80="","",M80*O80/100) -> 8395.6 | U80: =IF(I80="","",YEAR(B80)-I80) -> 68 | V80: =LOOKUP(M80,bin_lo,bin_lbl) -> $200-300K | W80: =TRIM(IF(M80>f_price_hi,"High price ","")&IF(AND(N80<>"",N80>f_dom_hi),"Long DOM ","")&IF(OR(Q80>f_psf_hi,Q80<f_psf_lo),"$/sqft ",""))
A81: 10109 | B81: 45834 | C81: Oak Hill | D81: Single Family | E81: 4 | F81: 3.5 | G81: 2290 | H81: 8270 | I81: 2011 | J81: 2 | K81: Excellent | L81: 616000 | M81: 615000 | N81: 41 | O81: 2.48 | P81: =DATE(YEAR(B81),MONTH(B81),1) -> 45809 | Q81: =M81/G81 -> 268.55895 | R81: =M81/L81 -> 0.99837662 | S81: =M81-L81 -> -1000 | T81: =IF(O81="","",M81*O81/100) -> 15252 | U81: =IF(I81="","",YEAR(B81)-I81) -> 14 | V81: =LOOKUP(M81,bin_lo,bin_lbl) -> $600-800K | W81: =TRIM(IF(M81>f_price_hi,"High price ","")&IF(AND(N81<>"",N81>f_dom_hi),"Long DOM ","")&IF(OR(Q81>f_psf_hi,Q81<f_psf_lo),"$/sqft ",""))
A82: 10035 | B82: 45835 | C82: Riverside | D82: Single Family | E82: 5 | F82: 4 | G82: 2540 | H82: 10050 | I82: 1993 | J82: 2 | K82: Fair | L82: 515000 | M82: 510000 | N82: 62 | O82: 3.22 | P82: =DATE(YEAR(B82),MONTH(B82),1) -> 45809 | Q82: =M82/G82 -> 200.7874 | R82: =M82/L82 -> 0.99029126 | S82: =M82-L82 -> -5000 | T82: =IF(O82="","",M82*O82/100) -> 16422 | U82: =IF(I82="","",YEAR(B82)-I82) -> 32 | V82: =LOOKUP(M82,bin_lo,bin_lbl) -> $500-600K | W82: =TRIM(IF(M82>f_price_hi,"High price ","")&IF(AND(N82<>"",N82>f_dom_hi),"Long DOM ","")&IF(OR(Q82>f_psf_hi,Q82<f_psf_lo),"$/sqft ","")) | X82: property_type standardised; condition standardised
A83: 10011 | B83: 45837 | C83: Riverside | D83: Single Family | E83: 2 | F83: 2.5 | G83: 1330 | H83: 4520 | J83: 2 | K83: Good | L83: 312000 | M83: 285000 | N83: 42 | O83: 2.89 | P83: =DATE(YEAR(B83),MONTH(B83),1) -> 45809 | Q83: =M83/G83 -> 214.28571 | R83: =M83/L83 -> 0.91346154 | S83: =M83-L83 -> -27000 | T83: =IF(O83="","",M83*O83/100) -> 8236.5 | U83: =IF(I83="","",YEAR(B83)-I83) | V83: =LOOKUP(M83,bin_lo,bin_lbl) -> $200-300K | W83: =TRIM(IF(M83>f_price_hi,"High price ","")&IF(AND(N83<>"",N83>f_dom_hi),"Long DOM ","")&IF(OR(Q83>f_psf_hi,Q83<f_psf_lo),"$/sqft ","")) | X83: year_built left blank
A84: 10176 | B84: 45841 | C84: Oak Hill | D84: Townhouse | E84: 3 | F84: 2.5 | G84: 1920 | H84: 2530 | I84: 2013 | J84: 3 | K84: Good | L84: 530000 | M84: 509000 | N84: 24 | O84: 2.43 | P84: =DATE(YEAR(B84),MONTH(B84),1) -> 45839 | Q84: =M84/G84 -> 265.10417 | R84: =M84/L84 -> 0.96037736 | S84: =M84-L84 -> -21000 | T84: =IF(O84="","",M84*O84/100) -> 12368.7 | U84: =IF(I84="","",YEAR(B84)-I84) -> 12 | V84: =LOOKUP(M84,bin_lo,bin_lbl) -> $500-600K | W84: =TRIM(IF(M84>f_price_hi,"High price ","")&IF(AND(N84<>"",N84>f_dom_hi),"Long DOM ","")&IF(OR(Q84>f_psf_hi,Q84<f_psf_lo),"$/sqft ","")) | X84: condition standardised
A85: 10234 | B85: 45841 | C85: Maple Heights | D85: Single Family | E85: 3 | F85: 1.5 | G85: 1650 | H85: 5030 | I85: 2007 | J85: 2 | K85: Excellent | L85: 412000 | M85: 396000 | N85: 60 | O85: 2.9 | P85: =DATE(YEAR(B85),MONTH(B85),1) -> 45839 | Q85: =M85/G85 -> 240 | R85: =M85/L85 -> 0.96116505 | S85: =M85-L85 -> -16000 | T85: =IF(O85="","",M85*O85/100) -> 11484 | U85: =IF(I85="","",YEAR(B85)-I85) -> 18 | V85: =LOOKUP(M85,bin_lo,bin_lbl) -> $300-400K | W85: =TRIM(IF(M85>f_price_hi,"High price ","")&IF(AND(N85<>"",N85>f_dom_hi),"Long DOM ","")&IF(OR(Q85>f_psf_hi,Q85<f_psf_lo),"$/sqft ","")) | X85: condition standardised
A86: 10175 | B86: 45844 | C86: Oak Hill | D86: Single Family | E86: 3 | F86: 1.5 | G86: 1790 | H86: 7930 | I86: 1979 | J86: 2 | K86: Poor | L86: 397000 | M86: 386000 | N86: 59 | O86: 3.23 | P86: =DATE(YEAR(B86),MONTH(B86),1) -> 45839 | Q86: =M86/G86 -> 215.64246 | R86: =M86/L86 -> 0.97229219 | S86: =M86-L86 -> -11000 | T86: =IF(O86="","",M86*O86/100) -> 12467.8 | U86: =IF(I86="","",YEAR(B86)-I86) -> 46 | V86: =LOOKUP(M86,bin_lo,bin_lbl) -> $300-400K | W86: =TRIM(IF(M86>f_price_hi,"High price ","")&IF(AND(N86<>"",N86>f_dom_hi),"Long DOM ","")&IF(OR(Q86>f_psf_hi,Q86<f_psf_lo),"$/sqft ","")) | X86: neighborhood standardised; property_type standardised
A87: 10162 | B87: 45845 | C87: Cedar Park | D87: Townhouse | E87: 3 | F87: 2 | G87: 1750 | H87: 1580 | I87: 2018 | J87: 1 | K87: Fair | L87: 252000 | M87: 232000 | N87: 58 | O87: 3.05 | P87: =DATE(YEAR(B87),MONTH(B87),1) -> 45839 | Q87: =M87/G87 -> 132.57143 | R87: =M87/L87 -> 0.92063492 | S87: =M87-L87 -> -20000 | T87: =IF(O87="","",M87*O87/100) -> 7076 | U87: =IF(I87="","",YEAR(B87)-I87) -> 7 | V87: =LOOKUP(M87,bin_lo,bin_lbl) -> $200-300K | W87: =TRIM(IF(M87>f_price_hi,"High price ","")&IF(AND(N87<>"",N87>f_dom_hi),"Long DOM ","")&IF(OR(Q87>f_psf_hi,Q87<f_psf_lo),"$/sqft ",""))
A88: 10047 | B88: 45848 | C88: Riverside | D88: Condo | E88: 1 | F88: 2 | G88: 520 | H88: 0 | I88: 1992 | J88: 0 | K88: Good | L88: 123000 | M88: 119000 | N88: 51 | P88: =DATE(YEAR(B88),MONTH(B88),1) -> 45839 | Q88: =M88/G88 -> 228.84615 | R88: =M88/L88 -> 0.96747967 | S88: =M88-L88 -> -4000 | T88: =IF(O88="","",M88*O88/100) | U88: =IF(I88="","",YEAR(B88)-I88) -> 33 | V88: =LOOKUP(M88,bin_lo,bin_lbl) -> Under $200K | W88: =TRIM(IF(M88>f_price_hi,"High price ","")&IF(AND(N88<>"",N88>f_dom_hi),"Long DOM ","")&IF(OR(Q88>f_psf_hi,Q88<f_psf_lo),"$/sqft ","")) | X88: commission left blank
A89: 10111 | B89: 45849 | C89: Riverside | D89: Condo | E89: 2 | F89: 2 | G89: 1310 | H89: 0 | J89: 0 | K89: Good | L89: 273000 | M89: 263000 | N89: 36 | O89: 2.92 | P89: =DATE(YEAR(B89),MONTH(B89),1) -> 45839 | Q89: =M89/G89 -> 200.76336 | R89: =M89/L89 -> 0.96336996 | S89: =M89-L89 -> -10000 | T89: =IF(O89="","",M89*O89/100) -> 7679.6 | U89: =IF(I89="","",YEAR(B89)-I89) | V89: =LOOKUP(M89,bin_lo,bin_lbl) -> $200-300K | W89: =TRIM(IF(M89>f_price_hi,"High price ","")&IF(AND(N89<>"",N89>f_dom_hi),"Long DOM ","")&IF(OR(Q89>f_psf_hi,Q89<f_psf_lo),"$/sqft ","")) | X89: bathrooms imputed (group median); year_built left blank
A90: 10168 | B90: 45852 | C90: Downtown | D90: Townhouse | E90: 3 | F90: 3.5 | G90: 2010 | H90: 2420 | I90: 1984 | J90: 1 | K90: Unknown | L90: 528000 | M90: 501000 | N90: 67 | O90: 2.48 | P90: =DATE(YEAR(B90),MONTH(B90),1) -> 45839 | Q90: =M90/G90 -> 249.25373 | R90: =M90/L90 -> 0.94886364 | S90: =M90-L90 -> -27000 | T90: =IF(O90="","",M90*O90/100) -> 12424.8 | U90: =IF(I90="","",YEAR(B90)-I90) -> 41 | V90: =LOOKUP(M90,bin_lo,bin_lbl) -> $500-600K | W90: =TRIM(IF(M90>f_price_hi,"High price ","")&IF(AND(N90<>"",N90>f_dom_hi),"Long DOM ","")&IF(OR(Q90>f_psf_hi,Q90<f_psf_lo),"$/sqft ","")) | X90: condition standardised
A91: 10208 | B91: 45854 | C91: Maple Heights | D91: Single Family | E91: 3 | F91: 3 | G91: 1740 | H91: 7320 | I91: 1970 | J91: 0 | K91: Excellent | L91: 381000 | M91: 346000 | N91: 67 | O91: 3.22 | P91: =DATE(YEAR(B91),MONTH(B91),1) -> 45839 | Q91: =M91/G91 -> 198.85057 | R91: =M91/L91 -> 0.90813648 | S91: =M91-L91 -> -35000 | T91: =IF(O91="","",M91*O91/100) -> 11141.2 | U91: =IF(I91="","",YEAR(B91)-I91) -> 55 | V91: =LOOKUP(M91,bin_lo,bin_lbl) -> $300-400K | W91: =TRIM(IF(M91>f_price_hi,"High price ","")&IF(AND(N91<>"",N91>f_dom_hi),"Long DOM ","")&IF(OR(Q91>f_psf_hi,Q91<f_psf_lo),"$/sqft ","")) | X91: neighborhood standardised; property_type standardised
A92: 10006 | B92: 45856 | C92: Cedar Park | D92: Townhouse | E92: 3 | F92: 2.5 | G92: 1750 | H92: 2320 | I92: 1989 | J92: 0 | K92: Excellent | L92: 272000 | M92: 259000 | O92: 2.94 | P92: =DATE(YEAR(B92),MONTH(B92),1) -> 45839 | Q92: =M92/G92 -> 148 | R92: =M92/L92 -> 0.95220588 | S92: =M92-L92 -> -13000 | T92: =IF(O92="","",M92*O92/100) -> 7614.6 | U92: =IF(I92="","",YEAR(B92)-I92) -> 36 | V92: =LOOKUP(M92,bin_lo,bin_lbl) -> $200-300K | W92: =TRIM(IF(M92>f_price_hi,"High price ","")&IF(AND(N92<>"",N92>f_dom_hi),"Long DOM ","")&IF(OR(Q92>f_psf_hi,Q92<f_psf_lo),"$/sqft ","")) | X92: days_on_market left blank
A93: 10013 | B93: 45858 | C93: Maple Heights | D93: Single Family | E93: 3 | F93: 2 | G93: 1740 | H93: 3960 | I93: 1968 | J93: 2 | K93: Fair | L93: 303000 | M93: 306000 | N93: 41 | O93: 3.05 | P93: =DATE(YEAR(B93),MONTH(B93),1) -> 45839 | Q93: =M93/G93 -> 175.86207 | R93: =M93/L93 -> 1.009901 | S93: =M93-L93 -> 3000 | T93: =IF(O93="","",M93*O93/100) -> 9333 | U93: =IF(I93="","",YEAR(B93)-I93) -> 57 | V93: =LOOKUP(M93,bin_lo,bin_lbl) -> $300-400K | W93: =TRIM(IF(M93>f_price_hi,"High price ","")&IF(AND(N93<>"",N93>f_dom_hi),"Long DOM ","")&IF(OR(Q93>f_psf_hi,Q93<f_psf_lo),"$/sqft ","")) | X93: property_type standardised
A94: 10189 | B94: 45862 | C94: Unknown | D94: Townhouse | E94: 2 | F94: 1.5 | G94: 1280 | H94: 2060 | I94: 2024 | J94: 2 | K94: Good | L94: 365000 | M94: 365000 | N94: 35 | O94: 3.07 | P94: =DATE(YEAR(B94),MONTH(B94),1) -> 45839 | Q94: =M94/G94 -> 285.15625 | R94: =M94/L94 -> 1 | S94: =M94-L94 -> 0 | T94: =IF(O94="","",M94*O94/100) -> 11205.5 | U94: =IF(I94="","",YEAR(B94)-I94) -> 1 | V94: =LOOKUP(M94,bin_lo,bin_lbl) -> $300-400K | W94: =TRIM(IF(M94>f_price_hi,"High price ","")&IF(AND(N94<>"",N94>f_dom_hi),"Long DOM ","")&IF(OR(Q94>f_psf_hi,Q94<f_psf_lo),"$/sqft ","")) | X94: neighborhood missing -> Unknown
A95: 10242 | B95: 45863 | C95: Downtown | D95: Condo | E95: 2 | F95: 2 | G95: 1230 | H95: 0 | I95: 1965 | J95: 1 | K95: Fair | L95: 309000 | M95: 286000 | N95: 82 | O95: 2.41 | P95: =DATE(YEAR(B95),MONTH(B95),1) -> 45839 | Q95: =M95/G95 -> 232.52033 | R95: =M95/L95 -> 0.92556634 | S95: =M95-L95 -> -23000 | T95: =IF(O95="","",M95*O95/100) -> 6892.6 | U95: =IF(I95="","",YEAR(B95)-I95) -> 60 | V95: =LOOKUP(M95,bin_lo,bin_lbl) -> $200-300K | W95: =TRIM(IF(M95>f_price_hi,"High price ","")&IF(AND(N95<>"",N95>f_dom_hi),"Long DOM ","")&IF(OR(Q95>f_psf_hi,Q95<f_psf_lo),"$/sqft ","")) | X95: neighborhood standardised
A96: 10248 | B96: 45866 | C96: Riverside | D96: Townhouse | E96: 2 | F96: 1 | G96: 1350 | H96: 2720 | I96: 2015 | J96: 2 | K96: Good | L96: 311000 | M96: 295000 | N96: 87 | O96: 2.52 | P96: =DATE(YEAR(B96),MONTH(B96),1) -> 45839 | Q96: =M96/G96 -> 218.51852 | R96: =M96/L96 -> 0.94855305 | S96: =M96-L96 -> -16000 | T96: =IF(O96="","",M96*O96/100) -> 7434 | U96: =IF(I96="","",YEAR(B96)-I96) -> 10 | V96: =LOOKUP(M96,bin_lo,bin_lbl) -> $200-300K | W96: =TRIM(IF(M96>f_price_hi,"High price ","")&IF(AND(N96<>"",N96>f_dom_hi),"Long DOM ","")&IF(OR(Q96>f_psf_hi,Q96<f_psf_lo),"$/sqft ","")) | X96: property_type standardised
A97: 10146 | B97: 45868 | C97: Riverside | D97: Single Family | E97: 3 | F97: 2 | G97: 1970 | H97: 7310 | I97: 2024 | J97: 1 | K97: Fair | L97: 437000 | M97: 429000 | N97: 74 | P97: =DATE(YEAR(B97),MONTH(B97),1) -> 45839 | Q97: =M97/G97 -> 217.7665 | R97: =M97/L97 -> 0.98169336 | S97: =M97-L97 -> -8000 | T97: =IF(O97="","",M97*O97/100) | U97: =IF(I97="","",YEAR(B97)-I97) -> 1 | V97: =LOOKUP(M97,bin_lo,bin_lbl) -> $400-500K | W97: =TRIM(IF(M97>f_price_hi,"High price ","")&IF(AND(N97<>"",N97>f_dom_hi),"Long DOM ","")&IF(OR(Q97>f_psf_hi,Q97<f_psf_lo),"$/sqft ","")) | X97: commission left blank
A98: 10076 | B98: 45869 | C98: Riverside | D98: Townhouse | E98: 3 | F98: 3 | G98: 1580 | H98: 2130 | I98: 1940 | J98: 2 | K98: Unknown | L98: 333000 | M98: 317000 | N98: 42 | O98: 2.78 | P98: =DATE(YEAR(B98),MONTH(B98),1) -> 45839 | Q98: =M98/G98 -> 200.63291 | R98: =M98/L98 -> 0.95195195 | S98: =M98-L98 -> -16000 | T98: =IF(O98="","",M98*O98/100) -> 8812.6 | U98: =IF(I98="","",YEAR(B98)-I98) -> 85 | V98: =LOOKUP(M98,bin_lo,bin_lbl) -> $300-400K | W98: =TRIM(IF(M98>f_price_hi,"High price ","")&IF(AND(N98<>"",N98>f_dom_hi),"Long DOM ","")&IF(OR(Q98>f_psf_hi,Q98<f_psf_lo),"$/sqft ","")) | X98: property_type standardised; condition missing -> Unknown; garage imputed (group median)
A99: 10020 | B99: 45870 | C99: Maple Heights | D99: Single Family | E99: 3 | F99: 2.5 | G99: 2030 | H99: 6600 | I99: 2019 | J99: 2 | K99: Good | L99: 464000 | M99: 447000 | N99: 98 | O99: 2.71 | P99: =DATE(YEAR(B99),MONTH(B99),1) -> 45870 | Q99: =M99/G99 -> 220.19704 | R99: =M99/L99 -> 0.96336207 | S99: =M99-L99 -> -17000 | T99: =IF(O99="","",M99*O99/100) -> 12113.7 | U99: =IF(I99="","",YEAR(B99)-I99) -> 6 | V99: =LOOKUP(M99,bin_lo,bin_lbl) -> $400-500K | W99: =TRIM(IF(M99>f_price_hi,"High price ","")&IF(AND(N99<>"",N99>f_dom_hi),"Long DOM ","")&IF(OR(Q99>f_psf_hi,Q99<f_psf_lo),"$/sqft ","")) | X99: property_type standardised
A100: 10171 | B100: 45870 | C100: Riverside | D100: Townhouse | E100: 3 | F100: 3 | G100: 1530 | H100: 2360 | I100: 1992 | J100: 1 | K100: Excellent | L100: 348000 | M100: 340000 | N100: 31 | O100: 2.67 | P100: =DATE(YEAR(B100),MONTH(B100),1) -> 45870 | Q100: =M100/G100 -> 222.22222 | R100: =M100/L100 -> 0.97701149 | S100: =M100-L100 -> -8000 | T100: =IF(O100="","",M100*O100/100) -> 9078 | U100: =IF(I100="","",YEAR(B100)-I100) -> 33 | V100: =LOOKUP(M100,bin_lo,bin_lbl) -> $300-400K | W100: =TRIM(IF(M100>f_price_hi,"High price ","")&IF(AND(N100<>"",N100>f_dom_hi),"Long DOM ","")&IF(OR(Q100>f_psf_hi,Q100<f_psf_lo),"$/sqft ","")) | X100: neighborhood standardised
...

Sheet Data_Raw
A1: sale_id | B1: sale_date | C1: neighborhood | D1: property_type | E1: bedrooms | F1: bathrooms | G1: sqft | H1: lot_size_sqft | I1: year_built | J1: garage_spaces | K1: condition | L1: list_price | M1: sale_price | N1: days_on_market | O1: agent_commission_pct
A2: 10144 | B2: 2025-01-01 | C2: Maple Heights | D2: Townhouse | E2: 3 | F2: 3 | G2: 1500 | H2: 1400 | I2: 2004 | J2: 3 | K2: Fair | L2: 297000 | M2: 290000 | N2: 82 | O2: 2.57
A3: 10067 | B3: 2025-01-02 | C3: Maple Heights | D3: Single Family | E3: 4 | F3: 2.5 | G3: 2370 | H3: 7660 | I3: 1996 | J3: 3 | K3: Fair | L3: 446000 | M3: 451000 | N3: 53 | O3: 2.71
A4: 10028 | B4: 2025-01-04 | C4: Oak Hill | D4: Single Family | E4: 3 | F4: 2.5 | G4: 1510 | H4: 4520 | I4: 2006 | J4: 2 | K4: Good | L4: 404000 | M4: 384000 | N4: 40 | O4: 2.79
A5: 10082 | B5: 2025-01-04 | C5: Riverside | D5: Single family | E5: 3 | F5: 2.5 | G5: 1880 | H5: 5670 | I5: 1978 | J5: 1 | K5: good | L5: 434000 | M5: 442000 | N5: 45
A6: 10043 | B6: 2025-01-07 | C6: downtown | D6: Condo | E6: 1 | F6: 1 | G6: 1110 | H6: 0 | I6: 1962 | J6: 0 | K6: Excellent | L6: 364000 | M6: 355000 | N6: 81 | O6: 3.02
A7: 10095 | B7: 2025-01-12 | C7: Riverside | D7: Townhouse | E7: 3 | F7: 2.5 | G7: 1510 | H7: 1240 | I7: 2022 | J7: 2 | K7: Good | L7: 373000 | M7: 358000 | N7: 61 | O7: 2.51
A8: 10041 | B8: 2025-01-15 | C8: Riverside | D8: Condominium | E8: 1 | F8: 1 | G8: 780 | H8: 0 | I8: 1982 | J8: 1 | K8: good | L8: 178000 | M8: 180000 | N8: 25
A9: 10178 | B9: 2025-01-15 | C9: Cedar Park | D9: Condo | E9: 3 | F9: 2.5 | G9: 1910 | H9: 0 | I9: 1959 | J9: 1 | K9: Good | L9: 242000 | M9: 239000 | N9: 35 | O9: 3.04
A10: 10142 | B10: 2025-01-16 | C10: Maple Heights | D10: Single Family | E10: 4 | F10: 3.5 | G10: 2360 | H10: 5700 | I10: 2008 | J10: 2 | K10: GOOD | L10: 489000 | M10: 442000 | N10: 60
A11: 10027 | B11: 2025-01-17 | C11: Riverside | D11: Single Family | E11: 3 | F11: 2 | G11: 1890 | H11: 6400 | I11: 2002 | J11: 1 | K11: poor | L11: 406000 | M11: 411000 | N11: 80 | O11: 2.95
A12: 10193 | B12: 2025-01-19 | C12: Oak Hill | D12: Townhouse | E12: 4 | F12: 3.5 | G12: 2260 | H12: 1850 | I12: 1941 | J12: 2 | K12: Poor | L12: 395000 | M12: 389000 | N12: 76 | O12: 2.5
A13: 10014 | B13: 2025-01-19 | C13: Cedar Park | D13: Single Family | E13: 5 | F13: 5 | G13: 2220 | H13: 8020 | J13: 2 | K13: Good | L13: 435000 | M13: 425000 | N13: 50 | O13: 2.7
A14: 10149 | B14: 2025-01-19 | C14: Riverside | D14: Single Family | E14: 4 | F14: 3.5 | H14: 8600 | I14: 2009 | L14: 453000 | M14: 450000 | N14: 65 | O14: 2.75
A15: 10083 | B15: 2025-01-24 | C15: Downtown | D15: Condo | E15: 2 | F15: 2 | G15: 1350 | H15: 0 | I15: 1961 | J15: 0 | K15: Good | L15: 371000 | M15: 359000 | N15: 43 | O15: 2.79
A16: 10105 | B16: 2025-01-25 | C16: Downtown | D16: Single Family | E16: 4 | F16: 3.5 | G16: 2010 | H16: 5170 | I16: 1980 | J16: 1 | K16: Fair | L16: 549000 | M16: 542000 | N16: 45 | O16: 2.97
A17: 10019 | B17: 2025-01-27 | C17: Cedar Park | D17: Single Family | E17: 3 | F17: 2.5 | G17: 1670 | H17: 4630 | I17: 2001 | J17: 2 | K17: GOOD | L17: 302000 | M17: 298000 | N17: 69 | O17: 2.55
A18: 10057 | B18: 2025-01-28 | C18: Riverside | D18: Single Family | E18: 4 | F18: 2.5 | G18: 2050 | H18: 5760 | I18: 2005 | J18: 2 | K18: GOOD | L18: 462000 | M18: 441000 | N18: 39 | O18: 3.02
A19: 10229 | B19: 2025-02-01 | C19: Maple Heights | D19: Townhouse | E19: 4 | F19: 3 | G19: 2150 | H19: 1740 | J19: 1 | K19: Good | L19: 350000 | M19: 342000 | N19: 40
A20: 10110 | B20: 2025-02-03 | C20: Cedar Park | D20: Single Family | E20: 3 | F20: 2.5 | G20: 1470 | H20: 3280 | I20: 1972 | J20: 1 | K20: Good | L20: 273000 | M20: 264000 | N20: 66 | O20: 3.05
A21: 10131 | B21: 2025-02-04 | C21: Oak Hill | D21: Single Family | E21: 3 | F21: 2 | G21: 1500 | H21: 5130 | I21: 1986 | J21: 1 | K21: Fair | L21: 393000 | M21: 403000 | N21: 60 | O21: 2.45
A22: 10124 | B22: 2025-02-07 | C22: Riverside | D22: Single Family | E22: 4 | F22: 3.5 | G22: 2050 | H22: 4930 | I22: 1974 | J22: 1 | K22: Good | L22: 487000 | M22: 452000 | N22: 43 | O22: 3.02
A23: 10081 | B23: 2025-02-08 | C23: Maple Heights | D23: Townhouse | E23: 2 | F23: 1 | H23: 2300 | I23: 1988 | J23: 1 | K23: Exc. | L23: 250000 | M23: 239000 | N23: 40 | O23: 3.08
A24: 10100 | B24: 2025-02-08 | C24: Cedar Park | D24: Single Family | E24: 3 | F24: 3 | G24: 1720 | H24: 6180 | I24: 1941 | J24: 1 | K24: Excellent | L24: 337000 | M24: 332000 | N24: 80 | O24: 2.68
A25: 10061 | B25: 2025-02-14 | C25: Maple Heights | D25: Single Family | E25: 3 | F25: 2.5 | G25: 1520 | H25: 6600 | I25: 1984 | J25: 0 | K25: Excellent | L25: 350000 | M25: 334000 | N25: 61 | O25: 3.03
A26: 10205 | B26: 2025-02-22 | C26: Oak Hill | D26: Single Family | E26: 3 | F26: 3 | G26: 1940 | H26: 4730 | I26: 2002 | J26: 1 | K26: Good | L26: 479000 | M26: 451000 | N26: 62 | O26: 2.71
A27: 10143 | B27: 2025-02-23 | C27: Cedar Park | D27: Single Family | E27: 3 | F27: 2.5 | G27: 1950 | H27: 8750 | I27: 2013 | J27: 2 | K27: Good | L27: 383000 | M27: 377000 | N27: 54 | O27: 3.11
A28: 10052 | B28: 2025-02-25 | C28: Oak Hill | D28: Single Family | E28: 4 | F28: 3 | G28: 2260 | H28: 10060 | I28: 1940 | J28: 0 | K28: Good | L28: 531000 | M28: 512000 | N28: 20 | O28: 3.07
A29: 10120 | B29: 2025-02-27 | C29: Maple Heights. | D29: Condo | E29: 1 | F29: 1 | G29: 940 | H29: 0 | I29: 1997 | J29: 0 | K29: Good | L29: 185000 | M29: 177000 | N29: 41 | O29: 3.07
A30: 10135 | B30: 2025-02-28 | C30: Maple Heights | D30: Single Family | E30: 5 | F30: 3 | G30: 2660 | H30: 11020 | I30: 1964 | J30: 1 | K30: Good | L30: 501000 | M30: 478000 | O30: 3.05
A31: 10202 | B31: 2025-03-02 | C31: Cedar Park | D31: Condo | E31: 1 | F31: 1.5 | G31: 690 | I31: 2018 | J31: 0 | K31: Good | L31: 131000 | M31: 131000 | N31: 37 | O31: 2.74
A32: 10106 | B32: 2025-03-05 | C32: Downtown | D32: single-family | E32: 2 | F32: 1.5 | G32: 1200 | H32: 4070 | I32: 2018 | J32: 2 | K32: Good | L32: 407000 | M32: 419000 | N32: 38 | O32: 2.52
A33: 10003 | B33: 2025-03-07 | C33: Cedar Park | D33: Single Family | E33: 3 | F33: 3 | G33: 1590 | H33: 4020 | I33: 2021 | J33: 1 | K33: Excellent | L33: 350000 | M33: 352000 | N33: 41 | O33: 2.54
A34: 10210 | B34: 2025-03-08 | C34: Maple Heights | D34: Townhouse | E34: 3 | F34: 2 | G34: 1620 | H34: 1550 | I34: 2016 | J34: 1 | K34: Excellent | L34: 343000 | M34: 333000 | N34: 37 | O34: 3.04
A35: 10104 | B35: 2025-03-08 | C35: Cedar Park | D35: Single Family | E35: 3 | F35: 2.5 | G35: 1550 | H35: 4630 | J35: 2 | K35: Fair | L35: 262000 | M35: 247000 | N35: 100 | O35: 3.02
A36: 10186 | B36: 2025-03-09 | C36: Maple Heights | D36: Single Family | E36: 5 | F36: 3.5 | H36: 6430 | I36: 2022 | J36: 2 | K36: Poor | L36: 476000 | M36: 443000 | N36: 87 | O36: 3.03
A37: 10132 | B37: 2025-03-18 | C37: Cedar Park | D37: Condo | E37: 2 | F37: 2 | G37: 1070 | H37: 0 | I37: 1989 | J37: 0 | K37: excellent | L37: 196000 | M37: 190000 | N37: 45 | O37: 2.97
A38: 10015 | B38: 2025-03-18 | C38: Riverside | D38: Condo | E38: 3 | F38: 3 | H38: 0 | I38: 1966 | J38: 1 | K38: Good | L38: 358000 | M38: 334000 | N38: 43 | O38: 3
A39: 10062 | B39: 2025-03-19 | C39: Oak Hill | D39: Single Family | E39: 6 | F39: 5.5 | G39: 6400 | H39: 41000 | I39: 2019 | J39: 4 | K39: Excellent | L39: 3450000 | M39: 3310000 | N39: 61 | O39: 2.49
A40: 10237 | B40: 2025-03-21 | C40: Riverside | D40: Single Family | E40: 5 | F40: 3.5 | G40: 2520 | I40: 2015 | J40: 2 | K40: Fair | L40: 476000 | M40: 463000 | N40: 54 | O40: 3.04
A41: 10031 | B41: 2025-03-21 | C41: Downtown | D41: Single Family | E41: 3 | F41: 2.5 | G41: 1640 | H41: 6560 | I41: 1998 | J41: 2 | K41: Excellent | L41: 535000 | M41: 489000 | N41: 41 | O41: 2.99
A42: 10099 | B42: 2025-03-22 | C42: OakHill | D42: Single Family | E42: 3 | F42: 2.5 | G42: 1880 | H42: 8190 | I42: 2010 | J42: 2 | L42: 539000 | M42: 513000 | N42: 93 | O42: 3.25
A43: 10235 | B43: 2025-03-24 | C43: Cedar Park | D43: Single Family | E43: 4 | F43: 3 | G43: 1960 | H43: 6730 | I43: 1998 | J43: 2 | K43: Good | L43: 335000 | M43: 320000 | N43: 64 | O43: 3.04
A44: 10116 | B44: 2025-03-26 | C44: Cedar Park | D44: Single Family | E44: 4 | F44: 3.5 | G44: 1960 | H44: 5550 | I44: 2017 | J44: 2 | K44: Good | L44: 408000 | M44: 392000 | N44: 49 | O44: 3.18
A45: 10156 | B45: 2025-03-27 | C45: Maple Heights | D45: CONDO | E45: 2 | F45: 2 | G45: 1400 | H45: 0 | I45: 2015 | J45: 1 | K45: Fair | L45: 270000 | M45: 264000 | O45: 2.95
A46: 10113 | B46: 2025-03-28 | C46: Riverside | D46: Single Family | E46: 4 | F46: 4 | G46: 2230 | H46: 5110 | I46: 2016 | J46: 2 | K46: fair | L46: 479000 | M46: 487000 | N46: 44 | O46: 3.33
A47: 10218 | B47: 2025-03-29 | C47: Oak Hill | D47: Condo | E47: 1 | F47: 1 | G47: 940 | H47: 0 | I47: 1980 | J47: 0 | K47: excellent | L47: 253000 | M47: 244000 | N47: 26 | O47: 3.32
A48: 10039 | B48: 2025-03-30 | C48: Riverside | D48: Single Family | E48: 3 | F48: 2.5 | G48: 1860 | H48: 8070 | I48: 1970 | J48: 1 | K48: Fair | L48: 379000 | M48: 370000 | N48: 50 | O48: 3.1
A49: 10018 | B49: 2025-03-30 | C49: Oak Hill | D49: single-family | E49: 5 | F49: 3.5 | G49: 2350 | H49: 5240 | I49: 1981 | J49: 1 | L49: 555000 | M49: 548000 | N49: 69 | O49: 3.01
A50: 10060 | B50: 2025-04-04 | C50: Oak Hill | D50: Single Family | E50: 5 | F50: 5.5 | G50: 2270 | H50: 7210 | I50: 2000 | J50: 2 | K50: Excellent | L50: 674000 | M50: 697000 | N50: 32 | O50: 2.75
A51: 10065 | B51: 2025-04-06 | C51: Maple Heights | D51: Single family | E51: 2 | F51: 2.5 | G51: 1240 | H51: 4170 | I51: 2024 | J51: 2 | K51: fair | L51: 333000 | M51: 315000 | N51: 56
A52: 10199 | B52: 2025-04-06 | C52: Oak Hill | D52: Single Family | E52: 4 | F52: 3 | G52: 2300 | H52: 6040 | I52: 2013 | K52: Good | L52: 643000 | M52: 636000 | N52: 59 | O52: 2.72
A53: 10194 | B53: 2025-04-12 | C53: Cedar Park | D53: Single Family | E53: 2 | F53: 1.5 | G53: 1240 | H53: 3470 | I53: 1983 | J53: 1 | K53: Poor | L53: 204000 | M53: 201000 | N53: 69 | O53: 2.74
A54: 10182 | B54: 2025-04-13 | C54: Cedar Park | D54: Townhouse | E54: 2 | F54: 1.5 | G54: 1400 | H54: 2140 | I54: 1969 | J54: 1 | L54: 216000 | M54: 214000 | N54: 45 | O54: 2.71
A55: 10088 | B55: 2025-04-15 | C55: Riverside | D55: Townhouse | E55: 3 | F55: 2.5 | G55: 1600 | H55: 2360 | I55: 2003 | K55: Excellent | L55: 380000 | M55: 382000 | N55: 48 | O55: 3.18
A56: 10214 | B56: 2025-04-16 | C56: Downtown | D56: Single Family | E56: 3 | F56: 3 | G56: 1820 | H56: 7970 | I56: 1937 | J56: 1 | K56: excellent | L56: 609000 | M56: 599000 | N56: 24 | O56: 2.55
A57: 10093 | B57: 2025-04-16 | C57: Riverside | D57: Townhouse | E57: 2 | F57: 1.5 | G57: 1210 | H57: 2540 | I57: 1985 | J57: 1 | K57: Excellent | L57: 285000 | M57: 280000 | N57: 56 | O57: 3.02
A58: 10094 | B58: 2025-04-17 | C58: Riverside | D58: Single family | E58: 4 | F58: 3 | G58: 2110 | H58: 5240 | I58: 2021 | J58: 2 | K58: Excellent | L58: 585000 | M58: 590000 | N58: 61 | O58: 2.57
A59: 10008 | B59: 2025-04-24 | C59: Downtown | D59: Single Family | E59: 4 | F59: 3 | G59: 1940 | H59: 4890 | I59: 1955 | J59: 0 | K59: Excellent | L59: 682000 | M59: 654000 | N59: 66 | O59: 2.96
A60: 10098 | B60: 2025-04-26 | C60: OakHill | D60: Single Family | E60: 3 | F60: 2.5 | G60: 1870 | H60: 7580 | I60: 1989 | J60: 0 | K60: Good | L60: 516000 | M60: 496000 | N60: 51 | O60: 3
A61: 10216 | B61: 2025-04-26 | C61: Downtown | D61: Condo | E61: 2 | F61: 1 | G61: 1040 | I61: 1993 | J61: 0 | K61: Good | L61: 334000 | M61: 319000 | N61: 62 | O61: 2.71
A62: 10236 | B62: 2025-04-29 | C62: Downtown | D62: Single Family | E62: 2 | F62: 1 | G62: 1380 | H62: 3980 | I62: 1951 | J62: 1 | K62: Fair | L62: 365000 | M62: 373000 | N62: 62 | O62: 3.21
A63: 10211 | B63: 2025-05-03 | C63: Downtown | D63: Single Family | E63: 4 | F63: 2.5 | G63: 2150 | H63: 5160 | I63: 1968 | J63: 2 | K63: Excellent | L63: 620000 | M63: 596000 | N63: 61 | O63: 3.05
A64: 10056 | B64: 2025-05-03 | C64: Downtown | D64: Condo | E64: 1 | F64: 1 | G64: 920 | H64: 0 | I64: 2001 | J64: 0 | K64: Good | L64: 313000 | M64: 294000 | N64: 62 | O64: 3.1
A65: 10128 | B65: 2025-05-05 | C65: Oak Hill | D65: single-family | E65: 4 | F65: 3 | G65: 2330 | H65: 10440 | I65: 2018 | J65: 1 | K65: Good | L65: 615000 | M65: 608000 | N65: 38 | O65: 3.18
A66: 10134 | B66: 2025-05-06 | C66: Riverside | D66: Single Family | E66: 5 | G66: 2480 | H66: 9820 | I66: 2014 | J66: 2 | K66: Excellent | L66: 591000 | M66: 596000 | N66: 48 | O66: 2.95
A67: 10225 | B67: 2025-05-10 | C67: Riverside | D67: Single Family | E67: 4 | F67: 2.5 | G67: 2060 | H67: 7630 | I67: 2018 | J67: 2 | L67: 430000 | M67: 405000 | N67: 40 | O67: 2.93
A68: 10177 | B68: 2025-05-17 | C68: Riverside | D68: Single Family | E68: 3 | F68: 2 | G68: 1440 | H68: 6370 | I68: 2016 | J68: 2 | K68: Fair | L68: 351000 | M68: 336000 | N68: 78 | O68: 3.02
A69: 10166 | B69: 2025-05-23 | C69: Riverside | D69: single fam | E69: 4 | F69: 2.5 | G69: 2360 | H69: 7460 | I69: 2000 | K69: good | L69: 511000 | M69: 514000 | N69: 51 | O69: 3.24
A70: 10073 | B70: 2025-05-26 | C70: Cedar Park | D70: Single Family | E70: 2 | F70: 1 | G70: 1480 | H70: 3890 | I70: 2016 | J70: 2 | K70: Fair | L70: 244000 | M70: 238000 | N70: 83 | O70: 2.54
A71: 10224 | B71: 2025-05-30 | C71: Cedar Park | D71: Single Family | E71: 3 | F71: 3 | G71: 1950 | H71: 4460 | I71: 1983 | J71: 2 | K71: Good | L71: 350000 | M71: 355000 | N71: 96 | O71: 2.69
A72: 10172 | B72: 2025-05-31 | C72: Maple Heights | D72: Single Family | E72: 3 | F72: 3 | G72: 1600 | H72: 5040 | I72: 1990 | J72: 0 | K72: Good | L72: 328000 | M72: 317000 | N72: 68 | O72: 2.99
A73: 10180 | B73: 2025-06-02 | C73: DOWNTOWN | D73: Condo | E73: 2 | F73: 2 | G73: 1280 | H73: 0 | I73: 1974 | J73: 1 | K73: Fair | L73: 422000 | M73: 383000 | N73: 73 | O73: 2.98
A74: 10151 | B74: 2025-06-06 | C74: Cedar Park | D74: Single Family | E74: 3 | G74: 1790 | H74: 7470 | I74: 2020 | J74: 2 | K74: Fair | L74: 375000 | M74: 355000 | N74: 60 | O74: 3.2
A75: 10051 | B75: 2025-06-09 | C75: Oak Hill | D75: Townhouse | E75: 3 | F75: 2 | G75: 1750 | H75: 1720 | I75: 2006 | J75: 2 | K75: Excellent | L75: 479000 | M75: 492000 | N75: 36 | O75: 2.54
A76: 10002 | B76: 2025-06-10 | C76: Riverside | D76: Condo | E76: 1 | F76: 1 | G76: 760 | H76: 0 | I76: 2021 | J76: 1 | K76: Good | L76: 200000 | M76: 198000 | N76: 67 | O76: 3.18
A77: 10072 | B77: 2025-06-12 | C77: Riverside | D77: Single Family | E77: 3 | F77: 2.5 | G77: 1790 | H77: 7960 | I77: 2006 | J77: 2 | K77: Excellent | L77: 443000 | M77: 440000 | N77: 36 | O77: 2.96
A78: 10230 | B78: 2025-06-19 | C78: Oak Hill | D78: Single Family | E78: 3 | F78: 2 | G78: 1890 | H78: 7410 | I78: 1972 | J78: 1 | K78: Fair | L78: 531000 | M78: 510000 | N78: 91 | O78: 3.28
A79: 10069 | B79: 2025-06-19 | C79: Oak Hill | D79: Single Family | E79: 4 | F79: 2.5 | G79: 1810 | H79: 7540 | I79: 2014 | J79: 2 | K79: Good | L79: 475000 | M79: 466000 | N79: 44 | O79: 2.8
A80: 10223 | B80: 2025-06-21 | C80: Maple Heights | D80: Single Family | E80: 3 | F80: 2 | G80: 1650 | H80: 3880 | I80: 1957 | J80: 2 | K80: Fair | L80: 284000 | M80: 278000 | N80: 100 | O80: 3.02
A81: 10109 | B81: 2025-06-26 | C81: Oak Hill | D81: Single Family | E81: 4 | F81: 3.5 | G81: 2290 | H81: 8270 | I81: 2011 | J81: 2 | K81: Excellent | L81: 616000 | M81: 615000 | N81: 41 | O81: 2.48
A82: 10035 | B82: 2025-06-27 | C82: Riverside | D82: single-family | E82: 5 | F82: 4 | G82: 2540 | H82: 10050 | I82: 1993 | J82: 2 | K82: fair | L82: 515000 | M82: 510000 | N82: 62 | O82: 3.22
A83: 10011 | B83: 2025-06-29 | C83: Riverside | D83: Single Family | E83: 2 | F83: 2.5 | G83: 1330 | H83: 4520 | J83: 2 | K83: Good | L83: 312000 | M83: 285000 | N83: 42 | O83: 2.89
A84: 10234 | B84: 2025-07-03 | C84: Maple Heights | D84: Single Family | E84: 3 | F84: 1.5 | G84: 1650 | H84: 5030 | I84: 2007 | J84: 2 | K84: excellent | L84: 412000 | M84: 396000 | N84: 60 | O84: 2.9
A85: 10176 | B85: 2025-07-03 | C85: Oak Hill | D85: Townhouse | E85: 3 | F85: 2.5 | G85: 1920 | H85: 2530 | I85: 2013 | J85: 3 | K85: good | L85: 530000 | M85: 509000 | N85: 24 | O85: 2.43
A86: 10175 | B86: 2025-07-06 | C86: Oak Hl. | D86: single fam | E86: 3 | F86: 1.5 | G86: 1790 | H86: 7930 | I86: 1979 | J86: 2 | K86: Poor | L86: 397000 | M86: 386000 | N86: 59 | O86: 3.23
A87: 10162 | B87: 2025-07-07 | C87: Cedar Park | D87: Townhouse | E87: 3 | F87: 2 | G87: 1750 | H87: 1580 | I87: 2018 | J87: 1 | K87: Fair | L87: 252000 | M87: 232000 | N87: 58 | O87: 3.05
A88: 10047 | B88: 2025-07-10 | C88: Riverside | D88: Condo | E88: 1 | F88: 2 | G88: 520 | H88: 0 | I88: 1992 | J88: 0 | K88: Good | L88: 123000 | M88: 119000 | N88: 51
A89: 10111 | B89: 2025-07-11 | C89: Riverside | D89: Condo | E89: 2 | G89: 1310 | H89: 0 | J89: 0 | K89: Good | L89: 273000 | M89: 263000 | N89: 36 | O89: 2.92
A90: 10168 | B90: 2025-07-14 | C90: Downtown | D90: Townhouse | E90: 3 | F90: 3.5 | G90: 2010 | H90: 2420 | I90: 1984 | J90: 1 | K90: unknown | L90: 528000 | M90: 501000 | N90: 67 | O90: 2.48
A91: 10208 | B91: 2025-07-16 | C91: Maple Heights. | D91: Single family | E91: 3 | F91: 3 | G91: 1740 | H91: 7320 | I91: 1970 | J91: 0 | K91: Excellent | L91: 381000 | M91: 346000 | N91: 67 | O91: 3.22
A92: 10006 | B92: 2025-07-18 | C92: Cedar Park | D92: Townhouse | E92: 3 | F92: 2.5 | G92: 1750 | H92: 2320 | I92: 1989 | J92: 0 | K92: Excellent | L92: 272000 | M92: 259000 | O92: 2.94
A93: 10013 | B93: 2025-07-20 | C93: Maple Heights | D93: Single family | E93: 3 | F93: 2 | G93: 1740 | H93: 3960 | I93: 1968 | J93: 2 | K93: Fair | L93: 303000 | M93: 306000 | N93: 41 | O93: 3.05
A94: 10189 | B94: 2025-07-24 | D94: Townhouse | E94: 2 | F94: 1.5 | G94: 1280 | H94: 2060 | I94: 2024 | J94: 2 | K94: Good | L94: 365000 | M94: 365000 | N94: 35 | O94: 3.07
A95: 10242 | B95: 2025-07-25 | C95: DOWNTOWN | D95: Condo | E95: 2 | F95: 2 | G95: 1230 | H95: 0 | I95: 1965 | J95: 1 | K95: Fair | L95: 309000 | M95: 286000 | N95: 82 | O95: 2.41
A96: 10248 | B96: 2025-07-28 | C96: Riverside | D96: TH | E96: 2 | F96: 1 | G96: 1350 | H96: 2720 | I96: 2015 | J96: 2 | K96: Good | L96: 311000 | M96: 295000 | N96: 87 | O96: 2.52
A97: 10146 | B97: 2025-07-30 | C97: Riverside | D97: Single Family | E97: 3 | F97: 2 | G97: 1970 | H97: 7310 | I97: 2024 | J97: 1 | K97: Fair | L97: 437000 | M97: 429000 | N97: 74
A98: 10076 | B98: 2025-07-31 | C98: Riverside | D98: townhouse | E98: 3 | F98: 3 | G98: 1580 | H98: 2130 | I98: 1940 | L98: 333000 | M98: 317000 | N98: 42 | O98: 2.78
A99: 10020 | B99: 2025-08-01 | C99: Maple Heights | D99: SFH | E99: 3 | F99: 2.5 | G99: 2030 | H99: 6600 | I99: 2019 | J99: 2 | K99: Good | L99: 464000 | M99: 447000 | N99: 98 | O99: 2.71
A100: 10171 | B100: 2025-08-01 | C100: riverside | D100: Townhouse | E100: 3 | F100: 3 | G100: 1530 | H100: 2360 | I100: 1992 | J100: 1 | K100: Excellent | L100: 348000 | M100: 340000 | N100: 31 | O100: 2.67
...
